Workbook

Sheet Usuarios
A1: ID | B1: Nombre | C1: Primer Apellido | D1: Segundo Apellido | E1: RUT | F1: Telefono | G1: Email | H1: Direccion | I1: Fecha Incorporacion | J1: Integrantes Hogar | K1: Estado | L1: Observaciones
A2: 1 | B2: Nancy | C2: Zuñiga | D2: Villarroel | E2: 9797809-3 | F2: 988584908 | H2: Pasaje Las Rosas #309 | K2: Activo
A3: 2 | B3: Gabriel | C3: Barria | D3: Zuñiga | E3: 19175724-6 | F3: 973550328 | H3: Pasaje los Claveles S/N | J3: 3 | K3: Activo
A4: 3 | B4: Gino | C4: Reyes | E4: 13062892-3 | F4: 976087017 | K4: Activo
A5: 4 | B5: Cristian | C5: Oyarzo | E5: 18910875-3 | F5: 988515396 | K5: Activo
A6: 5 | B6: Marisol | C6: Castro | F6: 976006959 | K6: Activo
A7: 6 | B7: Mauricio | C7: Muñoz | F7: 968619494 | K7: Activo
A8: 7 | B8: Marcelo | C8: Millanao | F8: 956400315 | K8: Activo
A9: 8 | B9: Gabriel | C9: Farias | F9: 995153542 | K9: Activo
A10: 9 | B10: Maria | C10: Marin | F10: 968619494 | K10: Activo
A11: 10 | B11: David | C11: Cartes | F11: 957124563 | K11: Activo
A12: 11 | B12: Miguel | C12: Ñanco | F12: 987177967 | K12: Activo
A13: 12 | B13: Pedro | C13: Contreras | F13: 989964614 | K13: Inactivo
A14: 13 | B14: Carlos | C14: Gamin | F14: 958180175 | K14: Activo
A15: 14 | B15: Ramona | C15: Mansilla | K15: Activo
A16: 15 | B16: Sandra | C16: Mancilla | D16: Merino | K16: Activo
A17: 16 | B17: Carlos | C17: Agüero | F17: 968603541 | K17: Activo
A18: 17 | B18: Joaquin | C18: Claramunt | F18: 986597010 | K18: Activo
A19: 18 | B19: Nelson | C19: Mansilla | F19: 965202900 | K19: Activo
A20: 19 | B20: Eduardo | C20: Chavez | F20: 976201354 | K20: Activo
A21: 20 | B21: Juan | C21: Chavez | F21: 976201354 | K21: Activo
A22: 21 | B22: Luis | C22: Martinez | K22: Activo
A23: 22 | B23: Yuri | C23: Millaquen | F23: 976087017 | K23: Activo
A24: 23 | B24: Carlos | C24: Nahuelpan | F24: 992904575 | K24: Activo
A25: 24 | B25: Maria | C25: Velasquez | D25: Miranda | F25: 976065837 | K25: Activo
A26: 25 | B26: Inés | C26: Velasquez | K26: Activo
A27: 26 | B27: Guido | C27: Quintuy | F27: 997031231 | H27: Frutería | K27: Inactivo
A28: 27 | B28: Pedro | C28: Almonacid | K28: Activo
A29: 28 | B29: Nora | C29: Ñanco | K29: Activo
A30: 29 | B30: Miriam | C30: Alvarado | F30: 998962803 | K30: Activo
A31: 30 | B31: Luz | C31: Maldonado | F31: 965913448 | K31: Activo
A32: 31 | B32: Patricia | C32: Carcamo | D32: Gonzales | F32: 996147837 | K32: Activo
A33: 32 | B33: Natividad | C33: Soto | F33: 985961781 | K33: Activo
A34: 33 | B34: Maria Oliva | C34: Soto | D34: Almonacid | F34: 994727047 | K34: Activo
A35: 34 | B35: Vanesa | C35: Aguilar | F35: 977891512 | K35: Activo
A36: 35 | B36: José | C36: Paredes | K36: Activo
A37: 36 | B37: Danilo | C37: Soto | D37: Soto | K37: Activo
A38: 37 | B38: Patricio | C38: Alvarez | D38: Mancilla | K38: Activo
A39: 38 | B39: Norma | C39: Sanchez | F39: 979958848 | K39: Activo
A40: 39 | B40: Gloria | C40: Alvarez | K40: Activo
A41: 40 | B41: Gloria | C41: Levil | F41: 986531665 | K41: Activo
A42: 41 | B42: Astrid | C42: Gomez | F42: 968197477 | K42: Activo
A43: 42 | B43: Leo | C43: Soto | K43: Activo
A44: 43 | B44: Ramon | C44: Maldonado | K44: Activo
A45: 44 | B45: María Sonia | C45: Quintui | K45: Activo
A46: 45 | B46: Monica | C46: Cuello | F46: 983607418 | K46: Activo
A47: 46 | B47: Mauricio | C47: Muñoz taller | F47: 968619494 | K47: Activo
A48: 47 | B48: Pablo | C48: Contreras | F48: 936973078 | K48: Activo
A49: 48 | B49: Luis Vicente | C49: Mondaca | D49: Muñoz | F49: 966470486 | K49: Activo
A50: 49 | B50: Rosa | C50: Nuñez | K50: Activo
A51: 50 | B51: Gloria Isamar | C51: Velasquez | D51: Almonacid | E51: 19.175.786-6 | F51: 967897918 | H51: Segundo pasaje, colindante con David Cartes | K51: Activo
A52: 51 | B52: Maria | C52: Manquian | F52: 973351014 | H52: Segundo pasaje, colindante con David Cartes | K52: Activo
A53: 52 | B53: Esteban | C53: Oyarzo | D53: Levil | F53: 976368582 | K53: Activo
A54: 53 | B54: Nicolas Andres | C54: Cardenas | D54: Bustamante | F54: 953848425 | H54: Sitio al lado de Nancy Zuñiga | K54: Activo
A55: 54 | B55: Rosa | C55: Mancilla | F55: 931428027 | H55: Camino principal, sector playa | K55: Activo
A56: 55 | B56: Guido | C56: Quintuy - Sitio vacío | K56: Activo
A57: 56 | B57: Mario | C57: Velasquez | F57: 933288507 | K57: Activo
A58: 57 | B58: Lishby | C58: Fuentes | D58: Diaz | F58: 56937015930 | K58: Activo

Sheet Plantilla
A1: ID | B1: Nombre | C1: Lectura_Anterior | D1: Lectura_Actual | E1: Consumo_m3 | F1: Tarifa_m3 | G1: Subtotal_Consumo | H1: Cargo_Fijo | I1: Total_Factura | J1: Fecha_Lectura | K1: Lectura Tomada | L1: Estado_Pago | M1: Monto_Pagado | N1: Fecha_Pago | O1: Forma_Pago | P1: Saldo_Pendiente | Q1: comprobante_link
A2: 41 | B2: =Usuarios!B42 & " " & Usuarios!C42 & " " & Usuarios!D42 -> Astrid Gomez | C2: =INDEX(INDIRECT("'" & TEXT(EDATE(J2,-2),"mm-yyyy") & "'!D:D"), MATCH(A2,INDIRECT("'" & TEXT(EDATE(J2,-2),"mm-yyyy") & "'!A:A"),0)) -> #NUM! | E2: =D2-C2 -> #NUM! | F2: 1182.6 | G2: =E2*F2 -> #NUM! | H2: 5000 | I2: =E2*F2+H2 -> #NUM! | K2: NO | L2: PENDIENTE | M2: =IF(L2="Pagado", I2, 0) -> 0 | P2: =IF(L2="NO APLICA",0, (I2-M2)) -> #NUM!
A3: 16 | B3: =Usuarios!B17 & " " & Usuarios!C17 & " " & Usuarios!D17 -> Carlos Agüero | C3: =INDEX(INDIRECT("'" & TEXT(EDATE(J3,-2),"mm-yyyy") & "'!D:D"), MATCH(A3,INDIRECT("'" & TEXT(EDATE(J3,-2),"mm-yyyy") & "'!A:A"),0)) -> #NUM! | E3: =D3-C3 -> #NUM! | F3: 1182.6 | G3: =E3*F3 -> #NUM! | H3: 5000 | I3: =E3*F3+H3 -> #NUM! | K3: NO | L3: PENDIENTE | M3: =IF(L3="Pagado", I3, 0) -> 0 | P3: =IF(L3="NO APLICA",0, (I3-M3)) -> #NUM!
A4: 13 | B4: =Usuarios!B14 & " " & Usuarios!C14 & " " & Usuarios!D14 -> Carlos Gamin | C4: =INDEX(INDIRECT("'" & TEXT(EDATE(J4,-2),"mm-yyyy") & "'!D:D"), MATCH(A4,INDIRECT("'" & TEXT(EDATE(J4,-2),"mm-yyyy") & "'!A:A"),0)) -> #NUM! | E4: =D4-C4 -> #NUM! | F4: 1182.6 | G4: =E4*F4 -> #NUM! | H4: 5000 | I4: =E4*F4+H4 -> #NUM! | K4: NO | L4: PENDIENTE | M4: =IF(L4="Pagado", I4, 0) -> 0 | P4: =IF(L4="NO APLICA",0, (I4-M4)) -> #NUM!
A5: 23 | B5: =Usuarios!B24 & " " & Usuarios!C24 & " " & Usuarios!D24 -> Carlos Nahuelpan | C5: =INDEX(INDIRECT("'" & TEXT(EDATE(J5,-2),"mm-yyyy") & "'!D:D"), MATCH(A5,INDIRECT("'" & TEXT(EDATE(J5,-2),"mm-yyyy") & "'!A:A"),0)) -> #NUM! | E5: =D5-C5 -> #NUM! | F5: 1182.6 | G5: =E5*F5 -> #NUM! | H5: 5000 | I5: =E5*F5+H5 -> #NUM! | K5: NO | L5: PENDIENTE | M5: =IF(L5="Pagado", I5, 0) -> 0 | P5: =IF(L5="NO APLICA",0, (I5-M5)) -> #NUM!
A6: 4 | B6: =Usuarios!B5 & " " & Usuarios!C5 & " " & Usuarios!D5 -> Cristian Oyarzo | C6: =INDEX(INDIRECT("'" & TEXT(EDATE(J6,-2),"mm-yyyy") & "'!D:D"), MATCH(A6,INDIRECT("'" & TEXT(EDATE(J6,-2),"mm-yyyy") & "'!A:A"),0)) -> #NUM! | E6: =D6-C6 -> #NUM! | F6: 1182.6 | G6: =E6*F6 -> #NUM! | H6: 5000 | I6: =E6*F6+H6 -> #NUM! | K6: NO | L6: PENDIENTE | M6: =IF(L6="Pagado", I6, 0) -> 0 | P6: =IF(L6="NO APLICA",0, (I6-M6)) -> #NUM!
A7: 36 | B7: =Usuarios!B37 & " " & Usuarios!C37 & " " & Usuarios!D37 -> Danilo Soto Soto | C7: =INDEX(INDIRECT("'" & TEXT(EDATE(J7,-2),"mm-yyyy") & "'!D:D"), MATCH(A7,INDIRECT("'" & TEXT(EDATE(J7,-2),"mm-yyyy") & "'!A:A"),0)) -> #NUM! | E7: =D7-C7 -> #NUM! | F7: 1182.6 | G7: =E7*F7 -> #NUM! | H7: 5000 | I7: =E7*F7+H7 -> #NUM! | K7: NO | L7: PENDIENTE | M7: =IF(L7="Pagado", I7, 0) -> 0 | P7: =IF(L7="NO APLICA",0, (I7-M7)) -> #NUM!
A8: 10 | B8: =Usuarios!B11 & " " & Usuarios!C11 & " " & Usuarios!D11 -> David Cartes | C8: =INDEX(INDIRECT("'" & TEXT(EDATE(J8,-2),"mm-yyyy") & "'!D:D"), MATCH(A8,INDIRECT("'" & TEXT(EDATE(J8,-2),"mm-yyyy") & "'!A:A"),0)) -> #NUM! | E8: =D8-C8 -> #NUM! | F8: 1182.6 | G8: =E8*F8 -> #NUM! | H8: 5000 | I8: =E8*F8+H8 -> #NUM! | K8: NO | L8: PENDIENTE | M8: =IF(L8="Pagado", I8, 0) -> 0 | P8: =IF(L8="NO APLICA",0, (I8-M8)) -> #NUM!
A9: 19 | B9: =Usuarios!B20 & " " & Usuarios!C20 & " " & Usuarios!D20 -> Eduardo Chavez | C9: =INDEX(INDIRECT("'" & TEXT(EDATE(J9,-2),"mm-yyyy") & "'!D:D"), MATCH(A9,INDIRECT("'" & TEXT(EDATE(J9,-2),"mm-yyyy") & "'!A:A"),0)) -> #NUM! | E9: =D9-C9 -> #NUM! | F9: 1182.6 | G9: =E9*F9 -> #NUM! | H9: 5000 | I9: =E9*F9+H9 -> #NUM! | K9: NO | L9: PENDIENTE | M9: =IF(L9="Pagado", I9, 0) -> 0 | P9: =IF(L9="NO APLICA",0, (I9-M9)) -> #NUM!
A10: 52 | B10: =Usuarios!B53 & " " & Usuarios!C53 & " " & Usuarios!D53 -> Esteban Oyarzo Levil | C10: =INDEX(INDIRECT("'" & TEXT(EDATE(J10,-2),"mm-yyyy") & "'!D:D"), MATCH(A10,INDIRECT("'" & TEXT(EDATE(J10,-2),"mm-yyyy") & "'!A:A"),0)) -> #NUM! | E10: =D10-C10 -> #NUM! | F10: 1182.6 | G10: =E10*F10 -> #NUM! | H10: 5000 | I10: =E10*F10+H10 -> #NUM! | K10: NO | L10: PENDIENTE | M10: =IF(L10="Pagado", I10, 0) -> 0 | P10: =IF(L10="NO APLICA",0, (I10-M10)) -> #NUM!
A11: 8 | B11: =Usuarios!B9 & " " & Usuarios!C9 & " " & Usuarios!D9 -> Gabriel Farias | C11: =INDEX(INDIRECT("'" & TEXT(EDATE(J11,-2),"mm-yyyy") & "'!D:D"), MATCH(A11,INDIRECT("'" & TEXT(EDATE(J11,-2),"mm-yyyy") & "'!A:A"),0)) -> #NUM! | E11: =D11-C11 -> #NUM! | F11: 1182.6 | G11: =E11*F11 -> #NUM! | H11: 5000 | I11: =E11*F11+H11 -> #NUM! | K11: NO | L11: PENDIENTE | M11: =IF(L11="Pagado", I11, 0) -> 0 | P11: =IF(L11="NO APLICA",0, (I11-M11)) -> #NUM!
A12: 2 | B12: =Usuarios!B3 & " " & Usuarios!C3 & " " & Usuarios!D3 -> Gabriel Barria Zuñiga | C12: =INDEX(INDIRECT("'" & TEXT(EDATE(J12,-2),"mm-yyyy") & "'!D:D"), MATCH(A12,INDIRECT("'" & TEXT(EDATE(J12,-2),"mm-yyyy") & "'!A:A"),0)) -> #NUM! | E12: =D12-C12 -> #NUM! | F12: 1182.6 | G12: =E12*F12 -> #NUM! | H12: 5000 | I12: =E12*F12+H12 -> #NUM! | K12: NO | L12: PENDIENTE | M12: =IF(L12="Pagado", I12, 0) -> 0 | P12: =IF(L12="NO APLICA",0, (I12-M12)) -> #NUM!
A13: 3 | B13: =Usuarios!B4 & " " & Usuarios!C4 & " " & Usuarios!D4 -> Gino Reyes | C13: =INDEX(INDIRECT("'" & TEXT(EDATE(J13,-2),"mm-yyyy") & "'!D:D"), MATCH(A13,INDIRECT("'" & TEXT(EDATE(J13,-2),"mm-yyyy") & "'!A:A"),0)) -> #NUM! | E13: =D13-C13 -> #NUM! | F13: 1182.6 | G13: =E13*F13 -> #NUM! | H13: 5000 | I13: =E13*F13+H13 -> #NUM! | K13: NO | L13: PENDIENTE | M13: =IF(L13="Pagado", I13, 0) -> 0 | P13: =IF(L13="NO APLICA",0, (I13-M13)) -> #NUM!
A14: 39 | B14: =Usuarios!B40 & " " & Usuarios!C40 & " " & Usuarios!D40 -> Gloria Alvarez | C14: =INDEX(INDIRECT("'" & TEXT(EDATE(J14,-2),"mm-yyyy") & "'!D:D"), MATCH(A14,INDIRECT("'" & TEXT(EDATE(J14,-2),"mm-yyyy") & "'!A:A"),0)) -> #NUM! | E14: =D14-C14 -> #NUM! | F14: 1182.6 | G14: =E14*F14 -> #NUM! | H14: 5000 | I14: =E14*F14+H14 -> #NUM! | K14: NO | L14: PENDIENTE | M14: =IF(L14="Pagado", I14, 0) -> 0 | P14: =IF(L14="NO APLICA",0, (I14-M14)) -> #NUM!
A15: 40 | B15: =Usuarios!B41 & " " & Usuarios!C41 & " " & Usuarios!D41 -> Gloria Levil | C15: =INDEX(INDIRECT("'" & TEXT(EDATE(J15,-2),"mm-yyyy") & "'!D:D"), MATCH(A15,INDIRECT("'" & TEXT(EDATE(J15,-2),"mm-yyyy") & "'!A:A"),0)) -> #NUM! | E15: =D15-C15 -> #NUM! | F15: 1182.6 | G15: =E15*F15 -> #NUM! | H15: 5000 | I15: =E15*F15+H15 -> #NUM! | K15: NO | L15: PENDIENTE | M15: =IF(L15="Pagado", I15, 0) -> 0 | P15: =IF(L15="NO APLICA",0, (I15-M15)) -> #NUM!
A16: 50 | B16: =Usuarios!B51 & " " & Usuarios!C51 & " " & Usuarios!D51 -> Gloria Isamar Velasquez Almonacid | C16: =INDEX(INDIRECT("'" & TEXT(EDATE(J16,-2),"mm-yyyy") & "'!D:D"), MATCH(A16,INDIRECT("'" & TEXT(EDATE(J16,-2),"mm-yyyy") & "'!A:A"),0)) -> #NUM! | E16: =D16-C16 -> #NUM! | F16: 1182.6 | G16: =E16*F16 -> #NUM! | H16: 5000 | I16: =E16*F16+H16 -> #NUM! | K16: NO | L16: PENDIENTE | M16: =IF(L16="Pagado", I16, 0) -> 0 | P16: =IF(L16="NO APLICA",0, (I16-M16)) -> #NUM!
A17: 26 | B17: =Usuarios!B27 & " " & Usuarios!C27 & " " & Usuarios!D27 -> Guido Quintuy | C17: =INDEX(INDIRECT("'" & TEXT(EDATE(J17,-2),"mm-yyyy") & "'!D:D"), MATCH(A17,INDIRECT("'" & TEXT(EDATE(J17,-2),"mm-yyyy") & "'!A:A"),0)) -> #NUM! | K17: NO | L17: PENDIENTE
A18: 55 | B18: =Usuarios!B56 & " " & Usuarios!C56 & " " & Usuarios!D56 -> Guido Quintuy - Sitio vacío | C18: =INDEX(INDIRECT("'" & TEXT(EDATE(J18,-2),"mm-yyyy") & "'!D:D"), MATCH(A18,INDIRECT("'" & TEXT(EDATE(J18,-2),"mm-yyyy") & "'!A:A"),0)) -> #NUM! | E18: =D18-C18 -> #NUM! | F18: 1182.6 | G18: =E18*F18 -> #NUM! | H18: 5000 | I18: =E18*F18+H18 -> #NUM! | K18: NO | L18: PENDIENTE | M18: =IF(L18="Pagado", I18, 0) -> 0 | P18: =IF(L18="NO APLICA",0, (I18-M18)) -> #NUM!
A19: 25 | B19: =Usuarios!B26 & " " & Usuarios!C26 & " " & Usuarios!D26 -> Inés Velasquez | C19: =INDEX(INDIRECT("'" & TEXT(EDATE(J19,-2),"mm-yyyy") & "'!D:D"), MATCH(A19,INDIRECT("'" & TEXT(EDATE(J19,-2),"mm-yyyy") & "'!A:A"),0)) -> #NUM! | E19: =D19-C19 -> #NUM! | F19: 1182.6 | G19: =E19*F19 -> #NUM! | H19: 5000 | I19: =E19*F19+H19 -> #NUM! | K19: NO | L19: PENDIENTE | M19: =IF(L19="Pagado", I19, 0) -> 0 | P19: =IF(L19="NO APLICA",0, (I19-M19)) -> #NUM!
A20: 17 | B20: =Usuarios!B18 & " " & Usuarios!C18 & " " & Usuarios!D18 -> Joaquin Claramunt | C20: =INDEX(INDIRECT("'" & TEXT(EDATE(J20,-2),"mm-yyyy") & "'!D:D"), MATCH(A20,INDIRECT("'" & TEXT(EDATE(J20,-2),"mm-yyyy") & "'!A:A"),0)) -> #NUM! | E20: =D20-C20 -> #NUM! | F20: 1182.6 | G20: =E20*F20 -> #NUM! | H20: 5000 | I20: =E20*F20+H20 -> #NUM! | K20: NO | L20: PENDIENTE | M20: =IF(L20="Pagado", I20, 0) -> 0 | P20: =IF(L20="NO APLICA",0, (I20-M20)) -> #NUM!
A21: 35 | B21: =Usuarios!B36 & " " & Usuarios!C36 & " " & Usuarios!D36 -> José Paredes | C21: =INDEX(INDIRECT("'" & TEXT(EDATE(J21,-2),"mm-yyyy") & "'!D:D"), MATCH(A21,INDIRECT("'" & TEXT(EDATE(J21,-2),"mm-yyyy") & "'!A:A"),0)) -> #NUM! | E21: =D21-C21 -> #NUM! | F21: 1182.6 | G21: =E21*F21 -> #NUM! | H21: 5000 | I21: =E21*F21+H21 -> #NUM! | K21: NO | L21: PENDIENTE | M21: =IF(L21="Pagado", I21, 0) -> 0 | P21: =IF(L21="NO APLICA",0, (I21-M21)) -> #NUM!
A22: 20 | B22: =Usuarios!B21 & " " & Usuarios!C21 & " " & Usuarios!D21 -> Juan Chavez | C22: =INDEX(INDIRECT("'" & TEXT(EDATE(J22,-2),"mm-yyyy") & "'!D:D"), MATCH(A22,INDIRECT("'" & TEXT(EDATE(J22,-2),"mm-yyyy") & "'!A:A"),0)) -> #NUM! | E22: =D22-C22 -> #NUM! | F22: 1182.6 | G22: =E22*F22 -> #NUM! | H22: 5000 | I22: =E22*F22+H22 -> #NUM! | K22: NO | L22: PENDIENTE | M22: =IF(L22="Pagado", I22, 0) -> 0 | P22: =IF(L22="NO APLICA",0, (I22-M22)) -> #NUM!
A23: 42 | B23: =Usuarios!B43 & " " & Usuarios!C43 & " " & Usuarios!D43 -> Leo Soto | C23: =INDEX(INDIRECT("'" & TEXT(EDATE(J23,-2),"mm-yyyy") & "'!D:D"), MATCH(A23,INDIRECT("'" & TEXT(EDATE(J23,-2),"mm-yyyy") & "'!A:A"),0)) -> #NUM! | E23: =D23-C23 -> #NUM! | F23: 1182.6 | G23: =E23*F23 -> #NUM! | H23: 5000 | I23: =E23*F23+H23 -> #NUM! | K23: NO | L23: PENDIENTE | M23: =IF(L23="Pagado", I23, 0) -> 0 | P23: =IF(L23="NO APLICA",0, (I23-M23)) -> #NUM!
A24: 57 | B24: =Usuarios!B58 & " " & Usuarios!C58 & " " & Usuarios!D58 -> Lishby Fuentes Diaz | C24: =INDEX(INDIRECT("'" & TEXT(EDATE(J24,-2),"mm-yyyy") & "'!D:D"), MATCH(A24,INDIRECT("'" & TEXT(EDATE(J24,-2),"mm-yyyy") & "'!A:A"),0)) -> #NUM! | E24: =D24-C24 -> #NUM! | F24: 1182.6 | G24: =E24*F24 -> #NUM! | H24: 5000 | I24: =E24*F24+H24 -> #NUM! | K24: NO | L24: PENDIENTE | M24: =IF(L24="Pagado", I24, 0) -> 0 | P24: =IF(L24="NO APLICA",0, (I24-M24)) -> #NUM!
A25: 48 | B25: =Usuarios!B49 & " " & Usuarios!C49 & " " & Usuarios!D49 -> Luis Vicente Mondaca Muñoz | C25: =INDEX(INDIRECT("'" & TEXT(EDATE(J25,-2),"mm-yyyy") & "'!D:D"), MATCH(A25,INDIRECT("'" & TEXT(EDATE(J25,-2),"mm-yyyy") & "'!A:A"),0)) -> #NUM! | E25: =D25-C25 -> #NUM! | F25: 1182.6 | G25: =E25*F25 -> #NUM! | H25: 5000 | I25: =E25*F25+H25 -> #NUM! | K25: NO | L25: PENDIENTE | M25: =IF(L25="Pagado", I25, 0) -> 0 | P25: =IF(L25="NO APLICA",0, (I25-M25)) -> #NUM!
A26: 30 | B26: =Usuarios!B31 & " " & Usuarios!C31 & " " & Usuarios!D31 -> Luz Maldonado | C26: =INDEX(INDIRECT("'" & TEXT(EDATE(J26,-2),"mm-yyyy") & "'!D:D"), MATCH(A26,INDIRECT("'" & TEXT(EDATE(J26,-2),"mm-yyyy") & "'!A:A"),0)) -> #NUM! | E26: =D26-C26 -> #NUM! | F26: 1182.6 | G26: =E26*F26 -> #NUM! | H26: 5000 | I26: =E26*F26+H26 -> #NUM! | K26: NO | L26: PENDIENTE | M26: =IF(L26="Pagado", I26, 0) -> 0 | P26: =IF(L26="NO APLICA",0, (I26-M26)) -> #NUM!
A27: 7 | B27: =Usuarios!B8 & " " & Usuarios!C8 & " " & Usuarios!D8 -> Marcelo Millanao | C27: =INDEX(INDIRECT("'" & TEXT(EDATE(J27,-2),"mm-yyyy") & "'!D:D"), MATCH(A27,INDIRECT("'" & TEXT(EDATE(J27,-2),"mm-yyyy") & "'!A:A"),0)) -> #NUM! | E27: =D27-C27 -> #NUM! | F27: 1182.6 | G27: =E27*F27 -> #NUM! | H27: 5000 | I27: =E27*F27+H27 -> #NUM! | K27: NO | L27: PENDIENTE | M27: =IF(L27="Pagado", I27, 0) -> 0 | P27: =IF(L27="NO APLICA",0, (I27-M27)) -> #NUM!
A28: 51 | B28: =Usuarios!B52 & " " & Usuarios!C52 & " " & Usuarios!D52 -> Maria Manquian | C28: =INDEX(INDIRECT("'" & TEXT(EDATE(J28,-2),"mm-yyyy") & "'!D:D"), MATCH(A28,INDIRECT("'" & TEXT(EDATE(J28,-2),"mm-yyyy") & "'!A:A"),0)) -> #NUM! | E28: =D28-C28 -> #NUM! | F28: 1182.6 | G28: =E28*F28 -> #NUM! | H28: 5000 | I28: =E28*F28+H28 -> #NUM! | K28: NO | L28: PENDIENTE | M28: =IF(L28="Pagado", I28, 0) -> 0 | P28: =IF(L28="NO APLICA",0, (I28-M28)) -> #NUM!
A29: 9 | B29: =Usuarios!B10 & " " & Usuarios!C10 & " " & Usuarios!D10 -> Maria Marin | C29: =INDEX(INDIRECT("'" & TEXT(EDATE(J29,-2),"mm-yyyy") & "'!D:D"), MATCH(A29,INDIRECT("'" & TEXT(EDATE(J29,-2),"mm-yyyy") & "'!A:A"),0)) -> #NUM! | E29: =D29-C29 -> #NUM! | F29: 1182.6 | G29: =E29*F29 -> #NUM! | H29: 5000 | I29: =E29*F29+H29 -> #NUM! | K29: NO | L29: PENDIENTE | M29: =IF(L29="Pagado", I29, 0) -> 0 | P29: =IF(L29="NO APLICA",0, (I29-M29)) -> #NUM!
A30: 33 | B30: =Usuarios!B34 & " " & Usuarios!C34 & " " & Usuarios!D34 -> Maria Oliva Soto Almonacid | C30: =INDEX(INDIRECT("'" & TEXT(EDATE(J30,-2),"mm-yyyy") & "'!D:D"), MATCH(A30,INDIRECT("'" & TEXT(EDATE(J30,-2),"mm-yyyy") & "'!A:A"),0)) -> #NUM! | E30: =D30-C30 -> #NUM! | F30: 1182.6 | G30: =E30*F30 -> #NUM! | H30: 5000 | I30: =E30*F30+H30 -> #NUM! | K30: NO | L30: PENDIENTE | M30: =IF(L30="Pagado", I30, 0) -> 0 | P30: =IF(L30="NO APLICA",0, (I30-M30)) -> #NUM!
A31: 44 | B31: =Usuarios!B45 & " " & Usuarios!C45 & " " & Usuarios!D45 -> María Sonia Quintui | C31: =INDEX(INDIRECT("'" & TEXT(EDATE(J31,-2),"mm-yyyy") & "'!D:D"), MATCH(A31,INDIRECT("'" & TEXT(EDATE(J31,-2),"mm-yyyy") & "'!A:A"),0)) -> #NUM! | E31: =D31-C31 -> #NUM! | F31: 1182.6 | G31: =E31*F31 -> #NUM! | H31: 5000 | I31: =E31*F31+H31 -> #NUM! | K31: NO | L31: PENDIENTE | M31: =IF(L31="Pagado", I31, 0) -> 0 | P31: =IF(L31="NO APLICA",0, (I31-M31)) -> #NUM!
A32: 24 | B32: =Usuarios!B25 & " " & Usuarios!C25 & " " & Usuarios!D25 -> Maria Velasquez Miranda | C32: =INDEX(INDIRECT("'" & TEXT(EDATE(J32,-2),"mm-yyyy") & "'!D:D"), MATCH(A32,INDIRECT("'" & TEXT(EDATE(J32,-2),"mm-yyyy") & "'!A:A"),0)) -> #NUM! | E32: =D32-C32 -> #NUM! | F32: 1182.6 | G32: =E32*F32 -> #NUM! | H32: 5000 | I32: =E32*F32+H32 -> #NUM! | K32: NO | L32: PENDIENTE | M32: =IF(L32="Pagado", I32, 0) -> 0 | P32: =IF(L32="NO APLICA",0, (I32-M32)) -> #NUM!
A33: 56 | B33: =Usuarios!B57 & " " & Usuarios!C57 & " " & Usuarios!D57 -> Mario Velasquez | C33: =INDEX(INDIRECT("'" & TEXT(EDATE(J33,-2),"mm-yyyy") & "'!D:D"), MATCH(A33,INDIRECT("'" & TEXT(EDATE(J33,-2),"mm-yyyy") & "'!A:A"),0)) -> #NUM! | E33: =D33-C33 -> #NUM! | F33: 1182.6 | G33: =E33*F33 -> #NUM! | H33: 5000 | I33: =E33*F33+H33 -> #NUM! | K33: NO | L33: PENDIENTE | M33: =IF(L33="Pagado", I33, 0) -> 0 | P33: =IF(L33="NO APLICA",0, (I33-M33)) -> #NUM!
A34: 5 | B34: =Usuarios!B6 & " " & Usuarios!C6 & " " & Usuarios!D6 -> Marisol Castro | C34: =INDEX(INDIRECT("'" & TEXT(EDATE(J34,-2),"mm-yyyy") & "'!D:D"), MATCH(A34,INDIRECT("'" & TEXT(EDATE(J34,-2),"mm-yyyy") & "'!A:A"),0)) -> #NUM! | E34: =D34-C34 -> #NUM! | F34: 1182.6 | G34: =E34*F34 -> #NUM! | H34: 5000 | I34: =E34*F34+H34 -> #NUM! | K34: NO | L34: PENDIENTE | M34: =IF(L34="Pagado", I34, 0) -> 0 | P34: =IF(L34="NO APLICA",0, (I34-M34)) -> #NUM!
A35: 6 | B35: =Usuarios!B7 & " " & Usuarios!C7 & " " & Usuarios!D7 -> Mauricio Muñoz | C35: =INDEX(INDIRECT("'" & TEXT(EDATE(J35,-2),"mm-yyyy") & "'!D:D"), MATCH(A35,INDIRECT("'" & TEXT(EDATE(J35,-2),"mm-yyyy") & "'!A:A"),0)) -> #NUM! | E35: =D35-C35 -> #NUM! | F35: 1182.6 | G35: =E35*F35 -> #NUM! | H35: 5000 | I35: =E35*F35+H35 -> #NUM! | K35: NO | L35: PENDIENTE | M35: =IF(L35="Pagado", I35, 0) -> 0 | P35: =IF(L35="NO APLICA",0, (I35-M35)) -> #NUM!
A36: 46 | B36: =Usuarios!B47 & " " & Usuarios!C47 & " " & Usuarios!D47 -> Mauricio Muñoz taller | C36: =INDEX(INDIRECT("'" & TEXT(EDATE(J36,-2),"mm-yyyy") & "'!D:D"), MATCH(A36,INDIRECT("'" & TEXT(EDATE(J36,-2),"mm-yyyy") & "'!A:A"),0)) -> #NUM! | E36: =D36-C36 -> #NUM! | F36: 1182.6 | G36: =E36*F36 -> #NUM! | H36: 5000 | I36: =E36*F36+H36 -> #NUM! | K36: NO | L36: PENDIENTE | M36: =IF(L36="Pagado", I36, 0) -> 0 | P36: =IF(L36="NO APLICA",0, (I36-M36)) -> #NUM!
A37: 11 | B37: =Usuarios!B12 & " " & Usuarios!C12 & " " & Usuarios!D12 -> Miguel Ñanco | C37: =INDEX(INDIRECT("'" & TEXT(EDATE(J37,-2),"mm-yyyy") & "'!D:D"), MATCH(A37,INDIRECT("'" & TEXT(EDATE(J37,-2),"mm-yyyy") & "'!A:A"),0)) -> #NUM! | E37: =D37-C37 -> #NUM! | F37: 1182.6 | G37: =E37*F37 -> #NUM! | H37: 5000 | I37: =E37*F37+H37 -> #NUM! | K37: NO | L37: PENDIENTE | M37: =IF(L37="Pagado", I37, 0) -> 0 | P37: =IF(L37="NO APLICA",0, (I37-M37)) -> #NUM!
A38: 29 | B38: =Usuarios!B30 & " " & Usuarios!C30 & " " & Usuarios!D30 -> Miriam Alvarado | C38: =INDEX(INDIRECT("'" & TEXT(EDATE(J38,-2),"mm-yyyy") & "'!D:D"), MATCH(A38,INDIRECT("'" & TEXT(EDATE(J38,-2),"mm-yyyy") & "'!A:A"),0)) -> #NUM! | E38: =D38-C38 -> #NUM! | F38: 1182.6 | G38: =E38*F38 -> #NUM! | H38: 5000 | I38: =E38*F38+H38 -> #NUM! | K38: NO | L38: PENDIENTE | M38: =IF(L38="Pagado", I38, 0) -> 0 | P38: =IF(L38="NO APLICA",0, (I38-M38)) -> #NUM!
A39: 45 | B39: =Usuarios!B46 & " " & Usuarios!C46 & " " & Usuarios!D46 -> Monica Cuello | C39: =INDEX(INDIRECT("'" & TEXT(EDATE(J39,-2),"mm-yyyy") & "'!D:D"), MATCH(A39,INDIRECT("'" & TEXT(EDATE(J39,-2),"mm-yyyy") & "'!A:A"),0)) -> #NUM! | E39: =D39-C39 -> #NUM! | F39: 1182.6 | G39: =E39*F39 -> #NUM! | H39: 5000 | I39: =E39*F39+H39 -> #NUM! | K39: NO | L39: PENDIENTE | M39: =IF(L39="Pagado", I39, 0) -> 0 | P39: =IF(L39="NO APLICA",0, (I39-M39)) -> #NUM!
A40: 1 | B40: =Usuarios!B2 & " " & Usuarios!C2 & " " & Usuarios!D2 -> Nancy Zuñiga Villarroel | C40: =INDEX(INDIRECT("'" & TEXT(EDATE(J40,-2),"mm-yyyy") & "'!D:D"), MATCH(A40,INDIRECT("'" & TEXT(EDATE(J40,-2),"mm-yyyy") & "'!A:A"),0)) -> #NUM! | E40: =D40-C40 -> #NUM! | F40: 1182.6 | G40: =E40*F40 -> #NUM! | H40: 5000 | I40: =E40*F40+H40 -> #NUM! | K40: NO | L40: PENDIENTE | M40: =IF(L40="Pagado", I40, 0) -> 0 | P40: =IF(L40="NO APLICA",0, (I40-M40)) -> #NUM!
A41: 32 | B41: =Usuarios!B33 & " " & Usuarios!C33 & " " & Usuarios!D33 -> Natividad Soto | C41: =INDEX(INDIRECT("'" & TEXT(EDATE(J41,-2),"mm-yyyy") & "'!D:D"), MATCH(A41,INDIRECT("'" & TEXT(EDATE(J41,-2),"mm-yyyy") & "'!A:A"),0)) -> #NUM! | E41: =D41-C41 -> #NUM! | F41: 1182.6 | G41: =E41*F41 -> #NUM! | H41: 5000 | I41: =E41*F41+H41 -> #NUM! | K41: NO | L41: PENDIENTE | M41: 0 | P41: =IF(L41="NO APLICA",0, (I41-M41)) -> #NUM!
A42: 18 | B42: =Usuarios!B19 & " " & Usuarios!C19 & " " & Usuarios!D19 -> Nelson Mansilla | C42: =INDEX(INDIRECT("'" & TEXT(EDATE(J42,-2),"mm-yyyy") & "'!D:D"), MATCH(A42,INDIRECT("'" & TEXT(EDATE(J42,-2),"mm-yyyy") & "'!A:A"),0)) -> #NUM! | E42: =D42-C42 -> #NUM! | F42: 1182.6 | G42: =E42*F42 -> #NUM! | H42: 5000 | I42: =E42*F42+H42 -> #NUM! | K42: NO | L42: PENDIENTE | M42: =IF(L42="Pagado", I42, 0) -> 0 | P42: =IF(L42="NO APLICA",0, (I42-M42)) -> #NUM!
A43: 53 | B43: =Usuarios!B54 & " " & Usuarios!C54 & " " & Usuarios!D54 -> Nicolas Andres Cardenas Bustamante | C43: =INDEX(INDIRECT("'" & TEXT(EDATE(J43,-2),"mm-yyyy") & "'!D:D"), MATCH(A43,INDIRECT("'" & TEXT(EDATE(J43,-2),"mm-yyyy") & "'!A:A"),0)) -> #NUM! | E43: =D43-C43 -> #NUM! | F43: 1182.6 | G43: =E43*F43 -> #NUM! | H43: 5000 | I43: =E43*F43+H43 -> #NUM! | K43: NO | L43: PENDIENTE | M43: =IF(L43="Pagado", I43, 0) -> 0 | P43: =IF(L43="NO APLICA",0, (I43-M43)) -> #NUM!
A44: 28 | B44: =Usuarios!B29 & " " & Usuarios!C29 & " " & Usuarios!D29 -> Nora Ñanco | C44: =INDEX(INDIRECT("'" & TEXT(EDATE(J44,-2),"mm-yyyy") & "'!D:D"), MATCH(A44,INDIRECT("'" & TEXT(EDATE(J44,-2),"mm-yyyy") & "'!A:A"),0)) -> #NUM! | E44: =D44-C44 -> #NUM! | F44: 1182.6 | G44: =E44*F44 -> #NUM! | H44: 5000 | I44: =E44*F44+H44 -> #NUM! | K44: NO | L44: PENDIENTE | M44: =IF(L44="Pagado", I44, 0) -> 0 | P44: =IF(L44="NO APLICA",0, (I44-M44)) -> #NUM!
A45: 38 | B45: =Usuarios!B39 & " " & Usuarios!C39 & " " & Usuarios!D39 -> Norma Sanchez | C45: =INDEX(INDIRECT("'" & TEXT(EDATE(J45,-2),"mm-yyyy") & "'!D:D"), MATCH(A45,INDIRECT("'" & TEXT(EDATE(J45,-2),"mm-yyyy") & "'!A:A"),0)) -> #NUM! | E45: =D45-C45 -> #NUM! | F45: 1182.6 | G45: =E45*F45 -> #NUM! | H45: 5000 | I45: =E45*F45+H45 -> #NUM! | K45: NO | L45: PENDIENTE | M45: =IF(L45="Pagado", I45, 0) -> 0 | P45: =IF(L45="NO APLICA",0, (I45-M45)) -> #NUM!
A46: 47 | B46: =Usuarios!B48 & " " & Usuarios!C48 & " " & Usuarios!D48 -> Pablo Contreras | C46: =INDEX(INDIRECT("'" & TEXT(EDATE(J46,-2),"mm-yyyy") & "'!D:D"), MATCH(A46,INDIRECT("'" & TEXT(EDATE(J46,-2),"mm-yyyy") & "'!A:A"),0)) -> #NUM! | K46: NO | L46: NO APLICA | M46: =IF(L46="Pagado", I46, 0) -> 0 | P46: =IF(L46="NO APLICA",0, (I46-M46)) -> 0
A47: 31 | B47: =Usuarios!B32 & " " & Usuarios!C32 & " " & Usuarios!D32 -> Patricia Carcamo Gonzales | C47: =INDEX(INDIRECT("'" & TEXT(EDATE(J47,-2),"mm-yyyy") & "'!D:D"), MATCH(A47,INDIRECT("'" & TEXT(EDATE(J47,-2),"mm-yyyy") & "'!A:A"),0)) -> #NUM! | E47: =D47-C47 -> #NUM! | F47: 1182.6 | G47: =E47*F47 -> #NUM! | H47: 5000 | I47: =E47*F47+H47 -> #NUM! | K47: NO | L47: PENDIENTE | M47: =IF(L47="Pagado", I47, 0) -> 0 | P47: =IF(L47="NO APLICA",0, (I47-M47)) -> #NUM!
A48: 37 | B48: =Usuarios!B38 & " " & Usuarios!C38 & " " & Usuarios!D38 -> Patricio Alvarez Mancilla | C48: =INDEX(INDIRECT("'" & TEXT(EDATE(J48,-2),"mm-yyyy") & "'!D:D"), MATCH(A48,INDIRECT("'" & TEXT(EDATE(J48,-2),"mm-yyyy") & "'!A:A"),0)) -> #NUM! | E48: =D48-C48 -> #NUM! | F48: 1182.6 | G48: =E48*F48 -> #NUM! | H48: 5000 | I48: =E48*F48+H48 -> #NUM! | K48: NO | L48: PENDIENTE | M48: =IF(L48="Pagado", I48, 0) -> 0 | P48: =IF(L48="NO APLICA",0, (I48-M48)) -> #NUM!
A49: 27 | B49: =Usuarios!B28 & " " & Usuarios!C28 & " " & Usuarios!D28 -> Pedro Almonacid | C49: =INDEX(INDIRECT("'" & TEXT(EDATE(J49,-2),"mm-yyyy") & "'!D:D"), MATCH(A49,INDIRECT("'" & TEXT(EDATE(J49,-2),"mm-yyyy") & "'!A:A"),0)) -> #NUM! | E49: =D49-C49 -> #NUM! | F49: 1182.6 | G49: =E49*F49 -> #NUM! | H49: 5000 | I49: =E49*F49+H49 -> #NUM! | K49: NO | L49: PENDIENTE | M49: =IF(L49="Pagado", I49, 0) -> 0 | P49: =IF(L49="NO APLICA",0, (I49-M49)) -> #NUM!
A50: 12 | B50: =Usuarios!B13 & " " & Usuarios!C13 & " " & Usuarios!D13 -> Pedro Contreras | C50: =INDEX(INDIRECT("'" & TEXT(EDATE(J50,-2),"mm-yyyy") & "'!D:D"), MATCH(A50,INDIRECT("'" & TEXT(EDATE(J50,-2),"mm-yyyy") & "'!A:A"),0)) -> #NUM! | E50: =D50-C50 -> #NUM! | F50: 1182.6 | G50: =E50*F50 -> #NUM! | H50: 5000 | I50: =E50*F50+H50 -> #NUM! | K50: NO | L50: PENDIENTE | M50: =IF(L50="Pagado", I50, 0) -> 0 | P50: =IF(L50="NO APLICA",0, (I50-M50)) -> #NUM!
A51: 43 | B51: =Usuarios!B44 & " " & Usuarios!C44 & " " & Usuarios!D44 -> Ramon Maldonado | C51: =INDEX(INDIRECT("'" & TEXT(EDATE(J51,-2),"mm-yyyy") & "'!D:D"), MATCH(A51,INDIRECT("'" & TEXT(EDATE(J51,-2),"mm-yyyy") & "'!A:A"),0)) -> #NUM! | E51: =D51-C51 -> #NUM! | F51: 1182.6 | G51: =E51*F51 -> #NUM! | H51: 5000 | I51: =E51*F51+H51 -> #NUM! | K51: NO | L51: PENDIENTE | M51: =IF(L51="Pagado", I51, 0) -> 0 | P51: =IF(L51="NO APLICA",0, (I51-M51)) -> #NUM!
A52: 14 | B52: =Usuarios!B15 & " " & Usuarios!C15 & " " & Usuarios!D15 -> Ramona Mansilla | C52: =INDEX(INDIRECT("'" & TEXT(EDATE(J52,-2),"mm-yyyy") & "'!D:D"), MATCH(A52,INDIRECT("'" & TEXT(EDATE(J52,-2),"mm-yyyy") & "'!A:A"),0)) -> #NUM! | E52: =D52-C52 -> #NUM! | F52: 1182.6 | G52: =E52*F52 -> #NUM! | H52: 5000 | I52: =E52*F52+H52 -> #NUM! | K52: NO | L52: PENDIENTE | M52: =IF(L52="Pagado", I52, 0) -> 0 | P52: =IF(L52="NO APLICA",0, (I52-M52)) -> #NUM!
A53: 54 | B53: =Usuarios!B55 & " " & Usuarios!C55 & " " & Usuarios!D55 -> Rosa Mancilla | C53: =INDEX(INDIRECT("'" & TEXT(EDATE(J53,-2),"mm-yyyy") & "'!D:D"), MATCH(A53,INDIRECT("'" & TEXT(EDATE(J53,-2),"mm-yyyy") & "'!A:A"),0)) -> #NUM! | E53: =D53-C53 -> #NUM! | F53: 1182.6 | G53: =E53*F53 -> #NUM! | H53: 5000 | I53: =E53*F53+H53 -> #NUM! | K53: NO | L53: PENDIENTE | M53: =IF(L53="Pagado", I53, 0) -> 0 | P53: =IF(L53="NO APLICA",0, (I53-M53)) -> #NUM!
A54: 49 | B54: =Usuarios!B50 & " " & Usuarios!C50 & " " & Usuarios!D50 -> Rosa Nuñez | C54: =INDEX(INDIRECT("'" & TEXT(EDATE(J54,-2),"mm-yyyy") & "'!D:D"), MATCH(A54,INDIRECT("'" & TEXT(EDATE(J54,-2),"mm-yyyy") & "'!A:A"),0)) -> #NUM! | E54: =D54-C54 -> #NUM! | F54: 1182.6 | G54: =E54*F54 -> #NUM! | H54: 5000 | I54: =E54*F54+H54 -> #NUM! | K54: NO | L54: PENDIENTE | M54: =IF(L54="Pagado", I54, 0) -> 0 | P54: =IF(L54="NO APLICA",0, (I54-M54)) -> #NUM!
A55: 15 | B55: =Usuarios!B16 & " " & Usuarios!C16 & " " & Usuarios!D16 -> Sandra Mancilla Merino | C55: =INDEX(INDIRECT("'" & TEXT(EDATE(J55,-2),"mm-yyyy") & "'!D:D"), MATCH(A55,INDIRECT("'" & TEXT(EDATE(J55,-2),"mm-yyyy") & "'!A:A"),0)) -> #NUM! | E55: =D55-C55 -> #NUM! | F55: 1182.6 | G55: =E55*F55 -> #NUM! | H55: 5000 | I55: =E55*F55+H55 -> #NUM! | K55: NO | L55: PENDIENTE | M55: =IF(L55="Pagado", I55, 0) -> 0 | P55: =IF(L55="NO APLICA",0, (I55-M55)) -> #NUM!
A56: 34 | B56: =Usuarios!B35 & " " & Usuarios!C35 & " " & Usuarios!D35 -> Vanesa Aguilar | C56: =INDEX(INDIRECT("'" & TEXT(EDATE(J56,-2),"mm-yyyy") & "'!D:D"), MATCH(A56,INDIRECT("'" & TEXT(EDATE(J56,-2),"mm-yyyy") & "'!A:A"),0)) -> #NUM! | E56: =D56-C56 -> #NUM! | F56: 1182.6 | G56: =E56*F56 -> #NUM! | H56: 5000 | I56: =E56*F56+H56 -> #NUM! | K56: NO | L56: PENDIENTE | M56: =IF(L56="Pagado", I56, 0) -> 0 | P56: =IF(L56="NO APLICA",0, (I56-M56)) -> #NUM!
A57: 22 | B57: =Usuarios!B23 & " " & Usuarios!C23 & " " & Usuarios!D23 -> Yuri Millaquen | C57: =INDEX(INDIRECT("'" & TEXT(EDATE(J57,-2),"mm-yyyy") & "'!D:D"), MATCH(A57,INDIRECT("'" & TEXT(EDATE(J57,-2),"mm-yyyy") & "'!A:A"),0)) -> #NUM! | E57: =D57-C57 -> #NUM! | F57: 1182.6 | G57: =E57*F57 -> #NUM! | H57: 5000 | I57: =E57*F57+H57 -> #NUM! | K57: NO | L57: PENDIENTE | M57: =IF(L57="Pagado", I57, 0) -> 0 | P57: =IF(L57="NO APLICA",0, (I57-M57)) -> #NUM!
C58: ='07-2025'!D98

Sheet 01-2025
A1: ID | B1: Nombre | C1: Lectura_Anterior | D1: Lectura_Actual | E1: Consumo_m3 | F1: Tarifa_m3 | G1: Subtotal_Consumo | H1: Cargo_Fijo | I1: Total_Factura | J1: Fecha_Lectura | K1: Periodo | L1: Estado_Pago | M1: Monto_Pagado | N1: Fecha_Pago | O1: Forma_Pago | P1: Saldo_Pendiente | Q1: comprobante_link
A2: 1 | B2: =Usuarios!B2 & " " & Usuarios!C2 & " " & Usuarios!D2 -> Nancy Zuñiga Villarroel | C2: 152 | D2: 165 | E2: =D2-C2 -> 13 | F2: 1182.6 | G2: =E2*F2 -> 15373.8 | H2: 5000 | I2: =E2*F2+H2 -> 20373.8 | L2: PAGADO | M2: =IF(L2="Pagado", I2, 0) -> 20373.8 | P2: =IF(L2="NO APLICA",0, (I2-M2)) -> 0
A3: 2 | B3: =Usuarios!B3 & " " & Usuarios!C3 & " " & Usuarios!D3 -> Gabriel Barria Zuñiga | C3: 235 | D3: 253 | E3: =D3-C3 -> 18 | F3: 1182.6 | G3: =E3*F3 -> 21286.8 | H3: 5000 | I3: =E3*F3+H3 -> 26286.8 | L3: PAGADO | M3: =IF(L3="Pagado", I3, 0) -> 26286.8 | P3: =IF(L3="NO APLICA",0, (I3-M3)) -> 0
A4: 3 | B4: =Usuarios!B4 & " " & Usuarios!C4 & " " & Usuarios!D4 -> Gino Reyes | C4: 55 | D4: 55 | E4: =D4-C4 -> 0 | F4: 1182.6 | G4: =E4*F4 -> 0 | H4: 5000 | I4: =E4*F4+H4 -> 5000 | L4: PAGADO | M4: =IF(L4="Pagado", I4, 0) -> 5000 | P4: =IF(L4="NO APLICA",0, (I4-M4)) -> 0
A5: 4 | B5: =Usuarios!B5 & " " & Usuarios!C5 & " " & Usuarios!D5 -> Cristian Oyarzo | C5: 390 | D5: 420 | E5: =D5-C5 -> 30 | F5: 1182.6 | G5: =E5*F5 -> 35478 | H5: 5000 | I5: =E5*F5+H5 -> 40478 | L5: PAGADO | M5: =IF(L5="Pagado", I5, 0) -> 40478 | P5: =IF(L5="NO APLICA",0, (I5-M5)) -> 0
A6: 5 | B6: =Usuarios!B6 & " " & Usuarios!C6 & " " & Usuarios!D6 -> Marisol Castro | C6: 81 | D6: 88 | E6: =D6-C6 -> 7 | F6: 1182.6 | G6: =E6*F6 -> 8278.2 | H6: 5000 | I6: =E6*F6+H6 -> 13278.2 | L6: PAGADO | M6: =IF(L6="Pagado", I6, 0) -> 13278.2 | P6: =IF(L6="NO APLICA",0, (I6-M6)) -> 0
A7: 6 | B7: =Usuarios!B7 & " " & Usuarios!C7 & " " & Usuarios!D7 -> Mauricio Muñoz | C7: 163 | D7: 174 | E7: =D7-C7 -> 11 | F7: 1182.6 | G7: =E7*F7 -> 13008.6 | H7: 5000 | I7: =E7*F7+H7 -> 18008.6 | L7: PAGADO | M7: =IF(L7="Pagado", I7, 0) -> 18008.6 | P7: =IF(L7="NO APLICA",0, (I7-M7)) -> 0
A8: 7 | B8: =Usuarios!B8 & " " & Usuarios!C8 & " " & Usuarios!D8 -> Marcelo Millanao | C8: 200 | D8: 211 | E8: =D8-C8 -> 11 | F8: 1182.6 | G8: =E8*F8 -> 13008.6 | H8: 5000 | I8: =E8*F8+H8 -> 18008.6 | L8: PAGADO | M8: =IF(L8="Pagado", I8, 0) -> 18008.6 | P8: =IF(L8="NO APLICA",0, (I8-M8)) -> 0
A9: 8 | B9: =Usuarios!B9 & " " & Usuarios!C9 & " " & Usuarios!D9 -> Gabriel Farias | C9: 353 | D9: 379 | E9: =D9-C9 -> 26 | F9: 1182.6 | G9: =E9*F9 -> 30747.6 | H9: 5000 | I9: =E9*F9+H9 -> 35747.6 | L9: PAGADO | M9: =IF(L9="Pagado", I9, 0) -> 35747.6 | P9: =IF(L9="NO APLICA",0, (I9-M9)) -> 0
A10: 9 | B10: =Usuarios!B10 & " " & Usuarios!C10 & " " & Usuarios!D10 -> Maria Marin | C10: 126 | D10: 137 | E10: =D10-C10 -> 11 | F10: 1182.6 | G10: =E10*F10 -> 13008.6 | H10: 5000 | I10: =E10*F10+H10 -> 18008.6 | L10: PAGADO | M10: =IF(L10="Pagado", I10, 0) -> 18008.6 | P10: =IF(L10="NO APLICA",0, (I10-M10)) -> 0
A11: 10 | B11: =Usuarios!B11 & " " & Usuarios!C11 & " " & Usuarios!D11 -> David Cartes | C11: 90 | D11: 97 | E11: =D11-C11 -> 7 | F11: 1182.6 | G11: =E11*F11 -> 8278.2 | H11: 5000 | I11: =E11*F11+H11 -> 13278.2 | L11: PAGADO | M11: =IF(L11="Pagado", I11, 0) -> 13278.2 | P11: =IF(L11="NO APLICA",0, (I11-M11)) -> 0
A12: 11 | B12: =Usuarios!B12 & " " & Usuarios!C12 & " " & Usuarios!D12 -> Miguel Ñanco | C12: 159 | D12: 189 | E12: =D12-C12 -> 30 | F12: 1182.6 | G12: =E12*F12 -> 35478 | H12: 5000 | I12: =E12*F12+H12 -> 40478 | L12: PAGADO | M12: =IF(L12="Pagado", I12, 0) -> 40478 | P12: =IF(L12="NO APLICA",0, (I12-M12)) -> 0
A13: 12 | B13: =Usuarios!B13 & " " & Usuarios!C13 & " " & Usuarios!D13 -> Pedro Contreras | C13: 90 | D13: 97 | E13: =D13-C13 -> 7 | F13: 1182.6 | G13: =E13*F13 -> 8278.2 | H13: 5000 | I13: =E13*F13+H13 -> 13278.2 | L13: PAGADO | M13: =IF(L13="Pagado", I13, 0) -> 13278.2 | P13: =IF(L13="NO APLICA",0, (I13-M13)) -> 0
... A21: 20 | B21: =Usuarios!B21 & " " & Usuarios!C21 & " " & Usuarios!D21 -> Juan Chavez | C21: 20 | D21: 21 | E21: =D21-C21 -> 1 | F21: 1182.6 | G21: =E21*F21 -> 1182.6 | H21: 5000 | I21: =E21*F21+H21 -> 6182.6 | L21: PAGADO | M21: =IF(L21="Pagado", I21, 0) -> 6182.6 | P21: =IF(L21="NO APLICA",0, (I21-M21)) -> 0
A22: 21
A23: 22 | B23: =Usuarios!B23 & " " & Usuarios!C23 & " " & Usuarios!D23 -> Yuri Millaquen | C23: 119 | D23: 130 | E23: =D23-C23 -> 11 | F23: 1182.6 | G23: =E23*F23 -> 13008.6 | H23: 5000 | I23: =E23*F23+H23 -> 18008.6 | L23: PAGADO | M23: =IF(L23="Pagado", I23, 0) -> 18008.6 | P23: =IF(L23="NO APLICA",0, (I23-M23)) -> 0
A24: 23 | B24: =Usuarios!B24 & " " & Usuarios!C24 & " " & Usuarios!D24 -> Carlos Nahuelpan | C24: 83 | D24: 92 | E24: =D24-C24 -> 9 | F24: 1182.6 | G24: =E24*F24 -> 10643.4 | H24: 5000 | I24: =E24*F24+H24 -> 15643.4 | L24: PAGADO | M24: =IF(L24="Pagado", I24, 0) -> 15643.4 | P24: =IF(L24="NO APLICA",0, (I24-M24)) -> 0
A25: 24 | B25: =Usuarios!B25 & " " & Usuarios!C25 & " " & Usuarios!D25 -> Maria Velasquez Miranda | C25: 184 | D25: 203 | E25: =D25-C25 -> 19 | F25: 1182.6 | G25: =E25*F25 -> 22469.4 | H25: 5000 | I25: =E25*F25+H25 -> 27469.4 | L25: PAGADO | M25: =IF(L25="Pagado", I25, 0) -> 27469.4 | P25: =IF(L25="NO APLICA",0, (I25-M25)) -> 0
A26: 25 | B26: =Usuarios!B26 & " " & Usuarios!C26 & " " & Usuarios!D26 -> Inés Velasquez | C26: 96 | D26: 100 | E26: =D26-C26 -> 4 | F26: 1182.6 | G26: =E26*F26 -> 4730.4 | H26: 5000 | I26: =E26*F26+H26 -> 9730.4 | L26: PAGADO | M26: =IF(L26="Pagado", I26, 0) -> 9730.4 | P26: =IF(L26="NO APLICA",0, (I26-M26)) -> 0
A27: 26 | B27: =Usuarios!B27 & " " & Usuarios!C27 & " " & Usuarios!D27 -> Guido Quintuy | C27: 109 | D27: 117 | E27: =D27-C27 -> 8 | F27: 1182.6 | G27: =E27*F27 -> 9460.8 | H27: 5000 | I27: =E27*F27+H27 -> 14460.8 | L27: PAGADO | M27: =IF(L27="Pagado", I27, 0) -> 14460.8 | P27: =IF(L27="NO APLICA",0, (I27-M27)) -> 0
A28: 27 | B28: =Usuarios!B28 & " " & Usuarios!C28 & " " & Usuarios!D28 -> Pedro Almonacid | C28: 160 | D28: 177 | E28: =D28-C28 -> 17 | F28: 1182.6 | G28: =E28*F28 -> 20104.2 | H28: 5000 | I28: =E28*F28+H28 -> 25104.2 | L28: PENDIENTE | M28: =IF(L28="Pagado", I28, 0) -> 0 | P28: =IF(L28="NO APLICA",0, (I28-M28)) -> 25104.2
A29: 28 | B29: =Usuarios!B29 & " " & Usuarios!C29 & " " & Usuarios!D29 -> Nora Ñanco | C29: 363 | D29: 381 | E29: =D29-C29 -> 18 | F29: 1182.6 | G29: =E29*F29 -> 21286.8 | H29: 5000 | I29: =E29*F29+H29 -> 26286.8 | L29: PAGADO | M29: =IF(L29="Pagado", I29, 0) -> 26286.8 | P29: =IF(L29="NO APLICA",0, (I29-M29)) -> 0
A30: 29 | B30: =Usuarios!B30 & " " & Usuarios!C30 & " " & Usuarios!D30 -> Miriam Alvarado | C30: 488 | D30: 515 | E30: =D30-C30 -> 27 | F30: 1182.6 | G30: =E30*F30 -> 31930.2 | H30: 5000 | I30: =E30*F30+H30 -> 36930.2 | L30: PAGADO | M30: =IF(L30="Pagado", I30, 0) -> 36930.2 | P30: =IF(L30="NO APLICA",0, (I30-M30)) -> 0
A31: 30 | B31: =Usuarios!B31 & " " & Usuarios!C31 & " " & Usuarios!D31 -> Luz Maldonado | C31: 5 | D31: 5 | E31: =D31-C31 -> 0 | F31: 1182.6 | G31: =E31*F31 -> 0 | H31: 5000 | I31: =E31*F31+H31 -> 5000 | L31: PAGADO | M31: =IF(L31="Pagado", I31, 0) -> 5000 | P31: =IF(L31="NO APLICA",0, (I31-M31)) -> 0
A32: 31 | B32: =Usuarios!B32 & " " & Usuarios!C32 & " " & Usuarios!D32 -> Patricia Carcamo Gonzales | C32: 90 | D32: 113 | E32: =D32-C32 -> 23 | F32: 1182.6 | G32: =E32*F32 -> 27199.8 | H32: 5000 | I32: =E32*F32+H32 -> 32199.8 | L32: PAGADO | M32: =IF(L32="Pagado", I32, 0) -> 32199.8 | P32: =IF(L32="NO APLICA",0, (I32-M32)) -> 0
A33: 32 | B33: =Usuarios!B33 & " " & Usuarios!C33 & " " & Usuarios!D33 -> Natividad Soto | C33: 59 | D33: 66 | E33: =D33-C33 -> 7 | F33: 1182.6 | G33: =E33*F33 -> 8278.2 | H33: 5000 | I33: =E33*F33+H33 -> 13278.2 | L33: PAGADO | M33: =IF(L33="Pagado", I33, 0) -> 13278.2 | P33: =IF(L33="NO APLICA",0, (I33-M33)) -> 0
A34: 33 | B34: =Usuarios!B34 & " " & Usuarios!C34 & " " & Usuarios!D34 -> Maria Oliva Soto Almonacid | C34: 41 | D34: 43 | E34: =D34-C34 -> 2 | F34: 1182.6 | G34: =E34*F34 -> 2365.2 | H34: 5000 | I34: =E34*F34+H34 -> 7365.2 | L34: PAGADO | M34: =IF(L34="Pagado", I34, 0) -> 7365.2 | P34: =IF(L34="NO APLICA",0, (I34-M34)) -> 0
... A43: 42 | B43: =Usuarios!B43 & " " & Usuarios!C43 & " " & Usuarios!D43 -> Leo Soto | C43: 0 | D43: 0 | E43: =D43-C43 -> 0 | F43: 1182.6 | G43: =E43*F43 -> 0 | H43: 5000 | I43: =E43*F43+H43 -> 5000 | L43: PENDIENTE | M43: =IF(L43="Pagado", I43, 0) -> 0 | P43: =IF(L43="NO APLICA",0, (I43-M43)) -> 5000
A44: 43 | B44: =Usuarios!B44 & " " & Usuarios!C44 & " " & Usuarios!D44 -> Ramon Maldonado | C44: 0 | D44: 0 | E44: =D44-C44 -> 0 | F44: 1182.6 | G44: =E44*F44 -> 0 | H44: 5000 | I44: =E44*F44+H44 -> 5000 | L44: PENDIENTE | M44: =IF(L44="Pagado", I44, 0) -> 0 | O44: TRANSFERENCIA | P44: =IF(L44="NO APLICA",0, (I44-M44)) -> 5000
A45: 44 | B45: =Usuarios!B45 & " " & Usuarios!C45 & " " & Usuarios!D45 -> María Sonia Quintui | C45: 0 | D45: 0 | E45: =D45-C45 -> 0 | F45: 1182.6 | G45: =E45*F45 -> 0 | H45: 5000 | I45: =E45*F45+H45 -> 5000 | L45: PAGADO | M45: =IF(L45="Pagado", I45, 0) -> 5000 | P45: =IF(L45="NO APLICA",0, (I45-M45)) -> 0
A46: 45 | B46: =Usuarios!B46 & " " & Usuarios!C46 & " " & Usuarios!D46 -> Monica Cuello | C46: 0 | D46: 0 | E46: =D46-C46 -> 0 | F46: 1182.6 | G46: =E46*F46 -> 0 | H46: 5000 | I46: =E46*F46+H46 -> 5000 | L46: PAGADO | M46: =IF(L46="Pagado", I46, 0) -> 5000 | P46: =IF(L46="NO APLICA",0, (I46-M46)) -> 0
A47: 46 | B47: =Usuarios!B47 & " " & Usuarios!C47 & " " & Usuarios!D47 -> Mauricio Muñoz taller | C47: 0 | D47: 0 | E47: =D47-C47 -> 0 | F47: 1182.6 | G47: =E47*F47 -> 0 | H47: 5000 | I47: =E47*F47+H47 -> 5000 | L47: PENDIENTE | M47: =IF(L47="Pagado", I47, 0) -> 0 | P47: =IF(L47="NO APLICA",0, (I47-M47)) -> 5000
A48: 47 | B48: =Usuarios!B48 & " " & Usuarios!C48 & " " & Usuarios!D48 -> Pablo Contreras | C48: 0 | D48: 0 | E48: =D48-C48 -> 0 | F48: 1182.6 | G48: =E48*F48 -> 0 | H48: 5000 | I48: =E48*F48+H48 -> 5000 | L48: PAGADO | M48: =IF(L48="Pagado", I48, 0) -> 5000 | P48: =IF(L48="NO APLICA",0, (I48-M48)) -> 0
A49: 48 | B49: =Usuarios!B49 & " " & Usuarios!C49 & " " & Usuarios!D49 -> Luis Vicente Mondaca Muñoz | C49: 196 | D49: 226 | E49: =D49-C49 -> 30 | F49: 1182.6 | G49: =E49*F49 -> 35478 | H49: 5000 | I49: =E49*F49+H49 -> 40478 | L49: PAGADO | M49: =IF(L49="Pagado", I49, 0) -> 40478 | P49: =IF(L49="NO APLICA",0, (I49-M49)) -> 0
A50: 49 | B50: =Usuarios!B50 & " " & Usuarios!C50 & " " & Usuarios!D50 -> Rosa Nuñez | C50: 65 | D50: 70 | E50: =D50-C50 -> 5 | F50: 1182.6 | G50: =E50*F50 -> 5913 | H50: 5000 | I50: =E50*F50+H50 -> 10913 | L50: PAGADO | M50: =IF(L50="Pagado", I50, 0) -> 10913 | P50: =IF(L50="NO APLICA",0, (I50-M50)) -> 0
A51: 50 | B51: =Usuarios!B51 & " " & Usuarios!C51 & " " & Usuarios!D51 -> Gloria Isamar Velasquez Almonacid | C51: 11 | D51: 18 | E51: =D51-C51 -> 7 | F51: 1182.6 | G51: =E51*F51 -> 8278.2 | H51: 5000 | I51: =E51*F51+H51 -> 13278.2 | L51: PAGADO | M51: =IF(L51="Pagado", I51, 0) -> 13278.2 | P51: =IF(L51="NO APLICA",0, (I51-M51)) -> 0
A52: 51 | B52: =Usuarios!B52 & " " & Usuarios!C52 & " " & Usuarios!D52 -> Maria Manquian | C52: 0 | D52: 0 | E52: =D52-C52 -> 0 | F52: 1182.6 | G52: =E52*F52 -> 0 | H52: 5000 | I52: =E52*F52+H52 -> 5000 | L52: PAGADO | M52: =IF(L52="Pagado", I52, 0) -> 5000 | O52: TRANSFERENCIA | P52: =IF(L52="NO APLICA",0, (I52-M52)) -> 0
A53: 52 | B53: =Usuarios!B53 & " " & Usuarios!C53 & " " & Usuarios!D53 -> Esteban Oyarzo Levil | C53: 0 | D53: 0 | E53: =D53-C53 -> 0 | F53: 1182.6 | G53: =E53*F53 -> 0 | H53: 5000 | I53: =E53*F53+H53 -> 5000 | L53: PAGADO | M53: =IF(L53="Pagado", I53, 0) -> 5000 | P53: =IF(L53="NO APLICA",0, (I53-M53)) -> 0
A54: 53 | B54: =Usuarios!B54 & " " & Usuarios!C54 & " " & Usuarios!D54 -> Nicolas Andres Cardenas Bustamante | C54: 0 | D54: 0 | E54: =D54-C54 -> 0 | F54: 1182.6 | G54: =E54*F54 -> 0 | H54: 5000 | I54: =E54*F54+H54 -> 5000 | L54: PAGADO | M54: =IF(L54="Pagado", I54, 0) -> 5000 | P54: =IF(L54="NO APLICA",0, (I54-M54)) -> 0
A55: 54 | B55: =Usuarios!B55 & " " & Usuarios!C55 & " " & Usuarios!D55 -> Rosa Mancilla | C55: 0 | D55: 106 | E55: =D55-C55 -> 106 | F55: 1182.6 | G55: =E55*F55 -> 125355.6 | H55: 5000 | I55: =E55*F55+H55 -> 130355.6 | L55: PAGADO | M55: =IF(L55="Pagado", I55, 0) -> 130355.6 | P55: =IF(L55="NO APLICA",0, (I55-M55)) -> 0
A56: 55 | B56: =Usuarios!B56 & " " & Usuarios!C56 & " " & Usuarios!D56 -> Guido Quintuy - Sitio vacío | C56: 0 | D56: 0 | E56: =D56-C56 -> 0 | F56: 1182.6 | G56: =E56*F56 -> 0 | H56: 5000 | I56: =E56*F56+H56 -> 5000 | L56: PAGADO | M56: =IF(L56="Pagado", I56, 0) -> 5000 | P56: =IF(L56="NO APLICA",0, (I56-M56)) -> 0
A57: 56 | B57: =Usuarios!B57 & " " & Usuarios!C57 & " " & Usuarios!D57 -> Mario Velasquez | C57: 0 | D57: 5 | E57: =D57-C57 -> 5 | F57: 1182.6 | G57: =E57*F57 -> 5913 | H57: 5000 | I57: =E57*F57+H57 -> 10913 | L57: PAGADO | M57: =IF(L57="Pagado", I57, 0) -> 10913 | P57: =IF(L57="NO APLICA",0, (I57-M57)) -> 0
A58: 57 | B58: =Usuarios!B58 & " " & Usuarios!C58 & " " & Usuarios!D58 -> Lishby Fuentes Diaz | C58: 0 | D58: 0 | E58: =D58-C58 -> 0 | F58: 1182.6 | G58: =E58*F58 -> 0 | H58: 5000 | I58: =E58*F58+H58 -> 5000 | L58: NO APLICA | M58: =IF(L58="Pagado", I58, 0) -> 0 | P58: =IF(L58="NO APLICA",0, (I58-M58)) -> 0

Sheet 02-2025
A1: ID | B1: Nombre | C1: Lectura_Anterior | D1: Lectura_Actual | E1: Consumo_m3 | F1: Tarifa_m3 | G1: Subtotal_Consumo | H1: Cargo_Fijo | I1: Total_Factura | J1: Fecha_Lectura | K1: Periodo | L1: Estado_Pago | M1: Monto_Pagado | N1: Fecha_Pago | O1: Forma_Pago | P1: Saldo_Pendiente | Q1: comprobante_link
A2: 41 | B2: =Usuarios!B42 & " " & Usuarios!C42 & " " & Usuarios!D42 -> Astrid Gomez | C2: {=INDEX(INDIRECT("'" & TEXT(EDATE(J2,-2),"mm-yyyy") & "'!D:D"), MATCH(A2,INDIRECT("'" & TEXT(EDATE(J2,-2),"mm-yyyy") & "'!A:A"),0))} -> 86 | D2: 91 | E2: =D2-C2 -> 5 | F2: 1182.6 | G2: =E2*F2 -> 5913 | H2: 5000 | I2: =E2*F2+H2 -> 10913 | J2: 45724 | L2: PENDIENTE | M2: =IF(L2="Pagado", I2, 0) -> 0 | P2: =IF(L2="NO APLICA",0, (I2-M2)) -> 10913
A3: 16 | B3: =Usuarios!B17 & " " & Usuarios!C17 & " " & Usuarios!D17 -> Carlos Agüero | C3: {=INDEX('01-2025'!D:D,MATCH(INDEX(A:A, ROW()), '01-2025'!A:A, 0))} -> 150 | D3: 161 | E3: =D3-C3 -> 11 | F3: 1182.6 | G3: =E3*F3 -> 13008.6 | H3: 5000 | I3: =E3*F3+H3 -> 18008.6 | J3: 45724 | L3: PAGADO | M3: =IF(L3="Pagado", I3, 0) -> 18008.6 | P3: =IF(L3="NO APLICA",0, (I3-M3)) -> 0
A4: 13 | B4: =Usuarios!B14 & " " & Usuarios!C14 & " " & Usuarios!D14 -> Carlos Gamin | C4: {=INDEX('01-2025'!D:D,MATCH(INDEX(A:A, ROW()), '01-2025'!A:A, 0))} -> 158 | D4: 171 | E4: =D4-C4 -> 13 | F4: 1182.6 | G4: =E4*F4 -> 15373.8 | H4: 5000 | I4: =E4*F4+H4 -> 20373.8 | J4: 45724 | L4: PENDIENTE | M4: =IF(L4="Pagado", I4, 0) -> 0 | P4: =IF(L4="NO APLICA",0, (I4-M4)) -> 20373.8
A5: 23 | B5: =Usuarios!B24 & " " & Usuarios!C24 & " " & Usuarios!D24 -> Carlos Nahuelpan | C5: {=INDEX('01-2025'!D:D,MATCH(INDEX(A:A, ROW()), '01-2025'!A:A, 0))} -> 92 | D5: 100 | E5: =D5-C5 -> 8 | F5: 1182.6 | G5: =E5*F5 -> 9460.8 | H5: 5000 | I5: =E5*F5+H5 -> 14460.8 | J5: 45724 | L5: PAGADO | M5: =IF(L5="Pagado", I5, 0) -> 14460.8 | P5: =IF(L5="NO APLICA",0, (I5-M5)) -> 0
A6: 4 | B6: =Usuarios!B5 & " " & Usuarios!C5 & " " & Usuarios!D5 -> Cristian Oyarzo | C6: {=INDEX('01-2025'!D:D,MATCH(INDEX(A:A, ROW()), '01-2025'!A:A, 0))} -> 420 | D6: 455 | E6: =D6-C6 -> 35 | F6: 1182.6 | G6: =E6*F6 -> 41391 | H6: 5000 | I6: =E6*F6+H6 -> 46391 | J6: 45724 | L6: PAGADO | M6: =IF(L6="Pagado", I6, 0) -> 46391 | P6: =IF(L6="NO APLICA",0, (I6-M6)) -> 0
A7: 36 | B7: =Usuarios!B37 & " " & Usuarios!C37 & " " & Usuarios!D37 -> Danilo Soto Soto | C7: {=INDEX('01-2025'!D:D,MATCH(INDEX(A:A, ROW()), '01-2025'!A:A, 0))} -> 2 | D7: 2 | E7: =D7-C7 -> 0 | F7: 1182.6 | G7: =E7*F7 -> 0 | H7: 5000 | I7: =E7*F7+H7 -> 5000 | J7: 45724 | L7: PENDIENTE | M7: =IF(L7="Pagado", I7, 0) -> 0 | P7: =IF(L7="NO APLICA",0, (I7-M7)) -> 5000
A8: 10 | B8: =Usuarios!B11 & " " & Usuarios!C11 & " " & Usuarios!D11 -> David Cartes | C8: {=INDEX('01-2025'!D:D,MATCH(INDEX(A:A, ROW()), '01-2025'!A:A, 0))} -> 97 | D8: 104 | E8: =D8-C8 -> 7 | F8: 1182.6 | G8: =E8*F8 -> 8278.2 | H8: 5000 | I8: =E8*F8+H8 -> 13278.2 | J8: 45724 | L8: PAGADO | M8: =IF(L8="Pagado", I8, 0) -> 13278.2 | P8: =IF(L8="NO APLICA",0, (I8-M8)) -> 0
A9: 19 | B9: =Usuarios!B20 & " " & Usuarios!C20 & " " & Usuarios!D20 -> Eduardo Chavez | C9: {=INDEX('01-2025'!D:D,MATCH(INDEX(A:A, ROW()), '01-2025'!A:A, 0))} -> 67 | D9: 73 | E9: =D9-C9 -> 6 | F9: 1182.6 | G9: =E9*F9 -> 7095.6 | H9: 5000 | I9: =E9*F9+H9 -> 12095.6 | J9: 45724 | L9: PAGADO | M9: =IF(L9="Pagado", I9, 0) -> 12095.6 | P9: =IF(L9="NO APLICA",0, (I9-M9)) -> 0
A10: 52 | B10: =Usuarios!B53 & " " & Usuarios!C53 & " " & Usuarios!D53 -> Esteban Oyarzo Levil | C10: {=INDEX('01-2025'!D:D,MATCH(INDEX(A:A, ROW()), '01-2025'!A:A, 0))} -> 0 | D10: 0 | E10: =D10-C10 -> 0 | F10: 1182.6 | G10: =E10*F10 -> 0 | H10: 5000 | I10: =E10*F10+H10 -> 5000 | J10: 45724 | L10: PENDIENTE | M10: =IF(L10="Pagado", I10, 0) -> 0 | P10: =IF(L10="NO APLICA",0, (I10-M10)) -> 5000
A11: 8 | B11: =Usuarios!B9 & " " & Usuarios!C9 & " " & Usuarios!D9 -> Gabriel Farias | C11: {=INDEX('01-2025'!D:D,MATCH(INDEX(A:A, ROW()), '01-2025'!A:A, 0))} -> 379 | D11: 399 | E11: =D11-C11 -> 20 | F11: 1182.6 | G11: =E11*F11 -> 23652 | H11: 5000 | I11: =E11*F11+H11 -> 28652 | J11: 45724 | L11: PAGADO | M11: =IF(L11="Pagado", I11, 0) -> 28652 | P11: =IF(L11="NO APLICA",0, (I11-M11)) -> 0
A12: 2 | B12: =Usuarios!B3 & " " & Usuarios!C3 & " " & Usuarios!D3 -> Gabriel Barria Zuñiga | C12: {=INDEX('01-2025'!D:D,MATCH(INDEX(A:A, ROW()), '01-2025'!A:A, 0))} -> 253 | D12: 270 | E12: =D12-C12 -> 17 | F12: 1182.6 | G12: =E12*F12 -> 20104.2 | H12: 5000 | I12: =E12*F12+H12 -> 25104.2 | J12: 45724 | L12: PAGADO | M12: =IF(L12="Pagado", I12, 0) -> 25104.2 | P12: =IF(L12="NO APLICA",0, (I12-M12)) -> 0
A13: 3 | B13: =Usuarios!B4 & " " & Usuarios!C4 & " " & Usuarios!D4 -> Gino Reyes | C13: {=INDEX('01-2025'!D:D,MATCH(INDEX(A:A, ROW()), '01-2025'!A:A, 0))} -> 55 | D13: 60 | E13: =D13-C13 -> 5 | F13: 1182.6 | G13: =E13*F13 -> 5913 | H13: 5000 | I13: =E13*F13+H13 -> 10913 | J13: 45724 | L13: PAGADO | M13: =IF(L13="Pagado", I13, 0) -> 10913 | P13: =IF(L13="NO APLICA",0, (I13-M13)) -> 0
A14: 39 | B14: =Usuarios!B40 & " " & Usuarios!C40 & " " & Usuarios!D40 -> Gloria Alvarez | C14: {=INDEX('01-2025'!D:D,MATCH(INDEX(A:A, ROW()), '01-2025'!A:A, 0))} -> 108 | D14: 108 | E14: =D14-C14 -> 0 | F14: 1182.6 | G14: =E14*F14 -> 0 | H14: 5000 | I14: =E14*F14+H14 -> 5000 | J14: 45724 | L14: PAGADO | M14: =IF(L14="Pagado", I14, 0) -> 5000 | P14: =IF(L14="NO APLICA",0, (I14-M14)) -> 0
A15: 40 | B15: =Usuarios!B41 & " " & Usuarios!C41 & " " & Usuarios!D41 -> Gloria Levil | C15: {=INDEX('01-2025'!D:D,MATCH(INDEX(A:A, ROW()), '01-2025'!A:A, 0))} -> 81 | D15: 85 | E15: =D15-C15 -> 4 | F15: 1182.6 | G15: =E15*F15 -> 4730.4 | H15: 5000 | I15: =E15*F15+H15 -> 9730.4 | J15: 45724 | L15: PENDIENTE | M15: =IF(L15="Pagado", I15, 0) -> 0 | P15: =IF(L15="NO APLICA",0, (I15-M15)) -> 9730.4
A16: 50 | B16: =Usuarios!B51 & " " & Usuarios!C51 & " " & Usuarios!D51 -> Gloria Isamar Velasquez Almonacid | C16: {=INDEX('01-2025'!D:D,MATCH(INDEX(A:A, ROW()), '01-2025'!A:A, 0))} -> 18 | D16: 24 | E16: =D16-C16 -> 6 | F16: 1182.6 | G16: =E16*F16 -> 7095.6 | H16: 5000 | I16: =E16*F16+H16 -> 12095.6 | J16: 45724 | L16: PAGADO | M16: =IF(L16="Pagado", I16, 0) -> 12095.6 | P16: =IF(L16="NO APLICA",0, (I16-M16)) -> 0
A17: 26 | B17: =Usuarios!B27 & " " & Usuarios!C27 & " " & Usuarios!D27 -> Guido Quintuy | C17: {=INDEX('01-2025'!D:D,MATCH(INDEX(A:A, ROW()), '01-2025'!A:A, 0))} -> 117 | D17: 128 | E17: =D17-C17 -> 11 | F17: 1182.6 | G17: =E17*F17 -> 13008.6 | H17: 5000 | I17: =E17*F17+H17 -> 18008.6 | J17: 45724 | L17: PAGADO | M17: =IF(L17="Pagado", I17, 0) -> 18008.6 | P17: =IF(L17="NO APLICA",0, (I17-M17)) -> 0
A18: 55 | B18: =Usuarios!B56 & " " & Usuarios!C56 & " " & Usuarios!D56 -> Guido Quintuy - Sitio vacío | C18: {=INDEX('01-2025'!D:D,MATCH(INDEX(A:A, ROW()), '01-2025'!A:A, 0))} -> 0 | D18: 0 | E18: =D18-C18 -> 0 | F18: 1182.6 | G18: =E18*F18 -> 0 | H18: 5000 | I18: =E18*F18+H18 -> 5000 | J18: 45724 | L18: PENDIENTE | M18: =IF(L18="Pagado", I18, 0) -> 0 | P18: =IF(L18="NO APLICA",0, (I18-M18)) -> 5000
A19: 25 | B19: =Usuarios!B26 & " " & Usuarios!C26 & " " & Usuarios!D26 -> Inés Velasquez | C19: {=INDEX('01-2025'!D:D,MATCH(INDEX(A:A, ROW()), '01-2025'!A:A, 0))} -> 100 | D19: 109 | E19: =D19-C19 -> 9 | F19: 1182.6 | G19: =E19*F19 -> 10643.4 | H19: 5000 | I19: =E19*F19+H19 -> 15643.4 | J19: 45724 | L19: PAGADO | M19: =IF(L19="Pagado", I19, 0) -> 15643.4 | P19: =IF(L19="NO APLICA",0, (I19-M19)) -> 0
A20: 17 | B20: =Usuarios!B18 & " " & Usuarios!C18 & " " & Usuarios!D18 -> Joaquin Claramunt | C20: {=INDEX('01-2025'!D:D,MATCH(INDEX(A:A, ROW()), '01-2025'!A:A, 0))} -> 145 | D20: 152 | E20: =D20-C20 -> 7 | F20: 1182.6 | G20: =E20*F20 -> 8278.2 | H20: 5000 | I20: =E20*F20+H20 -> 13278.2 | J20: 45724 | L20: PAGADO | M20: =IF(L20="Pagado", I20, 0) -> 13278.2 | P20: =IF(L20="NO APLICA",0, (I20-M20)) -> 0
A21: 35 | B21: =Usuarios!B36 & " " & Usuarios!C36 & " " & Usuarios!D36 -> José Paredes | C21: {=INDEX('01-2025'!D:D,MATCH(INDEX(A:A, ROW()), '01-2025'!A:A, 0))} -> 0 | D21: 0 | E21: =D21-C21 -> 0 | F21: 1182.6 | G21: =E21*F21 -> 0 | H21: 5000 | I21: =E21*F21+H21 -> 5000 | J21: 45724 | L21: PENDIENTE | M21: =IF(L21="Pagado", I21, 0) -> 0 | P21: =IF(L21="NO APLICA",0, (I21-M21)) -> 5000
A22: 20 | B22: =Usuarios!B21 & " " & Usuarios!C21 & " " & Usuarios!D21 -> Juan Chavez | C22: {=INDEX('01-2025'!D:D,MATCH(INDEX(A:A, ROW()), '01-2025'!A:A, 0))} -> 21 | D22: 22 | E22: =D22-C22 -> 1 | F22: 1182.6 | G22: =E22*F22 -> 1182.6 | H22: 5000 | I22: =E22*F22+H22 -> 6182.6 | J22: 45724 | L22: PAGADO | M22: =IF(L22="Pagado", I22, 0) -> 6182.6 | P22: =IF(L22="NO APLICA",0, (I22-M22)) -> 0
A23: 42 | B23: =Usuarios!B43 & " " & Usuarios!C43 & " " & Usuarios!D43 -> Leo Soto | C23: {=INDEX('01-2025'!D:D,MATCH(INDEX(A:A, ROW()), '01-2025'!A:A, 0))} -> 0 | D23: 0 | E23: =D23-C23 -> 0 | F23: 1182.6 | G23: =E23*F23 -> 0 | H23: 5000 | I23: =E23*F23+H23 -> 5000 | J23: 45724 | L23: PENDIENTE | M23: =IF(L23="Pagado", I23, 0) -> 0 | P23: =IF(L23="NO APLICA",0, (I23-M23)) -> 5000
A24: 57 | B24: =Usuarios!B58 & " " & Usuarios!C58 & " " & Usuarios!D58 -> Lishby Fuentes Diaz | C24: {=INDEX('01-2025'!D:D,MATCH(INDEX(A:A, ROW()), '01-2025'!A:A, 0))} -> 0 | D24: 0 | E24: =D24-C24 -> 0 | F24: 1182.6 | G24: =E24*F24 -> 0 | H24: 5000 | I24: =E24*F24+H24 -> 5000 | J24: 45724 | L24: NO APLICA | M24: =IF(L24="Pagado", I24, 0) -> 0 | P24: =IF(L24="NO APLICA",0, (I24-M24)) -> 0
A25: 48 | B25: =Usuarios!B49 & " " & Usuarios!C49 & " " & Usuarios!D49 -> Luis Vicente Mondaca Muñoz | C25: {=INDEX('01-2025'!D:D,MATCH(INDEX(A:A, ROW()), '01-2025'!A:A, 0))} -> 226 | D25: 249 | E25: =D25-C25 -> 23 | F25: 1182.6 | G25: =E25*F25 -> 27199.8 | H25: 5000 | I25: =E25*F25+H25 -> 32199.8 | J25: 45724 | L25: PAGADO | M25: =IF(L25="Pagado", I25, 0) -> 32199.8 | P25: =IF(L25="NO APLICA",0, (I25-M25)) -> 0
A26: 30 | B26: =Usuarios!B31 & " " & Usuarios!C31 & " " & Usuarios!D31 -> Luz Maldonado | C26: {=INDEX('01-2025'!D:D,MATCH(INDEX(A:A, ROW()), '01-2025'!A:A, 0))} -> 5 | D26: 5 | E26: =D26-C26 -> 0 | F26: 1182.6 | G26: =E26*F26 -> 0 | H26: 5000 | I26: =E26*F26+H26 -> 5000 | J26: 45724 | L26: PAGADO | M26: =IF(L26="Pagado", I26, 0) -> 5000 | P26: =IF(L26="NO APLICA",0, (I26-M26)) -> 0
A27: 7 | B27: =Usuarios!B8 & " " & Usuarios!C8 & " " & Usuarios!D8 -> Marcelo Millanao | C27: {=INDEX('01-2025'!D:D,MATCH(INDEX(A:A, ROW()), '01-2025'!A:A, 0))} -> 211 | D27: 224 | E27: =D27-C27 -> 13 | F27: 1182.6 | G27: =E27*F27 -> 15373.8 | H27: 5000 | I27: =E27*F27+H27 -> 20373.8 | J27: 45724 | L27: PAGADO | M27: =IF(L27="Pagado", I27, 0) -> 20373.8 | P27: =IF(L27="NO APLICA",0, (I27-M27)) -> 0
A28: 51 | B28: =Usuarios!B52 & " " & Usuarios!C52 & " " & Usuarios!D52 -> Maria Manquian | C28: {=INDEX('01-2025'!D:D,MATCH(INDEX(A:A, ROW()), '01-2025'!A:A, 0))} -> 0 | D28: 0 | E28: =D28-C28 -> 0 | F28: 1182.6 | G28: =E28*F28 -> 0 | H28: 5000 | I28: =E28*F28+H28 -> 5000 | J28: 45724 | L28: PAGADO | M28: =IF(L28="Pagado", I28, 0) -> 5000 | O28: TRANSFERENCIA | P28: =IF(L28="NO APLICA",0, (I28-M28)) -> 0
A29: 9 | B29: =Usuarios!B10 & " " & Usuarios!C10 & " " & Usuarios!D10 -> Maria Marin | C29: {=INDEX('01-2025'!D:D,MATCH(INDEX(A:A, ROW()), '01-2025'!A:A, 0))} -> 137 | D29: 153 | E29: =D29-C29 -> 16 | F29: 1182.6 | G29: =E29*F29 -> 18921.6 | H29: 5000 | I29: =E29*F29+H29 -> 23921.6 | J29: 45724 | L29: PAGADO | M29: =IF(L29="Pagado", I29, 0) -> 23921.6 | P29: =IF(L29="NO APLICA",0, (I29-M29)) -> 0
A30: 33 | B30: =Usuarios!B34 & " " & Usuarios!C34 & " " & Usuarios!D34 -> Maria Oliva Soto Almonacid | C30: {=INDEX('01-2025'!D:D,MATCH(INDEX(A:A, ROW()), '01-2025'!A:A, 0))} -> 43 | D30: 45 | E30: =D30-C30 -> 2 | F30: 1182.6 | G30: =E30*F30 -> 2365.2 | H30: 5000 | I30: =E30*F30+H30 -> 7365.2 | J30: 45724 | L30: PAGADO | M30: =IF(L30="Pagado", I30, 0) -> 7365.2 | P30: =IF(L30="NO APLICA",0, (I30-M30)) -> 0
A31: 44 | B31: =Usuarios!B45 & " " & Usuarios!C45 & " " & Usuarios!D45 -> María Sonia Quintui | C31: {=INDEX('01-2025'!D:D,MATCH(INDEX(A:A, ROW()), '01-2025'!A:A, 0))} -> 0 | D31: 0 | E31: =D31-C31 -> 0 | F31: 1182.6 | G31: =E31*F31 -> 0 | H31: 5000 | I31: =E31*F31+H31 -> 5000 | J31: 45724 | L31: PAGADO | M31: =IF(L31="Pagado", I31, 0) -> 5000 | P31: =IF(L31="NO APLICA",0, (I31-M31)) -> 0
A32: 24 | B32: =Usuarios!B25 & " " & Usuarios!C25 & " " & Usuarios!D25 -> Maria Velasquez Miranda | C32: {=INDEX('01-2025'!D:D,MATCH(INDEX(A:A, ROW()), '01-2025'!A:A, 0))} -> 203 | D32: 227 | E32: =D32-C32 -> 24 | F32: 1182.6 | G32: =E32*F32 -> 28382.4 | H32: 5000 | I32: =E32*F32+H32 -> 33382.4 | J32: 45724 | L32: PAGADO | M32: =IF(L32="Pagado", I32, 0) -> 33382.4 | P32: =IF(L32="NO APLICA",0, (I32-M32)) -> 0
A33: 56 | B33: =Usuarios!B57 & " " & Usuarios!C57 & " " & Usuarios!D57 -> Mario Velasquez | C33: {=INDEX('01-2025'!D:D,MATCH(INDEX(A:A, ROW()), '01-2025'!A:A, 0))} -> 5 | D33: 8 | E33: =D33-C33 -> 3 | F33: 1182.6 | G33: =E33*F33 -> 3547.8 | H33: 5000 | I33: =E33*F33+H33 -> 8547.8 | J33: 45724 | L33: PENDIENTE | M33: =IF(L33="Pagado", I33, 0) -> 0 | P33: =IF(L33="NO APLICA",0, (I33-M33)) -> 8547.8
A34: 5 | B34: =Usuarios!B6 & " " & Usuarios!C6 & " " & Usuarios!D6 -> Marisol Castro | C34: {=INDEX('01-2025'!D:D,MATCH(INDEX(A:A, ROW()), '01-2025'!A:A, 0))} -> 88 | D34: 96 | E34: =D34-C34 -> 8 | F34: 1182.6 | G34: =E34*F34 -> 9460.8 | H34: 5000 | I34: =E34*F34+H34 -> 14460.8 | J34: 45724 | L34: PAGADO | M34: =IF(L34="Pagado", I34, 0) -> 14460.8 | P34: =IF(L34="NO APLICA",0, (I34-M34)) -> 0
A35: 6 | B35: =Usuarios!B7 & " " & Usuarios!C7 & " " & Usuarios!D7 -> Mauricio Muñoz | C35: {=INDEX('01-2025'!D:D,MATCH(INDEX(A:A, ROW()), '01-2025'!A:A, 0))} -> 174 | D35: 188 | E35: =D35-C35 -> 14 | F35: 1182.6 | G35: =E35*F35 -> 16556.4 | H35: 5000 | I35: =E35*F35+H35 -> 21556.4 | J35: 45724 | L35: PAGADO | M35: =IF(L35="Pagado", I35, 0) -> 21556.4 | P35: =IF(L35="NO APLICA",0, (I35-M35)) -> 0
A36: 46 | B36: =Usuarios!B47 & " " & Usuarios!C47 & " " & Usuarios!D47 -> Mauricio Muñoz taller | C36: {=INDEX('01-2025'!D:D,MATCH(INDEX(A:A, ROW()), '01-2025'!A:A, 0))} -> 0 | D36: 0 | E36: =D36-C36 -> 0 | F36: 1182.6 | G36: =E36*F36 -> 0 | H36: 5000 | I36: =E36*F36+H36 -> 5000 | J36: 45724 | L36: PAGADO | M36: =IF(L36="Pagado", I36, 0) -> 5000 | P36: =IF(L36="NO APLICA",0, (I36-M36)) -> 0
A37: 11 | B37: =Usuarios!B12 & " " & Usuarios!C12 & " " & Usuarios!D12 -> Miguel Ñanco | C37: {=INDEX('01-2025'!D:D,MATCH(INDEX(A:A, ROW()), '01-2025'!A:A, 0))} -> 189 | D37: 216 | E37: =D37-C37 -> 27 | F37: 1182.6 | G37: =E37*F37 -> 31930.2 | H37: 5000 | I37: =E37*F37+H37 -> 36930.2 | J37: 45724 | L37: PAGADO | M37: =IF(L37="Pagado", I37, 0) -> 36930.2 | P37: =IF(L37="NO APLICA",0, (I37-M37)) -> 0
A38: 29 | B38: =Usuarios!B30 & " " & Usuarios!C30 & " " & Usuarios!D30 -> Miriam Alvarado | C38: {=INDEX('01-2025'!D:D,MATCH(INDEX(A:A, ROW()), '01-2025'!A:A, 0))} -> 515 | D38: 539 | E38: =D38-C38 -> 24 | F38: 1182.6 | G38: =E38*F38 -> 28382.4 | H38: 5000 | I38: =E38*F38+H38 -> 33382.4 | J38: 45724 | L38: PAGADO | M38: =IF(L38="Pagado", I38, 0) -> 33382.4 | P38: =IF(L38="NO APLICA",0, (I38-M38)) -> 0
A39: 45 | B39: =Usuarios!B46 & " " & Usuarios!C46 & " " & Usuarios!D46 -> Monica Cuello | C39: {=INDEX('01-2025'!D:D,MATCH(INDEX(A:A, ROW()), '01-2025'!A:A, 0))} -> 0 | D39: 0 | E39: =D39-C39 -> 0 | F39: 1182.6 | G39: =E39*F39 -> 0 | H39: 5000 | I39: =E39*F39+H39 -> 5000 | J39: 45724 | L39: PAGADO | M39: =IF(L39="Pagado", I39, 0) -> 5000 | P39: =IF(L39="NO APLICA",0, (I39-M39)) -> 0
A40: 1 | B40: =Usuarios!B2 & " " & Usuarios!C2 & " " & Usuarios!D2 -> Nancy Zuñiga Villarroel | C40: {=INDEX('01-2025'!D:D,MATCH(INDEX(A:A, ROW()), '01-2025'!A:A, 0))} -> 165 | D40: 179 | E40: =D40-C40 -> 14 | F40: 1182.6 | G40: =E40*F40 -> 16556.4 | H40: 5000 | I40: =E40*F40+H40 -> 21556.4 | J40: 45724 | L40: PAGADO | M40: =IF(L40="Pagado", I40, 0) -> 21556.4 | P40: =IF(L40="NO APLICA",0, (I40-M40)) -> 0
A41: 32 | B41: =Usuarios!B33 & " " & Usuarios!C33 & " " & Usuarios!D33 -> Natividad Soto | C41: {=INDEX('01-2025'!D:D,MATCH(INDEX(A:A, ROW()), '01-2025'!A:A, 0))} -> 66 | D41: 77 | E41: =D41-C41 -> 11 | F41: 1182.6 | G41: =E41*F41 -> 13008.6 | H41: 5000 | I41: =E41*F41+H41 -> 18008.6 | J41: 45724 | L41: PAGADO | M41: =IF(L41="Pagado", I41, 0) -> 18008.6 | P41: =IF(L41="NO APLICA",0, (I41-M41)) -> 0
A42: 18 | B42: =Usuarios!B19 & " " & Usuarios!C19 & " " & Usuarios!D19 -> Nelson Mansilla | C42: {=INDEX('01-2025'!D:D,MATCH(INDEX(A:A, ROW()), '01-2025'!A:A, 0))} -> 113 | D42: 120 | E42: =D42-C42 -> 7 | F42: 1182.6 | G42: =E42*F42 -> 8278.2 | H42: 5000 | I42: =E42*F42+H42 -> 13278.2 | J42: 45724 | L42: PAGADO | M42: =IF(L42="Pagado", I42, 0) -> 13278.2 | P42: =IF(L42="NO APLICA",0, (I42-M42)) -> 0
A43: 53 | B43: =Usuarios!B54 & " " & Usuarios!C54 & " " & Usuarios!D54 -> Nicolas Andres Cardenas Bustamante | C43: {=INDEX('01-2025'!D:D,MATCH(INDEX(A:A, ROW()), '01-2025'!A:A, 0))} -> 0 | D43: 0 | E43: =D43-C43 -> 0 | F43: 1182.6 | G43: =E43*F43 -> 0 | H43: 5000 | I43: =E43*F43+H43 -> 5000 | J43: 45724 | L43: PAGADO | M43: =IF(L43="Pagado", I43, 0) -> 5000 | P43: =IF(L43="NO APLICA",0, (I43-M43)) -> 0
A44: 28 | B44: =Usuarios!B29 & " " & Usuarios!C29 & " " & Usuarios!D29 -> Nora Ñanco | C44: {=INDEX('01-2025'!D:D,MATCH(INDEX(A:A, ROW()), '01-2025'!A:A, 0))} -> 381 | D44: 400 | E44: =D44-C44 -> 19 | F44: 1182.6 | G44: =E44*F44 -> 22469.4 | H44: 5000 | I44: =E44*F44+H44 -> 27469.4 | J44: 45724 | L44: PAGADO | M44: =IF(L44="Pagado", I44, 0) -> 27469.4 | P44: =IF(L44="NO APLICA",0, (I44-M44)) -> 0
A45: 38 | B45: =Usuarios!B39 & " " & Usuarios!C39 & " " & Usuarios!D39 -> Norma Sanchez | C45: {=INDEX('01-2025'!D:D,MATCH(INDEX(A:A, ROW()), '01-2025'!A:A, 0))} -> 0 | D45: 0 | E45: =D45-C45 -> 0 | F45: 1182.6 | G45: =E45*F45 -> 0 | H45: 5000 | I45: =E45*F45+H45 -> 5000 | J45: 45724 | L45: PAGADO | M45: =IF(L45="Pagado", I45, 0) -> 5000 | P45: =IF(L45="NO APLICA",0, (I45-M45)) -> 0
A46: 47 | B46: =Usuarios!B48 & " " & Usuarios!C48 & " " & Usuarios!D48 -> Pablo Contreras | C46: {=INDEX('01-2025'!D:D,MATCH(INDEX(A:A, ROW()), '01-2025'!A:A, 0))} -> 0 | D46: 0 | E46: =D46-C46 -> 0 | F46: 1182.6 | G46: =E46*F46 -> 0 | H46: 5000 | I46: =E46*F46+H46 -> 5000 | J46: 45724 | L46: PAGADO | M46: =IF(L46="Pagado", I46, 0) -> 5000 | P46: =IF(L46="NO APLICA",0, (I46-M46)) -> 0
A47: 31 | B47: =Usuarios!B32 & " " & Usuarios!C32 & " " & Usuarios!D32 -> Patricia Carcamo Gonzales | C47: {=INDEX('01-2025'!D:D,MATCH(INDEX(A:A, ROW()), '01-2025'!A:A, 0))} -> 113 | D47: 138 | E47: =D47-C47 -> 25 | F47: 1182.6 | G47: =E47*F47 -> 29565 | H47: 5000 | I47: =E47*F47+H47 -> 34565 | J47: 45724 | L47: PAGADO | M47: =IF(L47="Pagado", I47, 0) -> 34565 | P47: =IF(L47="NO APLICA",0, (I47-M47)) -> 0
A48: 37 | B48: =Usuarios!B38 & " " & Usuarios!C38 & " " & Usuarios!D38 -> Patricio Alvarez Mancilla | C48: {=INDEX('01-2025'!D:D,MATCH(INDEX(A:A, ROW()), '01-2025'!A:A, 0))} -> 0 | D48: 0 | E48: =D48-C48 -> 0 | F48: 1182.6 | G48: =E48*F48 -> 0 | H48: 5000 | I48: =E48*F48+H48 -> 5000 | J48: 45724 | L48: PENDIENTE | M48: =IF(L48="Pagado", I48, 0) -> 0 | P48: =IF(L48="NO APLICA",0, (I48-M48)) -> 5000
A49: 27 | B49: =Usuarios!B28 & " " & Usuarios!C28 & " " & Usuarios!D28 -> Pedro Almonacid | C49: {=INDEX('01-2025'!D:D,MATCH(INDEX(A:A, ROW()), '01-2025'!A:A, 0))} -> 177 | D49: 189 | E49: =D49-C49 -> 12 | F49: 1182.6 | G49: =E49*F49 -> 14191.2 | H49: 5000 | I49: =E49*F49+H49 -> 19191.2 | J49: 45724 | L49: PENDIENTE | M49: =IF(L49="Pagado", I49, 0) -> 0 | P49: =IF(L49="NO APLICA",0, (I49-M49)) -> 19191.2
A50: 12 | B50: =Usuarios!B13 & " " & Usuarios!C13 & " " & Usuarios!D13 -> Pedro Contreras | C50: {=INDEX('01-2025'!D:D,MATCH(INDEX(A:A, ROW()), '01-2025'!A:A, 0))} -> 97 | D50: 103 | E50: =D50-C50 -> 6 | F50: 1182.6 | G50: =E50*F50 -> 7095.6 | H50: 5000 | I50: =E50*F50+H50 -> 12095.6 | J50: 45724 | L50: PAGADO | M50: =IF(L50="Pagado", I50, 0) -> 12095.6 | P50: =IF(L50="NO APLICA",0, (I50-M50)) -> 0
A51: 43 | B51: =Usuarios!B44 & " " & Usuarios!C44 & " " & Usuarios!D44 -> Ramon Maldonado | C51: {=INDEX('01-2025'!D:D,MATCH(INDEX(A:A, ROW()), '01-2025'!A:A, 0))} -> 0 | D51: 0 | E51: =D51-C51 -> 0 | F51: 1182.6 | G51: =E51*F51 -> 0 | H51: 5000 | I51: =E51*F51+H51 -> 5000 | J51: 45724 | L51: PAGADO | M51: =IF(L51="Pagado", I51, 0) -> 5000 | O51: TRANSFERENCIA | P51: =IF(L51="NO APLICA",0, (I51-M51)) -> 0
A52: 14 | B52: =Usuarios!B15 & " " & Usuarios!C15 & " " & Usuarios!D15 -> Ramona Mansilla | C52: {=INDEX('01-2025'!D:D,MATCH(INDEX(A:A, ROW()), '01-2025'!A:A, 0))} -> 40 | D52: 43 | E52: =D52-C52 -> 3 | F52: 1182.6 | G52: =E52*F52 -> 3547.8 | H52: 5000 | I52: =E52*F52+H52 -> 8547.8 | J52: 45724 | L52: PAGADO | M52: =IF(L52="Pagado", I52, 0) -> 8547.8 | P52: =IF(L52="NO APLICA",0, (I52-M52)) -> 0
A53: 54 | B53: =Usuarios!B55 & " " & Usuarios!C55 & " " & Usuarios!D55 -> Rosa Mancilla | C53: {=INDEX('01-2025'!D:D,MATCH(INDEX(A:A, ROW()), '01-2025'!A:A, 0))} -> 106 | D53: 106 | E53: =D53-C53 -> 0 | F53: 1182.6 | G53: =E53*F53 -> 0 | H53: 5000 | I53: =E53*F53+H53 -> 5000 | J53: 45724 | L53: PENDIENTE | M53: =IF(L53="Pagado", I53, 0) -> 0 | P53: =IF(L53="NO APLICA",0, (I53-M53)) -> 5000
A54: 49 | B54: =Usuarios!B50 & " " & Usuarios!C50 & " " & Usuarios!D50 -> Rosa Nuñez | C54: {=INDEX('01-2025'!D:D,MATCH(INDEX(A:A, ROW()), '01-2025'!A:A, 0))} -> 70 | D54: 76 | E54: =D54-C54 -> 6 | F54: 1182.6 | G54: =E54*F54 -> 7095.6 | H54: 5000 | I54: =E54*F54+H54 -> 12095.6 | J54: 45724 | L54: PENDIENTE | M54: =IF(L54="Pagado", I54, 0) -> 0 | P54: =IF(L54="NO APLICA",0, (I54-M54)) -> 12095.6
A55: 15 | B55: =Usuarios!B16 & " " & Usuarios!C16 & " " & Usuarios!D16 -> Sandra Mancilla Merino | C55: {=INDEX('01-2025'!D:D,MATCH(INDEX(A:A, ROW()), '01-2025'!A:A, 0))} -> 116 | D55: 127 | E55: =D55-C55 -> 11 | F55: 1182.6 | G55: =E55*F55 -> 13008.6 | H55: 5000 | I55: =E55*F55+H55 -> 18008.6 | J55: 45724 | L55: PENDIENTE | M55: =IF(L55="Pagado", I55, 0) -> 0 | P55: =IF(L55="NO APLICA",0, (I55-M55)) -> 18008.6
A56: 34 | B56: =Usuarios!B35 & " " & Usuarios!C35 & " " & Usuarios!D35 -> Vanesa Aguilar | C56: {=INDEX('01-2025'!D:D,MATCH(INDEX(A:A, ROW()), '01-2025'!A:A, 0))} -> 452 | D56: 487 | E56: =D56-C56 -> 35 | F56: 1182.6 | G56: =E56*F56 -> 41391 | H56: 5000 | I56: =E56*F56+H56 -> 46391 | J56: 45724 | L56: PENDIENTE | M56: =IF(L56="Pagado", I56, 0) -> 0 | P56: =IF(L56="NO APLICA",0, (I56-M56)) -> 46391
A57: 22 | B57: =Usuarios!B23 & " " & Usuarios!C23 & " " & Usuarios!D23 -> Yuri Millaquen | C57: {=INDEX('01-2025'!D:D,MATCH(INDEX(A:A, ROW()), '01-2025'!A:A, 0))} -> 130 | D57: 142 | E57: =D57-C57 -> 12 | F57: 1182.6 | G57: =E57*F57 -> 14191.2 | H57: 5000 | I57: =E57*F57+H57 -> 19191.2 | J57: 45724 | L57: PAGADO | M57: =IF(L57="Pagado", I57, 0) -> 19191.2 | P57: =IF(L57="NO APLICA",0, (I57-M57)) -> 0

Sheet 03-2025
A1: ID | B1: Nombre | C1: Lectura_Anterior | D1: Lectura_Actual | E1: Consumo_m3 | F1: Tarifa_m3 | G1: Subtotal_Consumo | H1: Cargo_Fijo | I1: Total_Factura | J1: Fecha_Lectura | K1: Periodo | L1: Estado_Pago | M1: Monto_Pagado | N1: Fecha_Pago | O1: Forma_Pago | P1: Saldo_Pendiente | Q1: comprobante_link
A2: 1 | B2: =Usuarios!B2 & " " & Usuarios!C2 & " " & Usuarios!D2 -> Nancy Zuñiga Villarroel | C2: =INDEX(INDIRECT("'" & TEXT(EDATE(J2,-2),"mm-yyyy") & "'!D:D"), MATCH(A2,INDIRECT("'" & TEXT(EDATE(J2,-2),"mm-yyyy") & "'!A:A"),0)) -> 179 | D2: 193 | E2: =D2-C2 -> 14 | F2: 1182.6 | G2: =E2*F2 -> 16556.4 | H2: 5000 | I2: =E2*F2+H2 -> 21556.4 | J2: 45755 | L2: PAGADO | M2: =IF(L2="Pagado", I2, 0) -> 21556.4 | P2: =IF(L2="NO APLICA",0, (I2-M2)) -> 0
A3: 2 | B3: =Usuarios!B3 & " " & Usuarios!C3 & " " & Usuarios!D3 -> Gabriel Barria Zuñiga | C3: =INDEX(INDIRECT("'" & TEXT(EDATE(J3,-2),"mm-yyyy") & "'!D:D"), MATCH(A3,INDIRECT("'" & TEXT(EDATE(J3,-2),"mm-yyyy") & "'!A:A"),0)) -> 270 | D3: 292 | E3: =D3-C3 -> 22 | F3: 1182.6 | G3: =E3*F3 -> 26017.2 | H3: 5000 | I3: =E3*F3+H3 -> 31017.2 | J3: 45755 | L3: PAGADO | M3: =IF(L3="Pagado", I3, 0) -> 31017.2 | P3: =IF(L3="NO APLICA",0, (I3-M3)) -> 0
A4: 3 | B4: =Usuarios!B4 & " " & Usuarios!C4 & " " & Usuarios!D4 -> Gino Reyes | C4: =INDEX(INDIRECT("'" & TEXT(EDATE(J4,-2),"mm-yyyy") & "'!D:D"), MATCH(A4,INDIRECT("'" & TEXT(EDATE(J4,-2),"mm-yyyy") & "'!A:A"),0)) -> 60 | D4: 66 | E4: =D4-C4 -> 6 | F4: 1182.6 | G4: =E4*F4 -> 7095.6 | H4: 5000 | I4: =E4*F4+H4 -> 12095.6 | J4: 45755 | L4: PENDIENTE | M4: =IF(L4="Pagado", I4, 0) -> 0 | P4: =IF(L4="NO APLICA",0, (I4-M4)) -> 12095.6
A5: 4 | B5: =Usuarios!B5 & " " & Usuarios!C5 & " " & Usuarios!D5 -> Cristian Oyarzo | C5: =INDEX(INDIRECT("'" & TEXT(EDATE(J5,-2),"mm-yyyy") & "'!D:D"), MATCH(A5,INDIRECT("'" & TEXT(EDATE(J5,-2),"mm-yyyy") & "'!A:A"),0)) -> 455 | D5: 493 | E5: =D5-C5 -> 38 | F5: 1182.6 | G5: =E5*F5 -> 44938.8 | H5: 5000 | I5: =E5*F5+H5 -> 49938.8 | J5: 45755 | L5: PAGADO | M5: =IF(L5="Pagado", I5, 0) -> 49938.8 | P5: =IF(L5="NO APLICA",0, (I5-M5)) -> 0
A6: 5 | B6: =Usuarios!B6 & " " & Usuarios!C6 & " " & Usuarios!D6 -> Marisol Castro | C6: =INDEX(INDIRECT("'" & TEXT(EDATE(J6,-2),"mm-yyyy") & "'!D:D"), MATCH(A6,INDIRECT("'" & TEXT(EDATE(J6,-2),"mm-yyyy") & "'!A:A"),0)) -> 96 | D6: 105 | E6: =D6-C6 -> 9 | F6: 1182.6 | G6: =E6*F6 -> 10643.4 | H6: 5000 | I6: =E6*F6+H6 -> 15643.4 | J6: 45755 | L6: PAGADO | M6: =IF(L6="Pagado", I6, 0) -> 15643.4 | P6: =IF(L6="NO APLICA",0, (I6-M6)) -> 0
A7: 6 | B7: =Usuarios!B7 & " " & Usuarios!C7 & " " & Usuarios!D7 -> Mauricio Muñoz | C7: =INDEX(INDIRECT("'" & TEXT(EDATE(J7,-2),"mm-yyyy") & "'!D:D"), MATCH(A7,INDIRECT("'" & TEXT(EDATE(J7,-2),"mm-yyyy") & "'!A:A"),0)) -> 188 | D7: 198 | E7: =D7-C7 -> 10 | F7: 1182.6 | G7: =E7*F7 -> 11826 | H7: 5000 | I7: =E7*F7+H7 -> 16826 | J7: 45755 | L7: PAGADO | M7: =IF(L7="Pagado", I7, 0) -> 16826 | P7: =IF(L7="NO APLICA",0, (I7-M7)) -> 0
A8: 7 | B8: =Usuarios!B8 & " " & Usuarios!C8 & " " & Usuarios!D8 -> Marcelo Millanao | C8: =INDEX(INDIRECT("'" & TEXT(EDATE(J8,-2),"mm-yyyy") & "'!D:D"), MATCH(A8,INDIRECT("'" & TEXT(EDATE(J8,-2),"mm-yyyy") & "'!A:A"),0)) -> 224 | D8: 238 | E8: =D8-C8 -> 14 | F8: 1182.6 | G8: =E8*F8 -> 16556.4 | H8: 5000 | I8: =E8*F8+H8 -> 21556.4 | J8: 45755 | L8: PAGADO | M8: =IF(L8="Pagado", I8, 0) -> 21556.4 | P8: =IF(L8="NO APLICA",0, (I8-M8)) -> 0
A9: 8 | B9: =Usuarios!B9 & " " & Usuarios!C9 & " " & Usuarios!D9 -> Gabriel Farias | C9: =INDEX(INDIRECT("'" & TEXT(EDATE(J9,-2),"mm-yyyy") & "'!D:D"), MATCH(A9,INDIRECT("'" & TEXT(EDATE(J9,-2),"mm-yyyy") & "'!A:A"),0)) -> 399 | D9: 432 | E9: =D9-C9 -> 33 | F9: 1182.6 | G9: =E9*F9 -> 39025.8 | H9: 5000 | I9: =E9*F9+H9 -> 44025.8 | J9: 45755 | L9: PAGADO | M9: =IF(L9="Pagado", I9, 0) -> 44025.8 | P9: =IF(L9="NO APLICA",0, (I9-M9)) -> 0
A10: 9 | B10: =Usuarios!B10 & " " & Usuarios!C10 & " " & Usuarios!D10 -> Maria Marin | C10: =INDEX(INDIRECT("'" & TEXT(EDATE(J10,-2),"mm-yyyy") & "'!D:D"), MATCH(A10,INDIRECT("'" & TEXT(EDATE(J10,-2),"mm-yyyy") & "'!A:A"),0)) -> 153 | D10: 177 | E10: =D10-C10 -> 24 | F10: 1182.6 | G10: =E10*F10 -> 28382.4 | H10: 5000 | I10: =E10*F10+H10 -> 33382.4 | J10: 45755 | L10: PAGADO | M10: =IF(L10="Pagado", I10, 0) -> 33382.4 | P10: =IF(L10="NO APLICA",0, (I10-M10)) -> 0
A11: 10 | B11: =Usuarios!B11 & " " & Usuarios!C11 & " " & Usuarios!D11 -> David Cartes | C11: =INDEX(INDIRECT("'" & TEXT(EDATE(J11,-2),"mm-yyyy") & "'!D:D"), MATCH(A11,INDIRECT("'" & TEXT(EDATE(J11,-2),"mm-yyyy") & "'!A:A"),0)) -> 104 | D11: 112 | E11: =D11-C11 -> 8 | F11: 1182.6 | G11: =E11*F11 -> 9460.8 | H11: 5000 | I11: =E11*F11+H11 -> 14460.8 | J11: 45755 | L11: PAGADO | M11: =IF(L11="Pagado", I11, 0) -> 14460.8 | P11: =IF(L11="NO APLICA",0, (I11-M11)) -> 0
A12: 11 | B12: =Usuarios!B12 & " " & Usuarios!C12 & " " & Usuarios!D12 -> Miguel Ñanco | C12: =INDEX(INDIRECT("'" & TEXT(EDATE(J12,-2),"mm-yyyy") & "'!D:D"), MATCH(A12,INDIRECT("'" & TEXT(EDATE(J12,-2),"mm-yyyy") & "'!A:A"),0)) -> 216 | D12: 240 | E12: =D12-C12 -> 24 | F12: 1182.6 | G12: =E12*F12 -> 28382.4 | H12: 5000 | I12: =E12*F12+H12 -> 33382.4 | J12: 45755 | L12: PAGADO | M12: =IF(L12="Pagado", I12, 0) -> 33382.4 | P12: =IF(L12="NO APLICA",0, (I12-M12)) -> 0
A13: 12 | B13: =Usuarios!B13 & " " & Usuarios!C13 & " " & Usuarios!D13 -> Pedro Contreras | C13: =INDEX(INDIRECT("'" & TEXT(EDATE(J13,-2),"mm-yyyy") & "'!D:D"), MATCH(A13,INDIRECT("'" & TEXT(EDATE(J13,-2),"mm-yyyy") & "'!A:A"),0)) -> 103 | D13: 109 | E13: =D13-C13 -> 6 | F13: 1182.6 | G13: =E13*F13 -> 7095.6 | H13: 5000 | I13: =E13*F13+H13 -> 12095.6 | J13: 45755 | L13: PENDIENTE | M13: =IF(L13="Pagado", I13, 0) -> 0 | P13: =IF(L13="NO APLICA",0, (I13-M13)) -> 12095.6
... A43: 42 | B43: =Usuarios!B43 & " " & Usuarios!C43 & " " & Usuarios!D43 -> Leo Soto | C43: =INDEX(INDIRECT("'" & TEXT(EDATE(J43,-2),"mm-yyyy") & "'!D:D"), MATCH(A43,INDIRECT("'" & TEXT(EDATE(J43,-2),"mm-yyyy") & "'!A:A"),0)) -> 0 | D43: 10 | E43: =D43-C43 -> 10 | F43: 1182.6 | G43: =E43*F43 -> 11826 | H43: 5000 | I43: =E43*F43+H43 -> 16826 | J43: 45755 | L43: PENDIENTE | M43: =IF(L43="Pagado", I43, 0) -> 0 | P43: =IF(L43="NO APLICA",0, (I43-M43)) -> 16826
A44: 43 | B44: =Usuarios!B44 & " " & Usuarios!C44 & " " & Usuarios!D44 -> Ramon Maldonado | C44: =INDEX(INDIRECT("'" & TEXT(EDATE(J44,-2),"mm-yyyy") & "'!D:D"), MATCH(A44,INDIRECT("'" & TEXT(EDATE(J44,-2),"mm-yyyy") & "'!A:A"),0)) -> 0 | D44: 0 | E44: =D44-C44 -> 0 | F44: 1182.6 | G44: =E44*F44 -> 0 | H44: 5000 | I44: =E44*F44+H44 -> 5000 | J44: 45755 | L44: PAGADO | M44: =IF(L44="Pagado", I44, 0) -> 5000 | O44: TRANSFERENCIA | P44: =IF(L44="NO APLICA",0, (I44-M44)) -> 0
A45: 44 | B45: =Usuarios!B45 & " " & Usuarios!C45 & " " & Usuarios!D45 -> María Sonia Quintui | C45: =INDEX(INDIRECT("'" & TEXT(EDATE(J45,-2),"mm-yyyy") & "'!D:D"), MATCH(A45,INDIRECT("'" & TEXT(EDATE(J45,-2),"mm-yyyy") & "'!A:A"),0)) -> 0 | D45: 0 | E45: =D45-C45 -> 0 | F45: 1182.6 | G45: =E45*F45 -> 0 | H45: 5000 | I45: =E45*F45+H45 -> 5000 | J45: 45755 | L45: PAGADO | M45: =IF(L45="Pagado", I45, 0) -> 5000 | P45: =IF(L45="NO APLICA",0, (I45-M45)) -> 0
A46: 45 | B46: =Usuarios!B46 & " " & Usuarios!C46 & " " & Usuarios!D46 -> Monica Cuello | C46: =INDEX(INDIRECT("'" & TEXT(EDATE(J46,-2),"mm-yyyy") & "'!D:D"), MATCH(A46,INDIRECT("'" & TEXT(EDATE(J46,-2),"mm-yyyy") & "'!A:A"),0)) -> 0 | D46: 0 | E46: =D46-C46 -> 0 | F46: 1182.6 | G46: =E46*F46 -> 0 | H46: 5000 | I46: =E46*F46+H46 -> 5000 | J46: 45755 | L46: PENDIENTE | M46: =IF(L46="Pagado", I46, 0) -> 0 | P46: =IF(L46="NO APLICA",0, (I46-M46)) -> 5000
A47: 46 | B47: =Usuarios!B47 & " " & Usuarios!C47 & " " & Usuarios!D47 -> Mauricio Muñoz taller | C47: =INDEX(INDIRECT("'" & TEXT(EDATE(J47,-2),"mm-yyyy") & "'!D:D"), MATCH(A47,INDIRECT("'" & TEXT(EDATE(J47,-2),"mm-yyyy") & "'!A:A"),0)) -> 0 | D47: 0 | E47: =D47-C47 -> 0 | F47: 1182.6 | G47: =E47*F47 -> 0 | H47: 5000 | I47: =E47*F47+H47 -> 5000 | J47: 45755 | L47: PENDIENTE | M47: =IF(L47="Pagado", I47, 0) -> 0 | P47: =IF(L47="NO APLICA",0, (I47-M47)) -> 5000
A48: 47 | B48: =Usuarios!B48 & " " & Usuarios!C48 & " " & Usuarios!D48 -> Pablo Contreras | C48: =INDEX(INDIRECT("'" & TEXT(EDATE(J48,-2),"mm-yyyy") & "'!D:D"), MATCH(A48,INDIRECT("'" & TEXT(EDATE(J48,-2),"mm-yyyy") & "'!A:A"),0)) -> 0 | D48: 0 | E48: =D48-C48 -> 0 | F48: 1182.6 | G48: =E48*F48 -> 0 | H48: 5000 | I48: =E48*F48+H48 -> 5000 | J48: 45755 | L48: PAGADO | M48: =IF(L48="Pagado", I48, 0) -> 5000 | P48: =IF(L48="NO APLICA",0, (I48-M48)) -> 0
A49: 48 | B49: =Usuarios!B49 & " " & Usuarios!C49 & " " & Usuarios!D49 -> Luis Vicente Mondaca Muñoz | C49: =INDEX(INDIRECT("'" & TEXT(EDATE(J49,-2),"mm-yyyy") & "'!D:D"), MATCH(A49,INDIRECT("'" & TEXT(EDATE(J49,-2),"mm-yyyy") & "'!A:A"),0)) -> 249 | D49: 281 | E49: =D49-C49 -> 32 | F49: 1182.6 | G49: =E49*F49 -> 37843.2 | H49: 5000 | I49: =E49*F49+H49 -> 42843.2 | J49: 45755 | L49: PAGADO | M49: =IF(L49="Pagado", I49, 0) -> 42843.2 | P49: =IF(L49="NO APLICA",0, (I49-M49)) -> 0
A50: 49 | B50: =Usuarios!B50 & " " & Usuarios!C50 & " " & Usuarios!D50 -> Rosa Nuñez | C50: =INDEX(INDIRECT("'" & TEXT(EDATE(J50,-2),"mm-yyyy") & "'!D:D"), MATCH(A50,INDIRECT("'" & TEXT(EDATE(J50,-2),"mm-yyyy") & "'!A:A"),0)) -> 76 | D50: 80 | E50: =D50-C50 -> 4 | F50: 1182.6 | G50: =E50*F50 -> 4730.4 | H50: 5000 | I50: =E50*F50+H50 -> 9730.4 | J50: 45755 | L50: PENDIENTE | M50: =IF(L50="Pagado", I50, 0) -> 0 | P50: =IF(L50="NO APLICA",0, (I50-M50)) -> 9730.4
A51: 50 | B51: =Usuarios!B51 & " " & Usuarios!C51 & " " & Usuarios!D51 -> Gloria Isamar Velasquez Almonacid | C51: =INDEX(INDIRECT("'" & TEXT(EDATE(J51,-2),"mm-yyyy") & "'!D:D"), MATCH(A51,INDIRECT("'" & TEXT(EDATE(J51,-2),"mm-yyyy") & "'!A:A"),0)) -> 24 | D51: 35 | E51: =D51-C51 -> 11 | F51: 1182.6 | G51: =E51*F51 -> 13008.6 | H51: 5000 | I51: =E51*F51+H51 -> 18008.6 | J51: 45755 | L51: PENDIENTE | M51: =IF(L51="Pagado", I51, 0) -> 0 | P51: =IF(L51="NO APLICA",0, (I51-M51)) -> 18008.6
A52: 51 | B52: =Usuarios!B52 & " " & Usuarios!C52 & " " & Usuarios!D52 -> Maria Manquian | C52: =INDEX(INDIRECT("'" & TEXT(EDATE(J52,-2),"mm-yyyy") & "'!D:D"), MATCH(A52,INDIRECT("'" & TEXT(EDATE(J52,-2),"mm-yyyy") & "'!A:A"),0)) -> 0 | D52: 0 | E52: =D52-C52 -> 0 | F52: 1182.6 | G52: =E52*F52 -> 0 | H52: 5000 | I52: =E52*F52+H52 -> 5000 | J52: 45755 | L52: PAGADO | M52: =IF(L52="Pagado", I52, 0) -> 5000 | O52: TRANSFERENCIA | P52: =IF(L52="NO APLICA",0, (I52-M52)) -> 0
A53: 52 | B53: =Usuarios!B53 & " " & Usuarios!C53 & " " & Usuarios!D53 -> Esteban Oyarzo Levil | C53: =INDEX(INDIRECT("'" & TEXT(EDATE(J53,-2),"mm-yyyy") & "'!D:D"), MATCH(A53,INDIRECT("'" & TEXT(EDATE(J53,-2),"mm-yyyy") & "'!A:A"),0)) -> 0 | D53: 0 | E53: =D53-C53 -> 0 | F53: 1182.6 | G53: =E53*F53 -> 0 | H53: 5000 | I53: =E53*F53+H53 -> 5000 | J53: 45755 | L53: PENDIENTE | M53: =IF(L53="Pagado", I53, 0) -> 0 | P53: =IF(L53="NO APLICA",0, (I53-M53)) -> 5000
A54: 53 | B54: =Usuarios!B54 & " " & Usuarios!C54 & " " & Usuarios!D54 -> Nicolas Andres Cardenas Bustamante | C54: =INDEX(INDIRECT("'" & TEXT(EDATE(J54,-2),"mm-yyyy") & "'!D:D"), MATCH(A54,INDIRECT("'" & TEXT(EDATE(J54,-2),"mm-yyyy") & "'!A:A"),0)) -> 0 | D54: 0 | E54: =D54-C54 -> 0 | F54: 1182.6 | G54: =E54*F54 -> 0 | H54: 5000 | I54: =E54*F54+H54 -> 5000 | J54: 45755 | L54: PAGADO | M54: =IF(L54="Pagado", I54, 0) -> 5000 | P54: =IF(L54="NO APLICA",0, (I54-M54)) -> 0
A55: 54 | B55: =Usuarios!B55 & " " & Usuarios!C55 & " " & Usuarios!D55 -> Rosa Mancilla | C55: =INDEX(INDIRECT("'" & TEXT(EDATE(J55,-2),"mm-yyyy") & "'!D:D"), MATCH(A55,INDIRECT("'" & TEXT(EDATE(J55,-2),"mm-yyyy") & "'!A:A"),0)) -> 106 | D55: 106 | E55: =D55-C55 -> 0 | F55: 1182.6 | G55: =E55*F55 -> 0 | H55: 5000 | I55: =E55*F55+H55 -> 5000 | J55: 45755 | L55: PENDIENTE | M55: =IF(L55="Pagado", I55, 0) -> 0 | P55: =IF(L55="NO APLICA",0, (I55-M55)) -> 5000
A56: 55 | B56: =Usuarios!B56 & " " & Usuarios!C56 & " " & Usuarios!D56 -> Guido Quintuy - Sitio vacío | C56: =INDEX(INDIRECT("'" & TEXT(EDATE(J56,-2),"mm-yyyy") & "'!D:D"), MATCH(A56,INDIRECT("'" & TEXT(EDATE(J56,-2),"mm-yyyy") & "'!A:A"),0)) -> 0 | D56: 0 | E56: =D56-C56 -> 0 | F56: 1182.6 | G56: =E56*F56 -> 0 | H56: 5000 | I56: =E56*F56+H56 -> 5000 | J56: 45755 | L56: PENDIENTE | M56: =IF(L56="Pagado", I56, 0) -> 0 | P56: =IF(L56="NO APLICA",0, (I56-M56)) -> 5000
A57: 56 | B57: =Usuarios!B57 & " " & Usuarios!C57 & " " & Usuarios!D57 -> Mario Velasquez | C57: =INDEX(INDIRECT("'" & TEXT(EDATE(J57,-2),"mm-yyyy") & "'!D:D"), MATCH(A57,INDIRECT("'" & TEXT(EDATE(J57,-2),"mm-yyyy") & "'!A:A"),0)) -> 8 | D57: 17 | E57: =D57-C57 -> 9 | F57: 1182.6 | G57: =E57*F57 -> 10643.4 | H57: 5000 | I57: =E57*F57+H57 -> 15643.4 | J57: 45755 | L57: PAGADO | M57: =IF(L57="Pagado", I57, 0) -> 15643.4 | P57: =IF(L57="NO APLICA",0, (I57-M57)) -> 0
A58: 57 | B58: =Usuarios!B58 & " " & Usuarios!C58 & " " & Usuarios!D58 -> Lishby Fuentes Diaz | C58: =INDEX(INDIRECT("'" & TEXT(EDATE(J58,-2),"mm-yyyy") & "'!D:D"), MATCH(A58,INDIRECT("'" & TEXT(EDATE(J58,-2),"mm-yyyy") & "'!A:A"),0)) -> 0 | D58: 0 | E58: =D58-C58 -> 0 | F58: 1182.6 | G58: =E58*F58 -> 0 | H58: 5000 | I58: =E58*F58+H58 -> 5000 | J58: 45755 | L58: NO APLICA | M58: =IF(L58="Pagado", I58, 0) -> 0 | P58: =IF(L58="NO APLICA",0, (I58-M58)) -> 0

Sheet 04-2025
A1: ID | B1: Nombre | C1: Lectura_Anterior | D1: Lectura_Actual | E1: Consumo_m3 | F1: Tarifa_m3 | G1: Subtotal_Consumo | H1: Cargo_Fijo | I1: Total_Factura | J1: Fecha_Lectura | K1: Periodo | L1: Estado_Pago | M1: Monto_Pagado | N1: Fecha_Pago | O1: Forma_Pago | P1: Saldo_Pendiente | Q1: comprobante_link
A2: 1 | B2: =Usuarios!B2 & " " & Usuarios!C2 & " " & Usuarios!D2 -> Nancy Zuñiga Villarroel | C2: =INDEX(INDIRECT("'" & TEXT(EDATE(J2,-2),"mm-yyyy") & "'!D:D"), MATCH(A2,INDIRECT("'" & TEXT(EDATE(J2,-2),"mm-yyyy") & "'!A:A"),0)) -> 193 | D2: 200 | E2: =D2-C2 -> 7 | F2: 1182.6 | G2: =E2*F2 -> 8278.2 | H2: 5000 | I2: =E2*F2+H2 -> 13278.2 | J2: 45785 | L2: PENDIENTE | M2: =IF(L2="Pagado", I2, 0) -> 0 | P2: =IF(L2="NO APLICA",0, (I2-M2)) -> 13278.2
A3: 2 | B3: =Usuarios!B3 & " " & Usuarios!C3 & " " & Usuarios!D3 -> Gabriel Barria Zuñiga | C3: =INDEX(INDIRECT("'" & TEXT(EDATE(J3,-2),"mm-yyyy") & "'!D:D"), MATCH(A3,INDIRECT("'" & TEXT(EDATE(J3,-2),"mm-yyyy") & "'!A:A"),0)) -> 292 | D3: 309 | E3: =D3-C3 -> 17 | F3: 1182.6 | G3: =E3*F3 -> 20104.2 | H3: 5000 | I3: =E3*F3+H3 -> 25104.2 | J3: 45785 | L3: PAGADO | M3: =IF(L3="Pagado", I3, 0) -> 25104.2 | P3: =IF(L3="NO APLICA",0, (I3-M3)) -> 0
A4: 3 | B4: =Usuarios!B4 & " " & Usuarios!C4 & " " & Usuarios!D4 -> Gino Reyes | C4: =INDEX(INDIRECT("'" & TEXT(EDATE(J4,-2),"mm-yyyy") & "'!D:D"), MATCH(A4,INDIRECT("'" & TEXT(EDATE(J4,-2),"mm-yyyy") & "'!A:A"),0)) -> 66 | D4: 69 | E4: =D4-C4 -> 3 | F4: 1182.6 | G4: =E4*F4 -> 3547.8 | H4: 5000 | I4: =E4*F4+H4 -> 8547.8 | J4: 45785 | L4: PENDIENTE | M4: =IF(L4="Pagado", I4, 0) -> 0 | P4: =IF(L4="NO APLICA",0, (I4-M4)) -> 8547.8
A5: 4 | B5: =Usuarios!B5 & " " & Usuarios!C5 & " " & Usuarios!D5 -> Cristian Oyarzo | C5: =INDEX(INDIRECT("'" & TEXT(EDATE(J5,-2),"mm-yyyy") & "'!D:D"), MATCH(A5,INDIRECT("'" & TEXT(EDATE(J5,-2),"mm-yyyy") & "'!A:A"),0)) -> 493 | D5: 518 | E5: =D5-C5 -> 25 | F5: 1182.6 | G5: =E5*F5 -> 29565 | H5: 5000 | I5: =E5*F5+H5 -> 34565 | J5: 45785 | L5: PENDIENTE | M5: =IF(L5="Pagado", I5, 0) -> 0 | P5: =IF(L5="NO APLICA",0, (I5-M5)) -> 34565
A6: 5 | B6: =Usuarios!B6 & " " & Usuarios!C6 & " " & Usuarios!D6 -> Marisol Castro | C6: =INDEX(INDIRECT("'" & TEXT(EDATE(J6,-2),"mm-yyyy") & "'!D:D"), MATCH(A6,INDIRECT("'" & TEXT(EDATE(J6,-2),"mm-yyyy") & "'!A:A"),0)) -> 105 | D6: 110 | E6: =D6-C6 -> 5 | F6: 1182.6 | G6: =E6*F6 -> 5913 | H6: 5000 | I6: =E6*F6+H6 -> 10913 | J6: 45785 | L6: PAGADO | M6: =IF(L6="Pagado", I6, 0) -> 10913 | P6: =IF(L6="NO APLICA",0, (I6-M6)) -> 0
A7: 6 | B7: =Usuarios!B7 & " " & Usuarios!C7 & " " & Usuarios!D7 -> Mauricio Muñoz | C7: =INDEX(INDIRECT("'" & TEXT(EDATE(J7,-2),"mm-yyyy") & "'!D:D"), MATCH(A7,INDIRECT("'" & TEXT(EDATE(J7,-2),"mm-yyyy") & "'!A:A"),0)) -> 198 | D7: 203 | E7: =D7-C7 -> 5 | F7: 1182.6 | G7: =E7*F7 -> 5913 | H7: 5000 | I7: =E7*F7+H7 -> 10913 | J7: 45785 | L7: PAGADO | M7: =IF(L7="Pagado", I7, 0) -> 10913 | P7: =IF(L7="NO APLICA",0, (I7-M7)) -> 0
A8: 7 | B8: =Usuarios!B8 & " " & Usuarios!C8 & " " & Usuarios!D8 -> Marcelo Millanao | C8: =INDEX(INDIRECT("'" & TEXT(EDATE(J8,-2),"mm-yyyy") & "'!D:D"), MATCH(A8,INDIRECT("'" & TEXT(EDATE(J8,-2),"mm-yyyy") & "'!A:A"),0)) -> 238 | D8: 249 | E8: =D8-C8 -> 11 | F8: 1182.6 | G8: =E8*F8 -> 13008.6 | H8: 5000 | I8: =E8*F8+H8 -> 18008.6 | J8: 45785 | L8: PAGADO | M8: =IF(L8="Pagado", I8, 0) -> 18008.6 | P8: =IF(L8="NO APLICA",0, (I8-M8)) -> 0
A9: 8 | B9: =Usuarios!B9 & " " & Usuarios!C9 & " " & Usuarios!D9 -> Gabriel Farias | C9: =INDEX(INDIRECT("'" & TEXT(EDATE(J9,-2),"mm-yyyy") & "'!D:D"), MATCH(A9,INDIRECT("'" & TEXT(EDATE(J9,-2),"mm-yyyy") & "'!A:A"),0)) -> 432 | D9: 453 | E9: =D9-C9 -> 21 | F9: 1182.6 | G9: =E9*F9 -> 24834.6 | H9: 5000 | I9: =E9*F9+H9 -> 29834.6 | J9: 45785 | L9: PAGADO | M9: =IF(L9="Pagado", I9, 0) -> 29834.6 | P9: =IF(L9="NO APLICA",0, (I9-M9)) -> 0
A10: 9 | B10: =Usuarios!B10 & " " & Usuarios!C10 & " " & Usuarios!D10 -> Maria Marin | C10: =INDEX(INDIRECT("'" & TEXT(EDATE(J10,-2),"mm-yyyy") & "'!D:D"), MATCH(A10,INDIRECT("'" & TEXT(EDATE(J10,-2),"mm-yyyy") & "'!A:A"),0)) -> 177 | D10: 182 | E10: =D10-C10 -> 5 | F10: 1182.6 | G10: =E10*F10 -> 5913 | H10: 5000 | I10: =E10*F10+H10 -> 10913 | J10: 45785 | L10: PAGADO | M10: =IF(L10="Pagado", I10, 0) -> 10913 | P10: =IF(L10="NO APLICA",0, (I10-M10)) -> 0
A11: 10 | B11: =Usuarios!B11 & " " & Usuarios!C11 & " " & Usuarios!D11 -> David Cartes | C11: =INDEX(INDIRECT("'" & TEXT(EDATE(J11,-2),"mm-yyyy") & "'!D:D"), MATCH(A11,INDIRECT("'" & TEXT(EDATE(J11,-2),"mm-yyyy") & "'!A:A"),0)) -> 112 | D11: 118 | E11: =D11-C11 -> 6 | F11: 1182.6 | G11: =E11*F11 -> 7095.6 | H11: 5000 | I11: =E11*F11+H11 -> 12095.6 | J11: 45785 | L11: PAGADO | M11: =IF(L11="Pagado", I11, 0) -> 12095.6 | P11: =IF(L11="NO APLICA",0, (I11-M11)) -> 0
A12: 11 | B12: =Usuarios!B12 & " " & Usuarios!C12 & " " & Usuarios!D12 -> Miguel Ñanco | C12: =INDEX(INDIRECT("'" & TEXT(EDATE(J12,-2),"mm-yyyy") & "'!D:D"), MATCH(A12,INDIRECT("'" & TEXT(EDATE(J12,-2),"mm-yyyy") & "'!A:A"),0)) -> 240 | D12: 240 | E12: =D12-C12 -> 0 | F12: 1182.6 | G12: =E12*F12 -> 0 | H12: 5000 | I12: =E12*F12+H12 -> 5000 | J12: 45785 | L12: PENDIENTE | M12: =IF(L12="Pagado", I12, 0) -> 0 | P12: =IF(L12="NO APLICA",0, (I12-M12)) -> 5000
A13: 12 | B13: =Usuarios!B13 & " " & Usuarios!C13 & " " & Usuarios!D13 -> Pedro Contreras | C13: =INDEX(INDIRECT("'" & TEXT(EDATE(J13,-2),"mm-yyyy") & "'!D:D"), MATCH(A13,INDIRECT("'" & TEXT(EDATE(J13,-2),"mm-yyyy") & "'!A:A"),0)) -> 109 | D13: 113 | E13: =D13-C13 -> 4 | F13: 1182.6 | G13: =E13*F13 -> 4730.4 | H13: 5000 | I13: =E13*F13+H13 -> 9730.4 | J13: 45785 | L13: PENDIENTE | M13: =IF(L13="Pagado", I13, 0) -> 0 | P13: =IF(L13="NO APLICA",0, (I13-M13)) -> 9730.4
... A43: 42 | B43: =Usuarios!B43 & " " & Usuarios!C43 & " " & Usuarios!D43 -> Leo Soto | C43: =INDEX(INDIRECT("'" & TEXT(EDATE(J43,-2),"mm-yyyy") & "'!D:D"), MATCH(A43,INDIRECT("'" & TEXT(EDATE(J43,-2),"mm-yyyy") & "'!A:A"),0)) -> 10 | D43: 10 | E43: =D43-C43 -> 0 | F43: 1182.6 | G43: =E43*F43 -> 0 | H43: 5000 | I43: =E43*F43+H43 -> 5000 | J43: 45785 | L43: PENDIENTE | M43: =IF(L43="Pagado", I43, 0) -> 0 | P43: =IF(L43="NO APLICA",0, (I43-M43)) -> 5000
A44: 43 | B44: =Usuarios!B44 & " " & Usuarios!C44 & " " & Usuarios!D44 -> Ramon Maldonado | C44: =INDEX(INDIRECT("'" & TEXT(EDATE(J44,-2),"mm-yyyy") & "'!D:D"), MATCH(A44,INDIRECT("'" & TEXT(EDATE(J44,-2),"mm-yyyy") & "'!A:A"),0)) -> 0 | D44: 0 | E44: =D44-C44 -> 0 | F44: 1182.6 | G44: =E44*F44 -> 0 | H44: 5000 | I44: =E44*F44+H44 -> 5000 | J44: 45785 | L44: PAGADO | M44: =IF(L44="Pagado", I44, 0) -> 5000 | O44: TRANSFERENCIA | P44: =IF(L44="NO APLICA",0, (I44-M44)) -> 0
A45: 44 | B45: =Usuarios!B45 & " " & Usuarios!C45 & " " & Usuarios!D45 -> María Sonia Quintui | C45: =INDEX(INDIRECT("'" & TEXT(EDATE(J45,-2),"mm-yyyy") & "'!D:D"), MATCH(A45,INDIRECT("'" & TEXT(EDATE(J45,-2),"mm-yyyy") & "'!A:A"),0)) -> 0 | D45: 8 | E45: =D45-C45 -> 8 | F45: 1182.6 | G45: =E45*F45 -> 9460.8 | H45: 5000 | I45: =E45*F45+H45 -> 14460.8 | J45: 45785 | L45: PENDIENTE | M45: =IF(L45="Pagado", I45, 0) -> 0 | P45: =IF(L45="NO APLICA",0, (I45-M45)) -> 14460.8
A46: 45 | B46: =Usuarios!B46 & " " & Usuarios!C46 & " " & Usuarios!D46 -> Monica Cuello | C46: =INDEX(INDIRECT("'" & TEXT(EDATE(J46,-2),"mm-yyyy") & "'!D:D"), MATCH(A46,INDIRECT("'" & TEXT(EDATE(J46,-2),"mm-yyyy") & "'!A:A"),0)) -> 0 | D46: 0 | E46: =D46-C46 -> 0 | F46: 1182.6 | G46: =E46*F46 -> 0 | H46: 5000 | I46: =E46*F46+H46 -> 5000 | J46: 45785 | L46: PENDIENTE | M46: =IF(L46="Pagado", I46, 0) -> 0 | P46: =IF(L46="NO APLICA",0, (I46-M46)) -> 5000
A47: 46 | B47: =Usuarios!B47 & " " & Usuarios!C47 & " " & Usuarios!D47 -> Mauricio Muñoz taller | C47: =INDEX(INDIRECT("'" & TEXT(EDATE(J47,-2),"mm-yyyy") & "'!D:D"), MATCH(A47,INDIRECT("'" & TEXT(EDATE(J47,-2),"mm-yyyy") & "'!A:A"),0)) -> 0 | D47: 0 | E47: =D47-C47 -> 0 | F47: 1182.6 | G47: =E47*F47 -> 0 | H47: 5000 | I47: =E47*F47+H47 -> 5000 | J47: 45785 | L47: PENDIENTE | M47: =IF(L47="Pagado", I47, 0) -> 0 | P47: =IF(L47="NO APLICA",0, (I47-M47)) -> 5000
A48: 47 | B48: =Usuarios!B48 & " " & Usuarios!C48 & " " & Usuarios!D48 -> Pablo Contreras | C48: =INDEX(INDIRECT("'" & TEXT(EDATE(J48,-2),"mm-yyyy") & "'!D:D"), MATCH(A48,INDIRECT("'" & TEXT(EDATE(J48,-2),"mm-yyyy") & "'!A:A"),0)) -> 0 | D48: 0 | E48: =D48-C48 -> 0 | F48: 1182.6 | G48: =E48*F48 -> 0 | H48: 5000 | I48: =E48*F48+H48 -> 5000 | J48: 45785 | L48: PENDIENTE | M48: =IF(L48="Pagado", I48, 0) -> 0 | P48: =IF(L48="NO APLICA",0, (I48-M48)) -> 5000
A49: 48 | B49: =Usuarios!B49 & " " & Usuarios!C49 & " " & Usuarios!D49 -> Luis Vicente Mondaca Muñoz | C49: =INDEX(INDIRECT("'" & TEXT(EDATE(J49,-2),"mm-yyyy") & "'!D:D"), MATCH(A49,INDIRECT("'" & TEXT(EDATE(J49,-2),"mm-yyyy") & "'!A:A"),0)) -> 281 | D49: 294 | E49: =D49-C49 -> 13 | F49: 1182.6 | G49: =E49*F49 -> 15373.8 | H49: 5000 | I49: =E49*F49+H49 -> 20373.8 | J49: 45785 | L49: PAGADO | M49: =IF(L49="Pagado", I49, 0) -> 20373.8 | P49: =IF(L49="NO APLICA",0, (I49-M49)) -> 0
A50: 49 | B50: =Usuarios!B50 & " " & Usuarios!C50 & " " & Usuarios!D50 -> Rosa Nuñez | C50: =INDEX(INDIRECT("'" & TEXT(EDATE(J50,-2),"mm-yyyy") & "'!D:D"), MATCH(A50,INDIRECT("'" & TEXT(EDATE(J50,-2),"mm-yyyy") & "'!A:A"),0)) -> 80 | D50: 82 | E50: =D50-C50 -> 2 | F50: 1182.6 | G50: =E50*F50 -> 2365.2 | H50: 5000 | I50: =E50*F50+H50 -> 7365.2 | J50: 45785 | L50: PENDIENTE | M50: =IF(L50="Pagado", I50, 0) -> 0 | P50: =IF(L50="NO APLICA",0, (I50-M50)) -> 7365.2
A51: 50 | B51: =Usuarios!B51 & " " & Usuarios!C51 & " " & Usuarios!D51 -> Gloria Isamar Velasquez Almonacid | C51: =INDEX(INDIRECT("'" & TEXT(EDATE(J51,-2),"mm-yyyy") & "'!D:D"), MATCH(A51,INDIRECT("'" & TEXT(EDATE(J51,-2),"mm-yyyy") & "'!A:A"),0)) -> 35 | D51: 42 | E51: =D51-C51 -> 7 | F51: 1182.6 | G51: =E51*F51 -> 8278.2 | H51: 5000 | I51: =E51*F51+H51 -> 13278.2 | J51: 45785 | L51: PENDIENTE | M51: =IF(L51="Pagado", I51, 0) -> 0 | P51: =IF(L51="NO APLICA",0, (I51-M51)) -> 13278.2
A52: 51 | B52: =Usuarios!B52 & " " & Usuarios!C52 & " " & Usuarios!D52 -> Maria Manquian | C52: =INDEX(INDIRECT("'" & TEXT(EDATE(J52,-2),"mm-yyyy") & "'!D:D"), MATCH(A52,INDIRECT("'" & TEXT(EDATE(J52,-2),"mm-yyyy") & "'!A:A"),0)) -> 0 | D52: 0 | E52: =D52-C52 -> 0 | F52: 1182.6 | G52: =E52*F52 -> 0 | H52: 5000 | I52: =E52*F52+H52 -> 5000 | J52: 45785 | L52: PAGADO | M52: =IF(L52="Pagado", I52, 0) -> 5000 | O52: TRANSFERENCIA | P52: =IF(L52="NO APLICA",0, (I52-M52)) -> 0
A53: 52 | B53: =Usuarios!B53 & " " & Usuarios!C53 & " " & Usuarios!D53 -> Esteban Oyarzo Levil | C53: =INDEX(INDIRECT("'" & TEXT(EDATE(J53,-2),"mm-yyyy") & "'!D:D"), MATCH(A53,INDIRECT("'" & TEXT(EDATE(J53,-2),"mm-yyyy") & "'!A:A"),0)) -> 0 | D53: 0 | E53: =D53-C53 -> 0 | F53: 1182.6 | G53: =E53*F53 -> 0 | H53: 5000 | I53: =E53*F53+H53 -> 5000 | J53: 45785 | L53: PENDIENTE | M53: =IF(L53="Pagado", I53, 0) -> 0 | P53: =IF(L53="NO APLICA",0, (I53-M53)) -> 5000
A54: 53 | B54: =Usuarios!B54 & " " & Usuarios!C54 & " " & Usuarios!D54 -> Nicolas Andres Cardenas Bustamante | C54: =INDEX(INDIRECT("'" & TEXT(EDATE(J54,-2),"mm-yyyy") & "'!D:D"), MATCH(A54,INDIRECT("'" & TEXT(EDATE(J54,-2),"mm-yyyy") & "'!A:A"),0)) -> 0 | D54: 0 | E54: =D54-C54 -> 0 | F54: 1182.6 | G54: =E54*F54 -> 0 | H54: 5000 | I54: =E54*F54+H54 -> 5000 | J54: 45785 | L54: PAGADO | M54: =IF(L54="Pagado", I54, 0) -> 5000 | P54: =IF(L54="NO APLICA",0, (I54-M54)) -> 0
A55: 54 | B55: =Usuarios!B55 & " " & Usuarios!C55 & " " & Usuarios!D55 -> Rosa Mancilla | C55: =INDEX(INDIRECT("'" & TEXT(EDATE(J55,-2),"mm-yyyy") & "'!D:D"), MATCH(A55,INDIRECT("'" & TEXT(EDATE(J55,-2),"mm-yyyy") & "'!A:A"),0)) -> 106 | D55: 106 | E55: =D55-C55 -> 0 | F55: 1182.6 | G55: =E55*F55 -> 0 | H55: 5000 | I55: =E55*F55+H55 -> 5000 | J55: 45785 | L55: PENDIENTE | M55: =IF(L55="Pagado", I55, 0) -> 0 | P55: =IF(L55="NO APLICA",0, (I55-M55)) -> 5000
A56: 55 | B56: =Usuarios!B56 & " " & Usuarios!C56 & " " & Usuarios!D56 -> Guido Quintuy - Sitio vacío | C56: =INDEX(INDIRECT("'" & TEXT(EDATE(J56,-2),"mm-yyyy") & "'!D:D"), MATCH(A56,INDIRECT("'" & TEXT(EDATE(J56,-2),"mm-yyyy") & "'!A:A"),0)) -> 0 | D56: 0 | E56: =D56-C56 -> 0 | F56: 1182.6 | G56: =E56*F56 -> 0 | H56: 5000 | I56: =E56*F56+H56 -> 5000 | J56: 45785 | L56: PENDIENTE | M56: =IF(L56="Pagado", I56, 0) -> 0 | P56: =IF(L56="NO APLICA",0, (I56-M56)) -> 5000
A57: 56 | B57: =Usuarios!B57 & " " & Usuarios!C57 & " " & Usuarios!D57 -> Mario Velasquez | C57: =INDEX(INDIRECT("'" & TEXT(EDATE(J57,-2),"mm-yyyy") & "'!D:D"), MATCH(A57,INDIRECT("'" & TEXT(EDATE(J57,-2),"mm-yyyy") & "'!A:A"),0)) -> 17 | D57: 22 | E57: =D57-C57 -> 5 | F57: 1182.6 | G57: =E57*F57 -> 5913 | H57: 5000 | I57: =E57*F57+H57 -> 10913 | J57: 45785 | L57: PAGADO | M57: =IF(L57="Pagado", I57, 0) -> 10913 | P57: =IF(L57="NO APLICA",0, (I57-M57)) -> 0
A58: 57 | B58: =Usuarios!B58 & " " & Usuarios!C58 & " " & Usuarios!D58 -> Lishby Fuentes Diaz | C58: =INDEX(INDIRECT("'" & TEXT(EDATE(J58,-2),"mm-yyyy") & "'!D:D"), MATCH(A58,INDIRECT("'" & TEXT(EDATE(J58,-2),"mm-yyyy") & "'!A:A"),0)) -> 0 | D58: 0 | E58: =D58-C58 -> 0 | F58: 1182.6 | G58: =E58*F58 -> 0 | H58: 5000 | I58: =E58*F58+H58 -> 5000 | J58: 45785 | L58: NO APLICA | M58: =IF(L58="Pagado", I58, 0) -> 0 | P58: =IF(L58="NO APLICA",0, (I58-M58)) -> 0

Sheet 05-2025
A1: ID | B1: Nombre | C1: Lectura_Anterior | D1: Lectura_Actual | E1: Consumo_m3 | F1: Tarifa_m3 | G1: Subtotal_Consumo | H1: Cargo_Fijo | I1: Total_Factura | J1: Fecha_Lectura | K1: Periodo | L1: Estado_Pago | M1: Monto_Pagado | N1: Fecha_Pago | O1: Forma_Pago | P1: Saldo_Pendiente | Q1: comprobante_link
A2: 1 | B2: =Usuarios!B2 & " " & Usuarios!C2 & " " & Usuarios!D2 -> Nancy Zuñiga Villarroel | C2: =INDEX(INDIRECT("'" & TEXT(EDATE(J2,-2),"mm-yyyy") & "'!D:D"), MATCH(A2,INDIRECT("'" & TEXT(EDATE(J2,-2),"mm-yyyy") & "'!A:A"),0)) -> 200 | D2: 212 | E2: =D2-C2 -> 12 | F2: 1182.6 | G2: =E2*F2 -> 14191.2 | H2: 5000 | I2: =E2*F2+H2 -> 19191.2 | J2: 45816 | L2: PENDIENTE | M2: =IF(L2="Pagado", I2, 0) -> 0 | P2: =IF(L2="NO APLICA",0, (I2-M2)) -> 19191.2
A3: 2 | B3: =Usuarios!B3 & " " & Usuarios!C3 & " " & Usuarios!D3 -> Gabriel Barria Zuñiga | C3: =INDEX(INDIRECT("'" & TEXT(EDATE(J3,-2),"mm-yyyy") & "'!D:D"), MATCH(A3,INDIRECT("'" & TEXT(EDATE(J3,-2),"mm-yyyy") & "'!A:A"),0)) -> 309 | D3: 334 | E3: =D3-C3 -> 25 | F3: 1182.6 | G3: =E3*F3 -> 29565 | H3: 5000 | I3: =E3*F3+H3 -> 34565 | J3: 45816 | L3: PENDIENTE | M3: =IF(L3="Pagado", I3, 0) -> 0 | P3: =IF(L3="NO APLICA",0, (I3-M3)) -> 34565
A4: 3 | B4: =Usuarios!B4 & " " & Usuarios!C4 & " " & Usuarios!D4 -> Gino Reyes | C4: =INDEX(INDIRECT("'" & TEXT(EDATE(J4,-2),"mm-yyyy") & "'!D:D"), MATCH(A4,INDIRECT("'" & TEXT(EDATE(J4,-2),"mm-yyyy") & "'!A:A"),0)) -> 69 | D4: 75 | E4: =D4-C4 -> 6 | F4: 1182.6 | G4: =E4*F4 -> 7095.6 | H4: 5000 | I4: =E4*F4+H4 -> 12095.6 | J4: 45816 | L4: PENDIENTE | M4: =IF(L4="Pagado", I4, 0) -> 0 | P4: =IF(L4="NO APLICA",0, (I4-M4)) -> 12095.6
A5: 4 | B5: =Usuarios!B5 & " " & Usuarios!C5 & " " & Usuarios!D5 -> Cristian Oyarzo | C5: =INDEX(INDIRECT("'" & TEXT(EDATE(J5,-2),"mm-yyyy") & "'!D:D"), MATCH(A5,INDIRECT("'" & TEXT(EDATE(J5,-2),"mm-yyyy") & "'!A:A"),0)) -> 518 | D5: 553 | E5: =D5-C5 -> 35 | F5: 1182.6 | G5: =E5*F5 -> 41391 | H5: 5000 | I5: =E5*F5+H5 -> 46391 | J5: 45816 | L5: PENDIENTE | M5: =IF(L5="Pagado", I5, 0) -> 0 | P5: =IF(L5="NO APLICA",0, (I5-M5)) -> 46391
A6: 5 | B6: =Usuarios!B6 & " " & Usuarios!C6 & " " & Usuarios!D6 -> Marisol Castro | C6: =INDEX(INDIRECT("'" & TEXT(EDATE(J6,-2),"mm-yyyy") & "'!D:D"), MATCH(A6,INDIRECT("'" & TEXT(EDATE(J6,-2),"mm-yyyy") & "'!A:A"),0)) -> 110 | D6: 117 | E6: =D6-C6 -> 7 | F6: 1182.6 | G6: =E6*F6 -> 8278.2 | H6: 5000 | I6: =E6*F6+H6 -> 13278.2 | J6: 45816 | L6: PENDIENTE | M6: =IF(L6="Pagado", I6, 0) -> 0 | P6: =IF(L6="NO APLICA",0, (I6-M6)) -> 13278.2
A7: 6 | B7: =Usuarios!B7 & " " & Usuarios!C7 & " " & Usuarios!D7 -> Mauricio Muñoz | C7: =INDEX(INDIRECT("'" & TEXT(EDATE(J7,-2),"mm-yyyy") & "'!D:D"), MATCH(A7,INDIRECT("'" & TEXT(EDATE(J7,-2),"mm-yyyy") & "'!A:A"),0)) -> 203 | D7: 208 | E7: =D7-C7 -> 5 | F7: 1182.6 | G7: =E7*F7 -> 5913 | H7: 5000 | I7: =E7*F7+H7 -> 10913 | J7: 45816 | L7: PENDIENTE | M7: =IF(L7="Pagado", I7, 0) -> 0 | P7: =IF(L7="NO APLICA",0, (I7-M7)) -> 10913
A8: 7 | B8: =Usuarios!B8 & " " & Usuarios!C8 & " " & Usuarios!D8 -> Marcelo Millanao | C8: =INDEX(INDIRECT("'" & TEXT(EDATE(J8,-2),"mm-yyyy") & "'!D:D"), MATCH(A8,INDIRECT("'" & TEXT(EDATE(J8,-2),"mm-yyyy") & "'!A:A"),0)) -> 249 | D8: 263 | E8: =D8-C8 -> 14 | F8: 1182.6 | G8: =E8*F8 -> 16556.4 | H8: 5000 | I8: =E8*F8+H8 -> 21556.4 | J8: 45816 | L8: PENDIENTE | M8: =IF(L8="Pagado", I8, 0) -> 0 | P8: =IF(L8="NO APLICA",0, (I8-M8)) -> 21556.4
A9: 8 | B9: =Usuarios!B9 & " " & Usuarios!C9 & " " & Usuarios!D9 -> Gabriel Farias | C9: =INDEX(INDIRECT("'" & TEXT(EDATE(J9,-2),"mm-yyyy") & "'!D:D"), MATCH(A9,INDIRECT("'" & TEXT(EDATE(J9,-2),"mm-yyyy") & "'!A:A"),0)) -> 453 | D9: 482 | E9: =D9-C9 -> 29 | F9: 1182.6 | G9: =E9*F9 -> 34295.4 | H9: 5000 | I9: =E9*F9+H9 -> 39295.4 | J9: 45816 | L9: PENDIENTE | M9: =IF(L9="Pagado", I9, 0) -> 0 | P9: =IF(L9="NO APLICA",0, (I9-M9)) -> 39295.4
A10: 9 | B10: =Usuarios!B10 & " " & Usuarios!C10 & " " & Usuarios!D10 -> Maria Marin | C10: =INDEX(INDIRECT("'" & TEXT(EDATE(J10,-2),"mm-yyyy") & "'!D:D"), MATCH(A10,INDIRECT("'" & TEXT(EDATE(J10,-2),"mm-yyyy") & "'!A:A"),0)) -> 182 | D10: 193 | E10: =D10-C10 -> 11 | F10: 1182.6 | G10: =E10*F10 -> 13008.6 | H10: 5000 | I10: =E10*F10+H10 -> 18008.6 | J10: 45816 | L10: PENDIENTE | M10: =IF(L10="Pagado", I10, 0) -> 0 | P10: =IF(L10="NO APLICA",0, (I10-M10)) -> 18008.6
A11: 10 | B11: =Usuarios!B11 & " " & Usuarios!C11 & " " & Usuarios!D11 -> David Cartes | C11: =INDEX(INDIRECT("'" & TEXT(EDATE(J11,-2),"mm-yyyy") & "'!D:D"), MATCH(A11,INDIRECT("'" & TEXT(EDATE(J11,-2),"mm-yyyy") & "'!A:A"),0)) -> 118 | D11: 130 | E11: =D11-C11 -> 12 | F11: 1182.6 | G11: =E11*F11 -> 14191.2 | H11: 5000 | I11: =E11*F11+H11 -> 19191.2 | J11: 45816 | L11: PENDIENTE | M11: =IF(L11="Pagado", I11, 0) -> 0 | P11: =IF(L11="NO APLICA",0, (I11-M11)) -> 19191.2
A12: 11 | B12: =Usuarios!B12 & " " & Usuarios!C12 & " " & Usuarios!D12 -> Miguel Ñanco | C12: =INDEX(INDIRECT("'" & TEXT(EDATE(J12,-2),"mm-yyyy") & "'!D:D"), MATCH(A12,INDIRECT("'" & TEXT(EDATE(J12,-2),"mm-yyyy") & "'!A:A"),0)) -> 240 | D12: 240 | E12: =D12-C12 -> 0 | F12: 1182.6 | G12: =E12*F12 -> 0 | H12: 5000 | I12: =E12*F12+H12 -> 5000 | J12: 45816 | L12: PENDIENTE | M12: =IF(L12="Pagado", I12, 0) -> 0 | P12: =IF(L12="NO APLICA",0, (I12-M12)) -> 5000
A13: 12 | B13: =Usuarios!B13 & " " & Usuarios!C13 & " " & Usuarios!D13 -> Pedro Contreras | C13: =INDEX(INDIRECT("'" & TEXT(EDATE(J13,-2),"mm-yyyy") & "'!D:D"), MATCH(A13,INDIRECT("'" & TEXT(EDATE(J13,-2),"mm-yyyy") & "'!A:A"),0)) -> 113 | D13: 122 | E13: =D13-C13 -> 9 | F13: 1182.6 | G13: =E13*F13 -> 10643.4 | H13: 5000 | I13: =E13*F13+H13 -> 15643.4 | J13: 45816 | L13: PENDIENTE | M13: =IF(L13="Pagado", I13, 0) -> 0 | P13: =IF(L13="NO APLICA",0, (I13-M13)) -> 15643.4
... A43: 42 | B43: =Usuarios!B43 & " " & Usuarios!C43 & " " & Usuarios!D43 -> Leo Soto | C43: =INDEX(INDIRECT("'" & TEXT(EDATE(J43,-2),"mm-yyyy") & "'!D:D"), MATCH(A43,INDIRECT("'" & TEXT(EDATE(J43,-2),"mm-yyyy") & "'!A:A"),0)) -> 10 | D43: 10 | E43: =D43-C43 -> 0 | F43: 1182.6 | G43: =E43*F43 -> 0 | H43: 5000 | I43: =E43*F43+H43 -> 5000 | J43: 45816 | L43: PENDIENTE | M43: =IF(L43="Pagado", I43, 0) -> 0 | P43: =IF(L43="NO APLICA",0, (I43-M43)) -> 5000
A44: 43 | B44: =Usuarios!B44 & " " & Usuarios!C44 & " " & Usuarios!D44 -> Ramon Maldonado | C44: =INDEX(INDIRECT("'" & TEXT(EDATE(J44,-2),"mm-yyyy") & "'!D:D"), MATCH(A44,INDIRECT("'" & TEXT(EDATE(J44,-2),"mm-yyyy") & "'!A:A"),0)) -> 0 | D44: 0 | E44: =D44-C44 -> 0 | F44: 1182.6 | G44: =E44*F44 -> 0 | H44: 5000 | I44: =E44*F44+H44 -> 5000 | J44: 45816 | L44: PAGADO | M44: =IF(L44="Pagado", I44, 0) -> 5000 | O44: TRANSFERENCIA | P44: =IF(L44="NO APLICA",0, (I44-M44)) -> 0
A45: 44 | B45: =Usuarios!B45 & " " & Usuarios!C45 & " " & Usuarios!D45 -> María Sonia Quintui | C45: =INDEX(INDIRECT("'" & TEXT(EDATE(J45,-2),"mm-yyyy") & "'!D:D"), MATCH(A45,INDIRECT("'" & TEXT(EDATE(J45,-2),"mm-yyyy") & "'!A:A"),0)) -> 8 | D45: 11 | E45: =D45-C45 -> 3 | F45: 1182.6 | G45: =E45*F45 -> 3547.8 | H45: 5000 | I45: =E45*F45+H45 -> 8547.8 | J45: 45816 | L45: PENDIENTE | M45: =IF(L45="Pagado", I45, 0) -> 0 | P45: =IF(L45="NO APLICA",0, (I45-M45)) -> 8547.8
A46: 45 | B46: =Usuarios!B46 & " " & Usuarios!C46 & " " & Usuarios!D46 -> Monica Cuello | C46: =INDEX(INDIRECT("'" & TEXT(EDATE(J46,-2),"mm-yyyy") & "'!D:D"), MATCH(A46,INDIRECT("'" & TEXT(EDATE(J46,-2),"mm-yyyy") & "'!A:A"),0)) -> 0 | D46: 0 | E46: =D46-C46 -> 0 | F46: 1182.6 | G46: =E46*F46 -> 0 | H46: 5000 | I46: =E46*F46+H46 -> 5000 | J46: 45816 | L46: PENDIENTE | M46: =IF(L46="Pagado", I46, 0) -> 0 | P46: =IF(L46="NO APLICA",0, (I46-M46)) -> 5000
A47: 46 | B47: =Usuarios!B47 & " " & Usuarios!C47 & " " & Usuarios!D47 -> Mauricio Muñoz taller | C47: =INDEX(INDIRECT("'" & TEXT(EDATE(J47,-2),"mm-yyyy") & "'!D:D"), MATCH(A47,INDIRECT("'" & TEXT(EDATE(J47,-2),"mm-yyyy") & "'!A:A"),0)) -> 0 | D47: 0 | E47: =D47-C47 -> 0 | F47: 1182.6 | G47: =E47*F47 -> 0 | H47: 5000 | I47: =E47*F47+H47 -> 5000 | J47: 45816 | L47: PENDIENTE | M47: =IF(L47="Pagado", I47, 0) -> 0 | P47: =IF(L47="NO APLICA",0, (I47-M47)) -> 5000
A48: 47 | B48: =Usuarios!B48 & " " & Usuarios!C48 & " " & Usuarios!D48 -> Pablo Contreras | C48: =INDEX(INDIRECT("'" & TEXT(EDATE(J48,-2),"mm-yyyy") & "'!D:D"), MATCH(A48,INDIRECT("'" & TEXT(EDATE(J48,-2),"mm-yyyy") & "'!A:A"),0)) -> 0 | D48: 0 | E48: =D48-C48 -> 0 | F48: 1182.6 | G48: =E48*F48 -> 0 | H48: 5000 | I48: =E48*F48+H48 -> 5000 | J48: 45816 | L48: PENDIENTE | M48: =IF(L48="Pagado", I48, 0) -> 0 | P48: =IF(L48="NO APLICA",0, (I48-M48)) -> 5000
A49: 48 | B49: =Usuarios!B49 & " " & Usuarios!C49 & " " & Usuarios!D49 -> Luis Vicente Mondaca Muñoz | C49: =INDEX(INDIRECT("'" & TEXT(EDATE(J49,-2),"mm-yyyy") & "'!D:D"), MATCH(A49,INDIRECT("'" & TEXT(EDATE(J49,-2),"mm-yyyy") & "'!A:A"),0)) -> 294 | D49: 319 | E49: =D49-C49 -> 25 | F49: 1182.6 | G49: =E49*F49 -> 29565 | H49: 5000 | I49: =E49*F49+H49 -> 34565 | J49: 45816 | L49: PAGADO | M49: =IF(L49="Pagado", I49, 0) -> 34565 | N49: 45939 | O49: EFECTIVO | P49: =IF(L49="NO APLICA",0, (I49-M49)) -> 0
A50: 49 | B50: =Usuarios!B50 & " " & Usuarios!C50 & " " & Usuarios!D50 -> Rosa Nuñez | C50: =INDEX(INDIRECT("'" & TEXT(EDATE(J50,-2),"mm-yyyy") & "'!D:D"), MATCH(A50,INDIRECT("'" & TEXT(EDATE(J50,-2),"mm-yyyy") & "'!A:A"),0)) -> 82 | D50: 86 | E50: =D50-C50 -> 4 | F50: 1182.6 | G50: =E50*F50 -> 4730.4 | H50: 5000 | I50: =E50*F50+H50 -> 9730.4 | J50: 45816 | L50: PENDIENTE | M50: =IF(L50="Pagado", I50, 0) -> 0 | P50: =IF(L50="NO APLICA",0, (I50-M50)) -> 9730.4
A51: 50 | B51: =Usuarios!B51 & " " & Usuarios!C51 & " " & Usuarios!D51 -> Gloria Isamar Velasquez Almonacid | C51: =INDEX(INDIRECT("'" & TEXT(EDATE(J51,-2),"mm-yyyy") & "'!D:D"), MATCH(A51,INDIRECT("'" & TEXT(EDATE(J51,-2),"mm-yyyy") & "'!A:A"),0)) -> 42 | D51: 50 | E51: =D51-C51 -> 8 | F51: 1182.6 | G51: =E51*F51 -> 9460.8 | H51: 5000 | I51: =E51*F51+H51 -> 14460.8 | J51: 45816 | L51: PENDIENTE | M51: =IF(L51="Pagado", I51, 0) -> 0 | P51: =IF(L51="NO APLICA",0, (I51-M51)) -> 14460.8
A52: 51 | B52: =Usuarios!B52 & " " & Usuarios!C52 & " " & Usuarios!D52 -> Maria Manquian | C52: =INDEX(INDIRECT("'" & TEXT(EDATE(J52,-2),"mm-yyyy") & "'!D:D"), MATCH(A52,INDIRECT("'" & TEXT(EDATE(J52,-2),"mm-yyyy") & "'!A:A"),0)) -> 0 | D52: 0 | E52: =D52-C52 -> 0 | F52: 1182.6 | G52: =E52*F52 -> 0 | H52: 5000 | I52: =E52*F52+H52 -> 5000 | J52: 45816 | L52: PAGADO | M52: =IF(L52="Pagado", I52, 0) -> 5000 | O52: TRANSFERENCIA | P52: =IF(L52="NO APLICA",0, (I52-M52)) -> 0
A53: 52 | B53: =Usuarios!B53 & " " & Usuarios!C53 & " " & Usuarios!D53 -> Esteban Oyarzo Levil | C53: =INDEX(INDIRECT("'" & TEXT(EDATE(J53,-2),"mm-yyyy") & "'!D:D"), MATCH(A53,INDIRECT("'" & TEXT(EDATE(J53,-2),"mm-yyyy") & "'!A:A"),0)) -> 0 | D53: 0 | E53: =D53-C53 -> 0 | F53: 1182.6 | G53: =E53*F53 -> 0 | H53: 5000 | I53: =E53*F53+H53 -> 5000 | J53: 45816 | L53: PENDIENTE | M53: =IF(L53="Pagado", I53, 0) -> 0 | P53: =IF(L53="NO APLICA",0, (I53-M53)) -> 5000
A54: 53 | B54: =Usuarios!B54 & " " & Usuarios!C54 & " " & Usuarios!D54 -> Nicolas Andres Cardenas Bustamante | C54: =INDEX(INDIRECT("'" & TEXT(EDATE(J54,-2),"mm-yyyy") & "'!D:D"), MATCH(A54,INDIRECT("'" & TEXT(EDATE(J54,-2),"mm-yyyy") & "'!A:A"),0)) -> 0 | D54: 0 | E54: =D54-C54 -> 0 | F54: 1182.6 | G54: =E54*F54 -> 0 | H54: 5000 | I54: =E54*F54+H54 -> 5000 | J54: 45816 | L54: PAGADO | M54: =IF(L54="Pagado", I54, 0) -> 5000 | P54: =IF(L54="NO APLICA",0, (I54-M54)) -> 0
A55: 54 | B55: =Usuarios!B55 & " " & Usuarios!C55 & " " & Usuarios!D55 -> Rosa Mancilla | C55: =INDEX(INDIRECT("'" & TEXT(EDATE(J55,-2),"mm-yyyy") & "'!D:D"), MATCH(A55,INDIRECT("'" & TEXT(EDATE(J55,-2),"mm-yyyy") & "'!A:A"),0)) -> 106 | D55: 106 | E55: =D55-C55 -> 0 | F55: 1182.6 | G55: =E55*F55 -> 0 | H55: 5000 | I55: =E55*F55+H55 -> 5000 | J55: 45816 | L55: PENDIENTE | M55: =IF(L55="Pagado", I55, 0) -> 0 | P55: =IF(L55="NO APLICA",0, (I55-M55)) -> 5000
A56: 55 | B56: =Usuarios!B56 & " " & Usuarios!C56 & " " & Usuarios!D56 -> Guido Quintuy - Sitio vacío | C56: =INDEX(INDIRECT("'" & TEXT(EDATE(J56,-2),"mm-yyyy") & "'!D:D"), MATCH(A56,INDIRECT("'" & TEXT(EDATE(J56,-2),"mm-yyyy") & "'!A:A"),0)) -> 0 | D56: 0 | E56: =D56-C56 -> 0 | F56: 1182.6 | G56: =E56*F56 -> 0 | H56: 5000 | I56: =E56*F56+H56 -> 5000 | J56: 45816 | L56: PENDIENTE | M56: =IF(L56="Pagado", I56, 0) -> 0 | P56: =IF(L56="NO APLICA",0, (I56-M56)) -> 5000
A57: 56 | B57: =Usuarios!B57 & " " & Usuarios!C57 & " " & Usuarios!D57 -> Mario Velasquez | C57: =INDEX(INDIRECT("'" & TEXT(EDATE(J57,-2),"mm-yyyy") & "'!D:D"), MATCH(A57,INDIRECT("'" & TEXT(EDATE(J57,-2),"mm-yyyy") & "'!A:A"),0)) -> 22 | D57: 36 | E57: =D57-C57 -> 14 | F57: 1182.6 | G57: =E57*F57 -> 16556.4 | H57: 5000 | I57: =E57*F57+H57 -> 21556.4 | J57: 45816 | L57: PENDIENTE | M57: =IF(L57="Pagado", I57, 0) -> 0 | P57: =IF(L57="NO APLICA",0, (I57-M57)) -> 21556.4
A58: 57 | B58: =Usuarios!B58 & " " & Usuarios!C58 & " " & Usuarios!D58 -> Lishby Fuentes Diaz | C58: =INDEX(INDIRECT("'" & TEXT(EDATE(J58,-2),"mm-yyyy") & "'!D:D"), MATCH(A58,INDIRECT("'" & TEXT(EDATE(J58,-2),"mm-yyyy") & "'!A:A"),0)) -> 0 | D58: 0 | E58: =D58-C58 -> 0 | F58: 1182.6 | G58: =E58*F58 -> 0 | H58: 5000 | I58: =E58*F58+H58 -> 5000 | J58: 45816 | L58: NO APLICA | M58: =IF(L58="Pagado", I58, 0) -> 0 | P58: =IF(L58="NO APLICA",0, (I58-M58)) -> 0

Sheet 06-2025
A1: ID | B1: Nombre | C1: Lectura_Anterior | D1: Lectura_Actual | E1: Consumo_m3 | F1: Tarifa_m3 | G1: Subtotal_Consumo | H1: Cargo_Fijo | I1: Total_Factura | J1: Fecha_Lectura | K1: Periodo | L1: Estado_Pago | M1: Monto_Pagado | N1: Fecha_Pago | O1: Forma_Pago | P1: Saldo_Pendiente | Q1: comprobante_link
A2: 1 | B2: =Usuarios!B2 & " " & Usuarios!C2 & " " & Usuarios!D2 -> Nancy Zuñiga Villarroel | C2: =INDEX(INDIRECT("'" & TEXT(EDATE(J2,-2),"mm-yyyy") & "'!D:D"), MATCH(A2,INDIRECT("'" & TEXT(EDATE(J2,-2),"mm-yyyy") & "'!A:A"),0)) -> 212 | D2: 222 | E2: =D2-C2 -> 10 | F2: 1182.6 | G2: =E2*F2 -> 11826 | H2: 5000 | I2: =E2*F2+H2 -> 16826 | J2: 45846 | L2: PENDIENTE | M2: =IF(L2="Pagado", I2, 0) -> 0 | P2: =IF(L2="NO APLICA",0, (I2-M2)) -> 16826
A3: 2 | B3: =Usuarios!B3 & " " & Usuarios!C3 & " " & Usuarios!D3 -> Gabriel Barria Zuñiga | C3: =INDEX(INDIRECT("'" & TEXT(EDATE(J3,-2),"mm-yyyy") & "'!D:D"), MATCH(A3,INDIRECT("'" & TEXT(EDATE(J3,-2),"mm-yyyy") & "'!A:A"),0)) -> 334 | D3: 351 | E3: =D3-C3 -> 17 | F3: 1182.6 | G3: =E3*F3 -> 20104.2 | H3: 5000 | I3: =E3*F3+H3 -> 25104.2 | J3: 45846 | L3: PENDIENTE | M3: =IF(L3="Pagado", I3, 0) -> 0 | P3: =IF(L3="NO APLICA",0, (I3-M3)) -> 25104.2
A4: 3 | B4: =Usuarios!B4 & " " & Usuarios!C4 & " " & Usuarios!D4 -> Gino Reyes | C4: =INDEX(INDIRECT("'" & TEXT(EDATE(J4,-2),"mm-yyyy") & "'!D:D"), MATCH(A4,INDIRECT("'" & TEXT(EDATE(J4,-2),"mm-yyyy") & "'!A:A"),0)) -> 75 | D4: 1 | E4: =D4-C4 -> -74 | F4: 1182.6 | G4: =E4*F4 -> -87512.4 | H4: 5000 | I4: =E4*F4+H4 -> -82512.4 | J4: 45846 | L4: PENDIENTE | M4: =IF(L4="Pagado", I4, 0) -> 0 | P4: =IF(L4="NO APLICA",0, (I4-M4)) -> -82512.4
A5: 4 | B5: =Usuarios!B5 & " " & Usuarios!C5 & " " & Usuarios!D5 -> Cristian Oyarzo | C5: =INDEX(INDIRECT("'" & TEXT(EDATE(J5,-2),"mm-yyyy") & "'!D:D"), MATCH(A5,INDIRECT("'" & TEXT(EDATE(J5,-2),"mm-yyyy") & "'!A:A"),0)) -> 553 | D5: 581 | E5: =D5-C5 -> 28 | F5: 1182.6 | G5: =E5*F5 -> 33112.8 | H5: 5000 | I5: =E5*F5+H5 -> 38112.8 | J5: 45846 | L5: PENDIENTE | M5: =IF(L5="Pagado", I5, 0) -> 0 | P5: =IF(L5="NO APLICA",0, (I5-M5)) -> 38112.8
A6: 5 | B6: =Usuarios!B6 & " " & Usuarios!C6 & " " & Usuarios!D6 -> Marisol Castro | C6: =INDEX(INDIRECT("'" & TEXT(EDATE(J6,-2),"mm-yyyy") & "'!D:D"), MATCH(A6,INDIRECT("'" & TEXT(EDATE(J6,-2),"mm-yyyy") & "'!A:A"),0)) -> 117 | D6: 123 | E6: =D6-C6 -> 6 | F6: 1182.6 | G6: =E6*F6 -> 7095.6 | H6: 5000 | I6: =E6*F6+H6 -> 12095.6 | J6: 45846 | L6: PENDIENTE | M6: =IF(L6="Pagado", I6, 0) -> 0 | P6: =IF(L6="NO APLICA",0, (I6-M6)) -> 12095.6
A7: 6 | B7: =Usuarios!B7 & " " & Usuarios!C7 & " " & Usuarios!D7 -> Mauricio Muñoz | C7: =INDEX(INDIRECT("'" & TEXT(EDATE(J7,-2),"mm-yyyy") & "'!D:D"), MATCH(A7,INDIRECT("'" & TEXT(EDATE(J7,-2),"mm-yyyy") & "'!A:A"),0)) -> 208 | D7: 220 | E7: =D7-C7 -> 12 | F7: 1182.6 | G7: =E7*F7 -> 14191.2 | H7: 5000 | I7: =E7*F7+H7 -> 19191.2 | J7: 45846 | L7: PENDIENTE | M7: =IF(L7="Pagado", I7, 0) -> 0 | P7: =IF(L7="NO APLICA",0, (I7-M7)) -> 19191.2
A8: 7 | B8: =Usuarios!B8 & " " & Usuarios!C8 & " " & Usuarios!D8 -> Marcelo Millanao | C8: =INDEX(INDIRECT("'" & TEXT(EDATE(J8,-2),"mm-yyyy") & "'!D:D"), MATCH(A8,INDIRECT("'" & TEXT(EDATE(J8,-2),"mm-yyyy") & "'!A:A"),0)) -> 263 | D8: 272 | E8: =D8-C8 -> 9 | F8: 1182.6 | G8: =E8*F8 -> 10643.4 | H8: 5000 | I8: =E8*F8+H8 -> 15643.4 | J8: 45846 | L8: PENDIENTE | M8: =IF(L8="Pagado", I8, 0) -> 0 | P8: =IF(L8="NO APLICA",0, (I8-M8)) -> 15643.4
A9: 8 | B9: =Usuarios!B9 & " " & Usuarios!C9 & " " & Usuarios!D9 -> Gabriel Farias | C9: =INDEX(INDIRECT("'" & TEXT(EDATE(J9,-2),"mm-yyyy") & "'!D:D"), MATCH(A9,INDIRECT("'" & TEXT(EDATE(J9,-2),"mm-yyyy") & "'!A:A"),0)) -> 482 | D9: 508 | E9: =D9-C9 -> 26 | F9: 1182.6 | G9: =E9*F9 -> 30747.6 | H9: 5000 | I9: =E9*F9+H9 -> 35747.6 | J9: 45846 | L9: PENDIENTE | M9: =IF(L9="Pagado", I9, 0) -> 0 | P9: =IF(L9="NO APLICA",0, (I9-M9)) -> 35747.6
A10: 9 | B10: =Usuarios!B10 & " " & Usuarios!C10 & " " & Usuarios!D10 -> Maria Marin | C10: =INDEX(INDIRECT("'" & TEXT(EDATE(J10,-2),"mm-yyyy") & "'!D:D"), MATCH(A10,INDIRECT("'" & TEXT(EDATE(J10,-2),"mm-yyyy") & "'!A:A"),0)) -> 193 | D10: 202 | E10: =D10-C10 -> 9 | F10: 1182.6 | G10: =E10*F10 -> 10643.4 | H10: 5000 | I10: =E10*F10+H10 -> 15643.4 | J10: 45846 | L10: PENDIENTE | M10: =IF(L10="Pagado", I10, 0) -> 0 | P10: =IF(L10="NO APLICA",0, (I10-M10)) -> 15643.4
A11: 10 | B11: =Usuarios!B11 & " " & Usuarios!C11 & " " & Usuarios!D11 -> David Cartes | C11: =INDEX(INDIRECT("'" & TEXT(EDATE(J11,-2),"mm-yyyy") & "'!D:D"), MATCH(A11,INDIRECT("'" & TEXT(EDATE(J11,-2),"mm-yyyy") & "'!A:A"),0)) -> 130 | D11: 140 | E11: =D11-C11 -> 10 | F11: 1182.6 | G11: =E11*F11 -> 11826 | H11: 5000 | I11: =E11*F11+H11 -> 16826 | J11: 45846 | L11: PENDIENTE | M11: =IF(L11="Pagado", I11, 0) -> 0 | P11: =IF(L11="NO APLICA",0, (I11-M11)) -> 16826
A12: 11 | B12: =Usuarios!B12 & " " & Usuarios!C12 & " " & Usuarios!D12 -> Miguel Ñanco | C12: =INDEX(INDIRECT("'" & TEXT(EDATE(J12,-2),"mm-yyyy") & "'!D:D"), MATCH(A12,INDIRECT("'" & TEXT(EDATE(J12,-2),"mm-yyyy") & "'!A:A"),0)) -> 240 | D12: 0 | E12: =D12-C12 -> -240 | F12: 1182.6 | G12: =E12*F12 -> -283824 | H12: 5000 | I12: =E12*F12+H12 -> -278824 | J12: 45846 | L12: PENDIENTE | M12: =IF(L12="Pagado", I12, 0) -> 0 | P12: =IF(L12="NO APLICA",0, (I12-M12)) -> -278824
A13: 12 | B13: =Usuarios!B13 & " " & Usuarios!C13 & " " & Usuarios!D13 -> Pedro Contreras | C13: =INDEX(INDIRECT("'" & TEXT(EDATE(J13,-2),"mm-yyyy") & "'!D:D"), MATCH(A13,INDIRECT("'" & TEXT(EDATE(J13,-2),"mm-yyyy") & "'!A:A"),0)) -> 122 | D13: 129 | E13: =D13-C13 -> 7 | F13: 1182.6 | G13: =E13*F13 -> 8278.2 | H13: 5000 | I13: =E13*F13+H13 -> 13278.2 | J13: 45846 | L13: PENDIENTE | M13: =IF(L13="Pagado", I13, 0) -> 0 | P13: =IF(L13="NO APLICA",0, (I13-M13)) -> 13278.2
... A43: 42 | B43: =Usuarios!B43 & " " & Usuarios!C43 & " " & Usuarios!D43 -> Leo Soto | C43: =INDEX(INDIRECT("'" & TEXT(EDATE(J43,-2),"mm-yyyy") & "'!D:D"), MATCH(A43,INDIRECT("'" & TEXT(EDATE(J43,-2),"mm-yyyy") & "'!A:A"),0)) -> 10 | D43: 10 | E43: =D43-C43 -> 0 | F43: 1182.6 | G43: =E43*F43 -> 0 | H43: 5000 | I43: =E43*F43+H43 -> 5000 | J43: 45846 | L43: PENDIENTE | M43: =IF(L43="Pagado", I43, 0) -> 0 | P43: =IF(L43="NO APLICA",0, (I43-M43)) -> 5000
A44: 43 | B44: =Usuarios!B44 & " " & Usuarios!C44 & " " & Usuarios!D44 -> Ramon Maldonado | C44: =INDEX(INDIRECT("'" & TEXT(EDATE(J44,-2),"mm-yyyy") & "'!D:D"), MATCH(A44,INDIRECT("'" & TEXT(EDATE(J44,-2),"mm-yyyy") & "'!A:A"),0)) -> 0 | D44: 0 | E44: =D44-C44 -> 0 | F44: 1182.6 | G44: =E44*F44 -> 0 | H44: 5000 | I44: =E44*F44+H44 -> 5000 | J44: 45846 | L44: PENDIENTE | M44: =IF(L44="Pagado", I44, 0) -> 0 | O44: TRANSFERENCIA | P44: =IF(L44="NO APLICA",0, (I44-M44)) -> 5000
A45: 44 | B45: =Usuarios!B45 & " " & Usuarios!C45 & " " & Usuarios!D45 -> María Sonia Quintui | C45: =INDEX(INDIRECT("'" & TEXT(EDATE(J45,-2),"mm-yyyy") & "'!D:D"), MATCH(A45,INDIRECT("'" & TEXT(EDATE(J45,-2),"mm-yyyy") & "'!A:A"),0)) -> 11 | D45: 14 | E45: =D45-C45 -> 3 | F45: 1182.6 | G45: =E45*F45 -> 3547.8 | H45: 5000 | I45: =E45*F45+H45 -> 8547.8 | J45: 45846 | L45: PENDIENTE | M45: =IF(L45="Pagado", I45, 0) -> 0 | P45: =IF(L45="NO APLICA",0, (I45-M45)) -> 8547.8
A46: 45 | B46: =Usuarios!B46 & " " & Usuarios!C46 & " " & Usuarios!D46 -> Monica Cuello | C46: =INDEX(INDIRECT("'" & TEXT(EDATE(J46,-2),"mm-yyyy") & "'!D:D"), MATCH(A46,INDIRECT("'" & TEXT(EDATE(J46,-2),"mm-yyyy") & "'!A:A"),0)) -> 0 | D46: 0 | E46: =D46-C46 -> 0 | F46: 1182.6 | G46: =E46*F46 -> 0 | H46: 5000 | I46: =E46*F46+H46 -> 5000 | J46: 45846 | L46: PENDIENTE | M46: =IF(L46="Pagado", I46, 0) -> 0 | P46: =IF(L46="NO APLICA",0, (I46-M46)) -> 5000
A47: 46 | B47: =Usuarios!B47 & " " & Usuarios!C47 & " " & Usuarios!D47 -> Mauricio Muñoz taller | C47: =INDEX(INDIRECT("'" & TEXT(EDATE(J47,-2),"mm-yyyy") & "'!D:D"), MATCH(A47,INDIRECT("'" & TEXT(EDATE(J47,-2),"mm-yyyy") & "'!A:A"),0)) -> 0 | D47: 0 | E47: =D47-C47 -> 0 | F47: 1182.6 | G47: =E47*F47 -> 0 | H47: 5000 | I47: =E47*F47+H47 -> 5000 | J47: 45846 | L47: PENDIENTE | M47: =IF(L47="Pagado", I47, 0) -> 0 | P47: =IF(L47="NO APLICA",0, (I47-M47)) -> 5000
A48: 47 | B48: =Usuarios!B48 & " " & Usuarios!C48 & " " & Usuarios!D48 -> Pablo Contreras | C48: =INDEX(INDIRECT("'" & TEXT(EDATE(J48,-2),"mm-yyyy") & "'!D:D"), MATCH(A48,INDIRECT("'" & TEXT(EDATE(J48,-2),"mm-yyyy") & "'!A:A"),0)) -> 0 | D48: 0 | E48: =D48-C48 -> 0 | F48: 1182.6 | G48: =E48*F48 -> 0 | H48: 5000 | I48: =E48*F48+H48 -> 5000 | J48: 45846 | L48: NO APLICA | M48: =IF(L48="Pagado", I48, 0) -> 0 | P48: =IF(L48="NO APLICA",0, (I48-M48)) -> 0
A49: 48 | B49: =Usuarios!B49 & " " & Usuarios!C49 & " " & Usuarios!D49 -> Luis Vicente Mondaca Muñoz | C49: =INDEX(INDIRECT("'" & TEXT(EDATE(J49,-2),"mm-yyyy") & "'!D:D"), MATCH(A49,INDIRECT("'" & TEXT(EDATE(J49,-2),"mm-yyyy") & "'!A:A"),0)) -> 319 | D49: 339 | E49: =D49-C49 -> 20 | F49: 1182.6 | G49: =E49*F49 -> 23652 | H49: 5000 | I49: =E49*F49+H49 -> 28652 | J49: 45846 | L49: PAGADO | M49: =IF(L49="Pagado", I49, 0) -> 28652 | N49: 45939 | O49: EFECTIVO | P49: =IF(L49="NO APLICA",0, (I49-M49)) -> 0
A50: 49 | B50: =Usuarios!B50 & " " & Usuarios!C50 & " " & Usuarios!D50 -> Rosa Nuñez | C50: =INDEX(INDIRECT("'" & TEXT(EDATE(J50,-2),"mm-yyyy") & "'!D:D"), MATCH(A50,INDIRECT("'" & TEXT(EDATE(J50,-2),"mm-yyyy") & "'!A:A"),0)) -> 86 | D50: 89 | E50: =D50-C50 -> 3 | F50: 1182.6 | G50: =E50*F50 -> 3547.8 | H50: 5000 | I50: =E50*F50+H50 -> 8547.8 | J50: 45846 | L50: PENDIENTE | M50: =IF(L50="Pagado", I50, 0) -> 0 | P50: =IF(L50="NO APLICA",0, (I50-M50)) -> 8547.8
A51: 50 | B51: =Usuarios!B51 & " " & Usuarios!C51 & " " & Usuarios!D51 -> Gloria Isamar Velasquez Almonacid | C51: =INDEX(INDIRECT("'" & TEXT(EDATE(J51,-2),"mm-yyyy") & "'!D:D"), MATCH(A51,INDIRECT("'" & TEXT(EDATE(J51,-2),"mm-yyyy") & "'!A:A"),0)) -> 50 | D51: 57 | E51: =D51-C51 -> 7 | F51: 1182.6 | G51: =E51*F51 -> 8278.2 | H51: 5000 | I51: =E51*F51+H51 -> 13278.2 | J51: 45846 | L51: PENDIENTE | M51: =IF(L51="Pagado", I51, 0) -> 0 | P51: =IF(L51="NO APLICA",0, (I51-M51)) -> 13278.2
A52: 51 | B52: =Usuarios!B52 & " " & Usuarios!C52 & " " & Usuarios!D52 -> Maria Manquian | C52: =INDEX(INDIRECT("'" & TEXT(EDATE(J52,-2),"mm-yyyy") & "'!D:D"), MATCH(A52,INDIRECT("'" & TEXT(EDATE(J52,-2),"mm-yyyy") & "'!A:A"),0)) -> 0 | D52: 0 | E52: =D52-C52 -> 0 | F52: 1182.6 | G52: =E52*F52 -> 0 | H52: 5000 | I52: =E52*F52+H52 -> 5000 | J52: 45846 | L52: PENDIENTE | M52: =IF(L52="Pagado", I52, 0) -> 0 | O52: TRANSFERENCIA | P52: =IF(L52="NO APLICA",0, (I52-M52)) -> 5000
A53: 52 | B53: =Usuarios!B53 & " " & Usuarios!C53 & " " & Usuarios!D53 -> Esteban Oyarzo Levil | C53: =INDEX(INDIRECT("'" & TEXT(EDATE(J53,-2),"mm-yyyy") & "'!D:D"), MATCH(A53,INDIRECT("'" & TEXT(EDATE(J53,-2),"mm-yyyy") & "'!A:A"),0)) -> 0 | D53: 0 | E53: =D53-C53 -> 0 | F53: 1182.6 | G53: =E53*F53 -> 0 | H53: 5000 | I53: =E53*F53+H53 -> 5000 | J53: 45846 | L53: PENDIENTE | M53: =IF(L53="Pagado", I53, 0) -> 0 | P53: =IF(L53="NO APLICA",0, (I53-M53)) -> 5000
A54: 53 | B54: =Usuarios!B54 & " " & Usuarios!C54 & " " & Usuarios!D54 -> Nicolas Andres Cardenas Bustamante | C54: =INDEX(INDIRECT("'" & TEXT(EDATE(J54,-2),"mm-yyyy") & "'!D:D"), MATCH(A54,INDIRECT("'" & TEXT(EDATE(J54,-2),"mm-yyyy") & "'!A:A"),0)) -> 0 | D54: 0 | E54: =D54-C54 -> 0 | F54: 1182.6 | G54: =E54*F54 -> 0 | H54: 5000 | I54: =E54*F54+H54 -> 5000 | J54: 45846 | L54: PENDIENTE | M54: =IF(L54="Pagado", I54, 0) -> 0 | P54: =IF(L54="NO APLICA",0, (I54-M54)) -> 5000
A55: 54 | B55: =Usuarios!B55 & " " & Usuarios!C55 & " " & Usuarios!D55 -> Rosa Mancilla | C55: =INDEX(INDIRECT("'" & TEXT(EDATE(J55,-2),"mm-yyyy") & "'!D:D"), MATCH(A55,INDIRECT("'" & TEXT(EDATE(J55,-2),"mm-yyyy") & "'!A:A"),0)) -> 106 | D55: 106 | E55: =D55-C55 -> 0 | F55: 1182.6 | G55: =E55*F55 -> 0 | H55: 5000 | I55: =E55*F55+H55 -> 5000 | J55: 45846 | L55: PENDIENTE | M55: =IF(L55="Pagado", I55, 0) -> 0 | P55: =IF(L55="NO APLICA",0, (I55-M55)) -> 5000
A56: 55 | B56: =Usuarios!B56 & " " & Usuarios!C56 & " " & Usuarios!D56 -> Guido Quintuy - Sitio vacío | C56: =INDEX(INDIRECT("'" & TEXT(EDATE(J56,-2),"mm-yyyy") & "'!D:D"), MATCH(A56,INDIRECT("'" & TEXT(EDATE(J56,-2),"mm-yyyy") & "'!A:A"),0)) -> 0 | D56: 0 | E56: =D56-C56 -> 0 | F56: 1182.6 | G56: =E56*F56 -> 0 | H56: 5000 | I56: =E56*F56+H56 -> 5000 | J56: 45846 | L56: NO APLICA | M56: =IF(L56="Pagado", I56, 0) -> 0 | P56: =IF(L56="NO APLICA",0, (I56-M56)) -> 0
A57: 56 | B57: =Usuarios!B57 & " " & Usuarios!C57 & " " & Usuarios!D57 -> Mario Velasquez | C57: =INDEX(INDIRECT("'" & TEXT(EDATE(J57,-2),"mm-yyyy") & "'!D:D"), MATCH(A57,INDIRECT("'" & TEXT(EDATE(J57,-2),"mm-yyyy") & "'!A:A"),0)) -> 36 | D57: 47 | E57: =D57-C57 -> 11 | F57: 1182.6 | G57: =E57*F57 -> 13008.6 | H57: 5000 | I57: =E57*F57+H57 -> 18008.6 | J57: 45846 | L57: PENDIENTE | M57: =IF(L57="Pagado", I57, 0) -> 0 | P57: =IF(L57="NO APLICA",0, (I57-M57)) -> 18008.6
A58: 57 | B58: =Usuarios!B58 & " " & Usuarios!C58 & " " & Usuarios!D58 -> Lishby Fuentes Diaz | C58: =INDEX(INDIRECT("'" & TEXT(EDATE(J58,-2),"mm-yyyy") & "'!D:D"), MATCH(A58,INDIRECT("'" & TEXT(EDATE(J58,-2),"mm-yyyy") & "'!A:A"),0)) -> 0 | D58: 0 | E58: =D58-C58 -> 0 | F58: 1182.6 | G58: =E58*F58 -> 0 | H58: 5000 | I58: =E58*F58+H58 -> 5000 | J58: 45846 | L58: PENDIENTE | M58: =IF(L58="Pagado", I58, 0) -> 0 | P58: =IF(L58="NO APLICA",0, (I58-M58)) -> 5000

Sheet 07-2025
A1: ID | B1: Nombre | C1: Lectura_Anterior | D1: Lectura_Actual | E1: Consumo_m3 | F1: Tarifa_m3 | G1: Subtotal_Consumo | H1: Cargo_Fijo | I1: Total_Factura | J1: Fecha_Lectura | K1: Periodo | L1: Estado_Pago | M1: Monto_Pagado | N1: Fecha_Pago | O1: Forma_Pago | P1: Saldo_Pendiente | Q1: comprobante_link
A2: 41 | B2: =Usuarios!B42 & " " & Usuarios!C42 & " " & Usuarios!D42 -> Astrid Gomez | C2: =INDEX(INDIRECT("'" & TEXT(EDATE(J2,-2),"mm-yyyy") & "'!D:D"), MATCH(A2,INDIRECT("'" & TEXT(EDATE(J2,-2),"mm-yyyy") & "'!A:A"),0)) -> 111 | D2: 115 | E2: =D2-C2 -> 4 | F2: 1182.6 | G2: =E2*F2 -> 4730.4 | H2: 5000 | I2: =E2*F2+H2 -> 9730.4 | J2: 45877 | L2: PENDIENTE | M2: =IF(L2="Pagado", I2, 0) -> 0 | P2: =IF(L2="NO APLICA",0, (I2-M2)) -> 9730.4
A3: 16 | B3: =Usuarios!B17 & " " & Usuarios!C17 & " " & Usuarios!D17 -> Carlos Agüero | C3: =INDEX(INDIRECT("'" & TEXT(EDATE(J3,-2),"mm-yyyy") & "'!D:D"), MATCH(A3,INDIRECT("'" & TEXT(EDATE(J3,-2),"mm-yyyy") & "'!A:A"),0)) -> 205 | D3: 224 | E3: =D3-C3 -> 19 | F3: 1182.6 | G3: =E3*F3 -> 22469.4 | H3: 5000 | I3: =E3*F3+H3 -> 27469.4 | J3: 45877 | L3: PAGADO | M3: =IF(L3="Pagado", I3, 0) -> 27469.4 | P3: =IF(L3="NO APLICA",0, (I3-M3)) -> 0
A4: 13 | B4: =Usuarios!B14 & " " & Usuarios!C14 & " " & Usuarios!D14 -> Carlos Gamin | C4: =INDEX(INDIRECT("'" & TEXT(EDATE(J4,-2),"mm-yyyy") & "'!D:D"), MATCH(A4,INDIRECT("'" & TEXT(EDATE(J4,-2),"mm-yyyy") & "'!A:A"),0)) -> 210 | D4: 221 | E4: =D4-C4 -> 11 | F4: 1182.6 | G4: =E4*F4 -> 13008.6 | H4: 5000 | I4: =E4*F4+H4 -> 18008.6 | J4: 45877 | L4: PENDIENTE | M4: =IF(L4="Pagado", I4, 0) -> 0 | P4: =IF(L4="NO APLICA",0, (I4-M4)) -> 18008.6
A5: 23 | B5: =Usuarios!B24 & " " & Usuarios!C24 & " " & Usuarios!D24 -> Carlos Nahuelpan | C5: =INDEX(INDIRECT("'" & TEXT(EDATE(J5,-2),"mm-yyyy") & "'!D:D"), MATCH(A5,INDIRECT("'" & TEXT(EDATE(J5,-2),"mm-yyyy") & "'!A:A"),0)) -> 122 | D5: 127 | E5: =D5-C5 -> 5 | F5: 1182.6 | G5: =E5*F5 -> 5913 | H5: 5000 | I5: =E5*F5+H5 -> 10913 | J5: 45877 | L5: PAGADO | M5: =IF(L5="Pagado", I5, 0) -> 10913 | P5: =IF(L5="NO APLICA",0, (I5-M5)) -> 0
A6: 4 | B6: =Usuarios!B5 & " " & Usuarios!C5 & " " & Usuarios!D5 -> Cristian Oyarzo | C6: =INDEX(INDIRECT("'" & TEXT(EDATE(J6,-2),"mm-yyyy") & "'!D:D"), MATCH(A6,INDIRECT("'" & TEXT(EDATE(J6,-2),"mm-yyyy") & "'!A:A"),0)) -> 581 | D6: 615 | E6: =D6-C6 -> 34 | F6: 1182.6 | G6: =E6*F6 -> 40208.4 | H6: 5000 | I6: =E6*F6+H6 -> 45208.4 | J6: 45877 | L6: PAGADO | M6: =IF(L6="Pagado", I6, 0) -> 45208.4 | P6: =IF(L6="NO APLICA",0, (I6-M6)) -> 0
A7: 36 | B7: =Usuarios!B37 & " " & Usuarios!C37 & " " & Usuarios!D37 -> Danilo Soto Soto | C7: =INDEX(INDIRECT("'" & TEXT(EDATE(J7,-2),"mm-yyyy") & "'!D:D"), MATCH(A7,INDIRECT("'" & TEXT(EDATE(J7,-2),"mm-yyyy") & "'!A:A"),0)) -> 0 | D7: 0 | E7: =D7-C7 -> 0 | F7: 1182.6 | G7: =E7*F7 -> 0 | H7: 5000 | I7: =E7*F7+H7 -> 5000 | J7: 45877 | L7: PENDIENTE | M7: =IF(L7="Pagado", I7, 0) -> 0 | P7: =IF(L7="NO APLICA",0, (I7-M7)) -> 5000
A8: 10 | B8: =Usuarios!B11 & " " & Usuarios!C11 & " " & Usuarios!D11 -> David Cartes | C8: =INDEX(INDIRECT("'" & TEXT(EDATE(J8,-2),"mm-yyyy") & "'!D:D"), MATCH(A8,INDIRECT("'" & TEXT(EDATE(J8,-2),"mm-yyyy") & "'!A:A"),0)) -> 140 | D8: 150 | E8: =D8-C8 -> 10 | F8: 1182.6 | G8: =E8*F8 -> 11826 | H8: 5000 | I8: =E8*F8+H8 -> 16826 | J8: 45877 | L8: PAGADO | M8: =IF(L8="Pagado", I8, 0) -> 16826 | P8: =IF(L8="NO APLICA",0, (I8-M8)) -> 0
A9: 19 | B9: =Usuarios!B20 & " " & Usuarios!C20 & " " & Usuarios!D20 -> Eduardo Chavez | C9: =INDEX(INDIRECT("'" & TEXT(EDATE(J9,-2),"mm-yyyy") & "'!D:D"), MATCH(A9,INDIRECT("'" & TEXT(EDATE(J9,-2),"mm-yyyy") & "'!A:A"),0)) -> 93 | D9: 110 | E9: =D9-C9 -> 17 | F9: 1182.6 | G9: =E9*F9 -> 20104.2 | H9: 5000 | I9: =E9*F9+H9 -> 25104.2 | J9: 45877 | L9: PAGADO | M9: =IF(L9="Pagado", I9, 0) -> 25104.2 | P9: =IF(L9="NO APLICA",0, (I9-M9)) -> 0
A10: 52 | B10: =Usuarios!B53 & " " & Usuarios!C53 & " " & Usuarios!D53 -> Esteban Oyarzo Levil | C10: =INDEX(INDIRECT("'" & TEXT(EDATE(J10,-2),"mm-yyyy") & "'!D:D"), MATCH(A10,INDIRECT("'" & TEXT(EDATE(J10,-2),"mm-yyyy") & "'!A:A"),0)) -> 0 | D10: 0 | E10: =D10-C10 -> 0 | F10: 1182.6 | G10: =E10*F10 -> 0 | H10: 5000 | I10: =E10*F10+H10 -> 5000 | J10: 45877 | L10: PENDIENTE | M10: =IF(L10="Pagado", I10, 0) -> 0 | P10: =IF(L10="NO APLICA",0, (I10-M10)) -> 5000
A11: 8 | B11: =Usuarios!B9 & " " & Usuarios!C9 & " " & Usuarios!D9 -> Gabriel Farias | C11: =INDEX(INDIRECT("'" & TEXT(EDATE(J11,-2),"mm-yyyy") & "'!D:D"), MATCH(A11,INDIRECT("'" & TEXT(EDATE(J11,-2),"mm-yyyy") & "'!A:A"),0)) -> 508 | D11: 531 | E11: =D11-C11 -> 23 | F11: 1182.6 | G11: =E11*F11 -> 27199.8 | H11: 5000 | I11: =E11*F11+H11 -> 32199.8 | J11: 45877 | L11: PAGADO | M11: =IF(L11="Pagado", I11, 0) -> 32199.8 | P11: =IF(L11="NO APLICA",0, (I11-M11)) -> 0
A12: 2 | B12: =Usuarios!B3 & " " & Usuarios!C3 & " " & Usuarios!D3 -> Gabriel Barria Zuñiga | C12: =INDEX(INDIRECT("'" & TEXT(EDATE(J12,-2),"mm-yyyy") & "'!D:D"), MATCH(A12,INDIRECT("'" & TEXT(EDATE(J12,-2),"mm-yyyy") & "'!A:A"),0)) -> 351 | D12: 372 | E12: =D12-C12 -> 21 | F12: 1182.6 | G12: =E12*F12 -> 24834.6 | H12: 5000 | I12: =E12*F12+H12 -> 29834.6 | J12: 45877 | L12: PAGADO | M12: =IF(L12="Pagado", I12, 0) -> 29834.6 | P12: =IF(L12="NO APLICA",0, (I12-M12)) -> 0
A13: 3 | B13: =Usuarios!B4 & " " & Usuarios!C4 & " " & Usuarios!D4 -> Gino Reyes | C13: =INDEX(INDIRECT("'" & TEXT(EDATE(J13,-2),"mm-yyyy") & "'!D:D"), MATCH(A13,INDIRECT("'" & TEXT(EDATE(J13,-2),"mm-yyyy") & "'!A:A"),0)) -> 1 | D13: 3 | E13: =D13-C13 -> 2 | F13: 1182.6 | G13: =E13*F13 -> 2365.2 | H13: 5000 | I13: =E13*F13+H13 -> 7365.2 | J13: 45877 | L13: PAGADO | M13: =IF(L13="Pagado", I13, 0) -> 7365.2 | P13: =IF(L13="NO APLICA",0, (I13-M13)) -> 0
A14: 39 | B14: =Usuarios!B40 & " " & Usuarios!C40 & " " & Usuarios!D40 -> Gloria Alvarez | C14: =INDEX(INDIRECT("'" & TEXT(EDATE(J14,-2),"mm-yyyy") & "'!D:D"), MATCH(A14,INDIRECT("'" & TEXT(EDATE(J14,-2),"mm-yyyy") & "'!A:A"),0)) -> 10 | D14: 14 | E14: =D14-C14 -> 4 | F14: 1182.6 | G14: =E14*F14 -> 4730.4 | H14: 5000 | I14: =E14*F14+H14 -> 9730.4 | J14: 45877 | L14: PAGADO | M14: =IF(L14="Pagado", I14, 0) -> 9730.4 | P14: =IF(L14="NO APLICA",0, (I14-M14)) -> 0
A15: 40 | B15: =Usuarios!B41 & " " & Usuarios!C41 & " " & Usuarios!D41 -> Gloria Levil | C15: =INDEX(INDIRECT("'" & TEXT(EDATE(J15,-2),"mm-yyyy") & "'!D:D"), MATCH(A15,INDIRECT("'" & TEXT(EDATE(J15,-2),"mm-yyyy") & "'!A:A"),0)) -> 99 | D15: 99 | E15: =D15-C15 -> 0 | F15: 1182.6 | G15: =E15*F15 -> 0 | H15: 5000 | I15: =E15*F15+H15 -> 5000 | J15: 45877 | L15: PENDIENTE | M15: =IF(L15="Pagado", I15, 0) -> 0 | P15: =IF(L15="NO APLICA",0, (I15-M15)) -> 5000
A16: 50 | B16: =Usuarios!B51 & " " & Usuarios!C51 & " " & Usuarios!D51 -> Gloria Isamar Velasquez Almonacid | C16: =INDEX(INDIRECT("'" & TEXT(EDATE(J16,-2),"mm-yyyy") & "'!D:D"), MATCH(A16,INDIRECT("'" & TEXT(EDATE(J16,-2),"mm-yyyy") & "'!A:A"),0)) -> 57 | D16: 66 | E16: =D16-C16 -> 9 | F16: 1182.6 | G16: =E16*F16 -> 10643.4 | H16: 5000 | I16: =E16*F16+H16 -> 15643.4 | J16: 45877 | L16: PAGADO | M16: =IF(L16="Pagado", I16, 0) -> 15643.4 | P16: =IF(L16="NO APLICA",0, (I16-M16)) -> 0
A17: 26 | B17: =Usuarios!B27 & " " & Usuarios!C27 & " " & Usuarios!D27 -> Guido Quintuy | C17: =INDEX(INDIRECT("'" & TEXT(EDATE(J17,-2),"mm-yyyy") & "'!D:D"), MATCH(A17,INDIRECT("'" & TEXT(EDATE(J17,-2),"mm-yyyy") & "'!A:A"),0)) -> 145 | J17: 45877 | L17: NO APLICA
A18: 55 | B18: =Usuarios!B56 & " " & Usuarios!C56 & " " & Usuarios!D56 -> Guido Quintuy - Sitio vacío | C18: =INDEX(INDIRECT("'" & TEXT(EDATE(J18,-2),"mm-yyyy") & "'!D:D"), MATCH(A18,INDIRECT("'" & TEXT(EDATE(J18,-2),"mm-yyyy") & "'!A:A"),0)) -> 0 | D18: 0 | E18: =D18-C18 -> 0 | F18: 1182.6 | G18: =E18*F18 -> 0 | H18: 5000 | I18: =E18*F18+H18 -> 5000 | J18: 45877 | L18: PENDIENTE | M18: =IF(L18="Pagado", I18, 0) -> 0 | P18: =IF(L18="NO APLICA",0, (I18-M18)) -> 5000
A19: 25 | B19: =Usuarios!B26 & " " & Usuarios!C26 & " " & Usuarios!D26 -> Inés Velasquez | C19: =INDEX(INDIRECT("'" & TEXT(EDATE(J19,-2),"mm-yyyy") & "'!D:D"), MATCH(A19,INDIRECT("'" & TEXT(EDATE(J19,-2),"mm-yyyy") & "'!A:A"),0)) -> 128 | D19: 134 | E19: =D19-C19 -> 6 | F19: 1182.6 | G19: =E19*F19 -> 7095.6 | H19: 5000 | I19: =E19*F19+H19 -> 12095.6 | J19: 45877 | L19: PAGADO | M19: =IF(L19="Pagado", I19, 0) -> 12095.6 | P19: =IF(L19="NO APLICA",0, (I19-M19)) -> 0
A20: 17 | B20: =Usuarios!B18 & " " & Usuarios!C18 & " " & Usuarios!D18 -> Joaquin Claramunt | C20: =INDEX(INDIRECT("'" & TEXT(EDATE(J20,-2),"mm-yyyy") & "'!D:D"), MATCH(A20,INDIRECT("'" & TEXT(EDATE(J20,-2),"mm-yyyy") & "'!A:A"),0)) -> 194 | D20: 210 | E20: =D20-C20 -> 16 | F20: 1182.6 | G20: =E20*F20 -> 18921.6 | H20: 5000 | I20: =E20*F20+H20 -> 23921.6 | J20: 45877 | L20: PAGADO | M20: =IF(L20="Pagado", I20, 0) -> 23921.6 | P20: =IF(L20="NO APLICA",0, (I20-M20)) -> 0
A21: 35 | B21: =Usuarios!B36 & " " & Usuarios!C36 & " " & Usuarios!D36 -> José Paredes | C21: =INDEX(INDIRECT("'" & TEXT(EDATE(J21,-2),"mm-yyyy") & "'!D:D"), MATCH(A21,INDIRECT("'" & TEXT(EDATE(J21,-2),"mm-yyyy") & "'!A:A"),0)) -> 0 | D21: 0 | E21: =D21-C21 -> 0 | F21: 1182.6 | G21: =E21*F21 -> 0 | H21: 5000 | I21: =E21*F21+H21 -> 5000 | J21: 45877 | L21: PENDIENTE | M21: =IF(L21="Pagado", I21, 0) -> 0 | P21: =IF(L21="NO APLICA",0, (I21-M21)) -> 5000
A22: 20 | B22: =Usuarios!B21 & " " & Usuarios!C21 & " " & Usuarios!D21 -> Juan Chavez | C22: =INDEX(INDIRECT("'" & TEXT(EDATE(J22,-2),"mm-yyyy") & "'!D:D"), MATCH(A22,INDIRECT("'" & TEXT(EDATE(J22,-2),"mm-yyyy") & "'!A:A"),0)) -> 28 | D22: 29 | E22: =D22-C22 -> 1 | F22: 1182.6 | G22: =E22*F22 -> 1182.6 | H22: 5000 | I22: =E22*F22+H22 -> 6182.6 | J22: 45877 | L22: PAGADO | M22: =IF(L22="Pagado", I22, 0) -> 6182.6 | P22: =IF(L22="NO APLICA",0, (I22-M22)) -> 0
A23: 42 | B23: =Usuarios!B43 & " " & Usuarios!C43 & " " & Usuarios!D43 -> Leo Soto | C23: =INDEX(INDIRECT("'" & TEXT(EDATE(J23,-2),"mm-yyyy") & "'!D:D"), MATCH(A23,INDIRECT("'" & TEXT(EDATE(J23,-2),"mm-yyyy") & "'!A:A"),0)) -> 10 | D23: 0 | E23: =D23-C23 -> -10 | F23: 1182.6 | G23: =E23*F23 -> -11826 | H23: 5000 | I23: =E23*F23+H23 -> -6826 | J23: 45877 | L23: PENDIENTE | M23: =IF(L23="Pagado", I23, 0) -> 0 | P23: =IF(L23="NO APLICA",0, (I23-M23)) -> -6826
A24: 57 | B24: =Usuarios!B58 & " " & Usuarios!C58 & " " & Usuarios!D58 -> Lishby Fuentes Diaz | C24: =INDEX(INDIRECT("'" & TEXT(EDATE(J24,-2),"mm-yyyy") & "'!D:D"), MATCH(A24,INDIRECT("'" & TEXT(EDATE(J24,-2),"mm-yyyy") & "'!A:A"),0)) -> 0 | D24: 15 | E24: =D24-C24 -> 15 | F24: 1182.6 | G24: =E24*F24 -> 17739 | H24: 5000 | I24: =E24*F24+H24 -> 22739 | J24: 45877 | L24: PAGADO | M24: =IF(L24="Pagado", I24, 0) -> 22739 | P24: =IF(L24="NO APLICA",0, (I24-M24)) -> 0
A25: 48 | B25: =Usuarios!B49 & " " & Usuarios!C49 & " " & Usuarios!D49 -> Luis Vicente Mondaca Muñoz | C25: =INDEX(INDIRECT("'" & TEXT(EDATE(J25,-2),"mm-yyyy") & "'!D:D"), MATCH(A25,INDIRECT("'" & TEXT(EDATE(J25,-2),"mm-yyyy") & "'!A:A"),0)) -> 339 | D25: 359 | E25: =D25-C25 -> 20 | F25: 1182.6 | G25: =E25*F25 -> 23652 | H25: 5000 | I25: =E25*F25+H25 -> 28652 | J25: 45877 | L25: PAGADO | M25: =IF(L25="Pagado", I25, 0) -> 28652 | N25: 45939 | O25: EFECTIVO | P25: =IF(L25="NO APLICA",0, (I25-M25)) -> 0
A26: 30 | B26: =Usuarios!B31 & " " & Usuarios!C31 & " " & Usuarios!D31 -> Luz Maldonado | C26: =INDEX(INDIRECT("'" & TEXT(EDATE(J26,-2),"mm-yyyy") & "'!D:D"), MATCH(A26,INDIRECT("'" & TEXT(EDATE(J26,-2),"mm-yyyy") & "'!A:A"),0)) -> 5 | D26: 5 | E26: =D26-C26 -> 0 | F26: 1182.6 | G26: =E26*F26 -> 0 | H26: 5000 | I26: =E26*F26+H26 -> 5000 | J26: 45877 | L26: PAGADO | M26: =IF(L26="Pagado", I26, 0) -> 5000 | P26: =IF(L26="NO APLICA",0, (I26-M26)) -> 0
A27: 7 | B27: =Usuarios!B8 & " " & Usuarios!C8 & " " & Usuarios!D8 -> Marcelo Millanao | C27: =INDEX(INDIRECT("'" & TEXT(EDATE(J27,-2),"mm-yyyy") & "'!D:D"), MATCH(A27,INDIRECT("'" & TEXT(EDATE(J27,-2),"mm-yyyy") & "'!A:A"),0)) -> 272 | D27: 285 | E27: =D27-C27 -> 13 | F27: 1182.6 | G27: =E27*F27 -> 15373.8 | H27: 5000 | I27: =E27*F27+H27 -> 20373.8 | J27: 45877 | L27: PAGADO | M27: =IF(L27="Pagado", I27, 0) -> 20373.8 | P27: =IF(L27="NO APLICA",0, (I27-M27)) -> 0
A28: 51 | B28: =Usuarios!B52 & " " & Usuarios!C52 & " " & Usuarios!D52 -> Maria Manquian | C28: =INDEX(INDIRECT("'" & TEXT(EDATE(J28,-2),"mm-yyyy") & "'!D:D"), MATCH(A28,INDIRECT("'" & TEXT(EDATE(J28,-2),"mm-yyyy") & "'!A:A"),0)) -> 0 | D28: 0 | E28: =D28-C28 -> 0 | F28: 1182.6 | G28: =E28*F28 -> 0 | H28: 5000 | I28: =E28*F28+H28 -> 5000 | J28: 45877 | L28: PENDIENTE | M28: =IF(L28="Pagado", I28, 0) -> 0 | O28: TRANSFERENCIA | P28: =IF(L28="NO APLICA",0, (I28-M28)) -> 5000
A29: 9 | B29: =Usuarios!B10 & " " & Usuarios!C10 & " " & Usuarios!D10 -> Maria Marin | C29: =INDEX(INDIRECT("'" & TEXT(EDATE(J29,-2),"mm-yyyy") & "'!D:D"), MATCH(A29,INDIRECT("'" & TEXT(EDATE(J29,-2),"mm-yyyy") & "'!A:A"),0)) -> 202 | D29: 212 | E29: =D29-C29 -> 10 | F29: 1182.6 | G29: =E29*F29 -> 11826 | H29: 5000 | I29: =E29*F29+H29 -> 16826 | J29: 45877 | L29: PAGADO | M29: =IF(L29="Pagado", I29, 0) -> 16826 | P29: =IF(L29="NO APLICA",0, (I29-M29)) -> 0
A30: 33 | B30: =Usuarios!B34 & " " & Usuarios!C34 & " " & Usuarios!D34 -> Maria Oliva Soto Almonacid | C30: =INDEX(INDIRECT("'" & TEXT(EDATE(J30,-2),"mm-yyyy") & "'!D:D"), MATCH(A30,INDIRECT("'" & TEXT(EDATE(J30,-2),"mm-yyyy") & "'!A:A"),0)) -> 54 | D30: 55 | E30: =D30-C30 -> 1 | F30: 1182.6 | G30: =E30*F30 -> 1182.6 | H30: 5000 | I30: =E30*F30+H30 -> 6182.6 | J30: 45877 | L30: PAGADO | M30: =IF(L30="Pagado", I30, 0) -> 6182.6 | P30: =IF(L30="NO APLICA",0, (I30-M30)) -> 0
A31: 44 | B31: =Usuarios!B45 & " " & Usuarios!C45 & " " & Usuarios!D45 -> María Sonia Quintui | C31: =INDEX(INDIRECT("'" & TEXT(EDATE(J31,-2),"mm-yyyy") & "'!D:D"), MATCH(A31,INDIRECT("'" & TEXT(EDATE(J31,-2),"mm-yyyy") & "'!A:A"),0)) -> 14 | D31: 18 | E31: =D31-C31 -> 4 | F31: 1182.6 | G31: =E31*F31 -> 4730.4 | H31: 5000 | I31: =E31*F31+H31 -> 9730.4 | J31: 45877 | L31: PENDIENTE | M31: =IF(L31="Pagado", I31, 0) -> 0 | P31: =IF(L31="NO APLICA",0, (I31-M31)) -> 9730.4
A32: 24 | B32: =Usuarios!B25 & " " & Usuarios!C25 & " " & Usuarios!D25 -> Maria Velasquez Miranda | C32: =INDEX(INDIRECT("'" & TEXT(EDATE(J32,-2),"mm-yyyy") & "'!D:D"), MATCH(A32,INDIRECT("'" & TEXT(EDATE(J32,-2),"mm-yyyy") & "'!A:A"),0)) -> 292 | D32: 302 | E32: =D32-C32 -> 10 | F32: 1182.6 | G32: =E32*F32 -> 11826 | H32: 5000 | I32: =E32*F32+H32 -> 16826 | J32: 45877 | L32: PAGADO | M32: =IF(L32="Pagado", I32, 0) -> 16826 | P32: =IF(L32="NO APLICA",0, (I32-M32)) -> 0
A33: 56 | B33: =Usuarios!B57 & " " & Usuarios!C57 & " " & Usuarios!D57 -> Mario Velasquez | C33: =INDEX(INDIRECT("'" & TEXT(EDATE(J33,-2),"mm-yyyy") & "'!D:D"), MATCH(A33,INDIRECT("'" & TEXT(EDATE(J33,-2),"mm-yyyy") & "'!A:A"),0)) -> 47 | D33: 56 | E33: =D33-C33 -> 9 | F33: 1182.6 | G33: =E33*F33 -> 10643.4 | H33: 5000 | I33: =E33*F33+H33 -> 15643.4 | J33: 45877 | L33: PAGADO | M33: =IF(L33="Pagado", I33, 0) -> 15643.4 | P33: =IF(L33="NO APLICA",0, (I33-M33)) -> 0
A34: 5 | B34: =Usuarios!B6 & " " & Usuarios!C6 & " " & Usuarios!D6 -> Marisol Castro | C34: =INDEX(INDIRECT("'" & TEXT(EDATE(J34,-2),"mm-yyyy") & "'!D:D"), MATCH(A34,INDIRECT("'" & TEXT(EDATE(J34,-2),"mm-yyyy") & "'!A:A"),0)) -> 123 | D34: 130 | E34: =D34-C34 -> 7 | F34: 1182.6 | G34: =E34*F34 -> 8278.2 | H34: 5000 | I34: =E34*F34+H34 -> 13278.2 | J34: 45877 | L34: PAGADO | M34: =IF(L34="Pagado", I34, 0) -> 13278.2 | P34: =IF(L34="NO APLICA",0, (I34-M34)) -> 0
A35: 6 | B35: =Usuarios!B7 & " " & Usuarios!C7 & " " & Usuarios!D7 -> Mauricio Muñoz | C35: =INDEX(INDIRECT("'" & TEXT(EDATE(J35,-2),"mm-yyyy") & "'!D:D"), MATCH(A35,INDIRECT("'" & TEXT(EDATE(J35,-2),"mm-yyyy") & "'!A:A"),0)) -> 220 | D35: 225 | E35: =D35-C35 -> 5 | F35: 1182.6 | G35: =E35*F35 -> 5913 | H35: 5000 | I35: =E35*F35+H35 -> 10913 | J35: 45877 | L35: PAGADO | M35: =IF(L35="Pagado", I35, 0) -> 10913 | P35: =IF(L35="NO APLICA",0, (I35-M35)) -> 0
A36: 46 | B36: =Usuarios!B47 & " " & Usuarios!C47 & " " & Usuarios!D47 -> Mauricio Muñoz taller | C36: =INDEX(INDIRECT("'" & TEXT(EDATE(J36,-2),"mm-yyyy") & "'!D:D"), MATCH(A36,INDIRECT("'" & TEXT(EDATE(J36,-2),"mm-yyyy") & "'!A:A"),0)) -> 0 | D36: 0 | E36: =D36-C36 -> 0 | F36: 1182.6 | G36: =E36*F36 -> 0 | H36: 5000 | I36: =E36*F36+H36 -> 5000 | J36: 45877 | L36: PENDIENTE | M36: =IF(L36="Pagado", I36, 0) -> 0 | P36: =IF(L36="NO APLICA",0, (I36-M36)) -> 5000
A37: 11 | B37: =Usuarios!B12 & " " & Usuarios!C12 & " " & Usuarios!D12 -> Miguel Ñanco | C37: =INDEX(INDIRECT("'" & TEXT(EDATE(J37,-2),"mm-yyyy") & "'!D:D"), MATCH(A37,INDIRECT("'" & TEXT(EDATE(J37,-2),"mm-yyyy") & "'!A:A"),0)) -> 0 | D37: 1 | E37: =D37-C37 -> 1 | F37: 1182.6 | G37: =E37*F37 -> 1182.6 | H37: 5000 | I37: =E37*F37+H37 -> 6182.6 | J37: 45877 | L37: PAGADO | M37: =IF(L37="Pagado", I37, 0) -> 6182.6 | P37: =IF(L37="NO APLICA",0, (I37-M37)) -> 0
A38: 29 | B38: =Usuarios!B30 & " " & Usuarios!C30 & " " & Usuarios!D30 -> Miriam Alvarado | C38: =INDEX(INDIRECT("'" & TEXT(EDATE(J38,-2),"mm-yyyy") & "'!D:D"), MATCH(A38,INDIRECT("'" & TEXT(EDATE(J38,-2),"mm-yyyy") & "'!A:A"),0)) -> 613 | D38: 636 | E38: =D38-C38 -> 23 | F38: 1182.6 | G38: =E38*F38 -> 27199.8 | H38: 5000 | I38: =E38*F38+H38 -> 32199.8 | J38: 45877 | L38: PENDIENTE | M38: =IF(L38="Pagado", I38, 0) -> 0 | P38: =IF(L38="NO APLICA",0, (I38-M38)) -> 32199.8
A39: 45 | B39: =Usuarios!B46 & " " & Usuarios!C46 & " " & Usuarios!D46 -> Monica Cuello | C39: =INDEX(INDIRECT("'" & TEXT(EDATE(J39,-2),"mm-yyyy") & "'!D:D"), MATCH(A39,INDIRECT("'" & TEXT(EDATE(J39,-2),"mm-yyyy") & "'!A:A"),0)) -> 0 | D39: 0 | E39: =D39-C39 -> 0 | F39: 1182.6 | G39: =E39*F39 -> 0 | H39: 5000 | I39: =E39*F39+H39 -> 5000 | J39: 45877 | L39: PAGADO | M39: =IF(L39="Pagado", I39, 0) -> 5000 | P39: =IF(L39="NO APLICA",0, (I39-M39)) -> 0
A40: 1 | B40: =Usuarios!B2 & " " & Usuarios!C2 & " " & Usuarios!D2 -> Nancy Zuñiga Villarroel | C40: =INDEX(INDIRECT("'" & TEXT(EDATE(J40,-2),"mm-yyyy") & "'!D:D"), MATCH(A40,INDIRECT("'" & TEXT(EDATE(J40,-2),"mm-yyyy") & "'!A:A"),0)) -> 222 | D40: 233 | E40: =D40-C40 -> 11 | F40: 1182.6 | G40: =E40*F40 -> 13008.6 | H40: 5000 | I40: =E40*F40+H40 -> 18008.6 | J40: 45877 | L40: PENDIENTE | M40: =IF(L40="Pagado", I40, 0) -> 0 | P40: =IF(L40="NO APLICA",0, (I40-M40)) -> 18008.6
A41: 32 | B41: =Usuarios!B33 & " " & Usuarios!C33 & " " & Usuarios!D33 -> Natividad Soto | C41: =INDEX(INDIRECT("'" & TEXT(EDATE(J41,-2),"mm-yyyy") & "'!D:D"), MATCH(A41,INDIRECT("'" & TEXT(EDATE(J41,-2),"mm-yyyy") & "'!A:A"),0)) -> 129 | D41: 153 | E41: =D41-C41 -> 24 | F41: 1182.6 | G41: =E41*F41 -> 28382.4 | H41: 5000 | I41: =E41*F41+H41 -> 33382.4 | J41: 45877 | L41: PAGADO | M41: 28000 | P41: =IF(L41="NO APLICA",0, (I41-M41)) -> 5382.4
A42: 18 | B42: =Usuarios!B19 & " " & Usuarios!C19 & " " & Usuarios!D19 -> Nelson Mansilla | C42: =INDEX(INDIRECT("'" & TEXT(EDATE(J42,-2),"mm-yyyy") & "'!D:D"), MATCH(A42,INDIRECT("'" & TEXT(EDATE(J42,-2),"mm-yyyy") & "'!A:A"),0)) -> 147 | D42: 151 | E42: =D42-C42 -> 4 | F42: 1182.6 | G42: =E42*F42 -> 4730.4 | H42: 5000 | I42: =E42*F42+H42 -> 9730.4 | J42: 45877 | L42: PENDIENTE | M42: =IF(L42="Pagado", I42, 0) -> 0 | P42: =IF(L42="NO APLICA",0, (I42-M42)) -> 9730.4
A43: 53 | B43: =Usuarios!B54 & " " & Usuarios!C54 & " " & Usuarios!D54 -> Nicolas Andres Cardenas Bustamante | C43: =INDEX(INDIRECT("'" & TEXT(EDATE(J43,-2),"mm-yyyy") & "'!D:D"), MATCH(A43,INDIRECT("'" & TEXT(EDATE(J43,-2),"mm-yyyy") & "'!A:A"),0)) -> 0 | D43: 0 | E43: =D43-C43 -> 0 | F43: 1182.6 | G43: =E43*F43 -> 0 | H43: 5000 | I43: =E43*F43+H43 -> 5000 | J43: 45877 | L43: PENDIENTE | M43: =IF(L43="Pagado", I43, 0) -> 0 | P43: =IF(L43="NO APLICA",0, (I43-M43)) -> 5000
A44: 28 | B44: =Usuarios!B29 & " " & Usuarios!C29 & " " & Usuarios!D29 -> Nora Ñanco | C44: =INDEX(INDIRECT("'" & TEXT(EDATE(J44,-2),"mm-yyyy") & "'!D:D"), MATCH(A44,INDIRECT("'" & TEXT(EDATE(J44,-2),"mm-yyyy") & "'!A:A"),0)) -> 494 | D44: 513 | E44: =D44-C44 -> 19 | F44: 1182.6 | G44: =E44*F44 -> 22469.4 | H44: 5000 | I44: =E44*F44+H44 -> 27469.4 | J44: 45877 | L44: PAGADO | M44: =IF(L44="Pagado", I44, 0) -> 27469.4 | P44: =IF(L44="NO APLICA",0, (I44-M44)) -> 0
A45: 38 | B45: =Usuarios!B39 & " " & Usuarios!C39 & " " & Usuarios!D39 -> Norma Sanchez | C45: =INDEX(INDIRECT("'" & TEXT(EDATE(J45,-2),"mm-yyyy") & "'!D:D"), MATCH(A45,INDIRECT("'" & TEXT(EDATE(J45,-2),"mm-yyyy") & "'!A:A"),0)) -> 9 | D45: 9 | E45: =D45-C45 -> 0 | F45: 1182.6 | G45: =E45*F45 -> 0 | H45: 5000 | I45: =E45*F45+H45 -> 5000 | J45: 45877 | L45: PAGADO | M45: =IF(L45="Pagado", I45, 0) -> 5000 | P45: =IF(L45="NO APLICA",0, (I45-M45)) -> 0
A46: 47 | B46: =Usuarios!B48 & " " & Usuarios!C48 & " " & Usuarios!D48 -> Pablo Contreras | C46: =INDEX(INDIRECT("'" & TEXT(EDATE(J46,-2),"mm-yyyy") & "'!D:D"), MATCH(A46,INDIRECT("'" & TEXT(EDATE(J46,-2),"mm-yyyy") & "'!A:A"),0)) -> 0 | J46: 45877 | L46: NO APLICA | M46: =IF(L46="Pagado", I46, 0) -> 0 | P46: =IF(L46="NO APLICA",0, (I46-M46)) -> 0
A47: 31 | B47: =Usuarios!B32 & " " & Usuarios!C32 & " " & Usuarios!D32 -> Patricia Carcamo Gonzales | C47: =INDEX(INDIRECT("'" & TEXT(EDATE(J47,-2),"mm-yyyy") & "'!D:D"), MATCH(A47,INDIRECT("'" & TEXT(EDATE(J47,-2),"mm-yyyy") & "'!A:A"),0)) -> 195 | D47: 219 | E47: =D47-C47 -> 24 | F47: 1182.6 | G47: =E47*F47 -> 28382.4 | H47: 5000 | I47: =E47*F47+H47 -> 33382.4 | J47: 45877 | L47: PAGADO | M47: =IF(L47="Pagado", I47, 0) -> 33382.4 | P47: =IF(L47="NO APLICA",0, (I47-M47)) -> 0
A48: 37 | B48: =Usuarios!B38 & " " & Usuarios!C38 & " " & Usuarios!D38 -> Patricio Alvarez Mancilla | C48: =INDEX(INDIRECT("'" & TEXT(EDATE(J48,-2),"mm-yyyy") & "'!D:D"), MATCH(A48,INDIRECT("'" & TEXT(EDATE(J48,-2),"mm-yyyy") & "'!A:A"),0)) -> 0 | D48: 0 | E48: =D48-C48 -> 0 | F48: 1182.6 | G48: =E48*F48 -> 0 | H48: 5000 | I48: =E48*F48+H48 -> 5000 | J48: 45877 | L48: PAGADO | M48: =IF(L48="Pagado", I48, 0) -> 5000 | P48: =IF(L48="NO APLICA",0, (I48-M48)) -> 0
A49: 27 | B49: =Usuarios!B28 & " " & Usuarios!C28 & " " & Usuarios!D28 -> Pedro Almonacid | C49: =INDEX(INDIRECT("'" & TEXT(EDATE(J49,-2),"mm-yyyy") & "'!D:D"), MATCH(A49,INDIRECT("'" & TEXT(EDATE(J49,-2),"mm-yyyy") & "'!A:A"),0)) -> 236 | D49: 250 | E49: =D49-C49 -> 14 | F49: 1182.6 | G49: =E49*F49 -> 16556.4 | H49: 5000 | I49: =E49*F49+H49 -> 21556.4 | J49: 45877 | L49: PENDIENTE | M49: =IF(L49="Pagado", I49, 0) -> 0 | P49: =IF(L49="NO APLICA",0, (I49-M49)) -> 21556.4
A50: 12 | B50: =Usuarios!B13 & " " & Usuarios!C13 & " " & Usuarios!D13 -> Pedro Contreras | C50: =INDEX(INDIRECT("'" & TEXT(EDATE(J50,-2),"mm-yyyy") & "'!D:D"), MATCH(A50,INDIRECT("'" & TEXT(EDATE(J50,-2),"mm-yyyy") & "'!A:A"),0)) -> 129 | D50: 137 | E50: =D50-C50 -> 8 | F50: 1182.6 | G50: =E50*F50 -> 9460.8 | H50: 5000 | I50: =E50*F50+H50 -> 14460.8 | J50: 45877 | L50: PAGADO | M50: =IF(L50="Pagado", I50, 0) -> 14460.8 | P50: =IF(L50="NO APLICA",0, (I50-M50)) -> 0
A51: 43 | B51: =Usuarios!B44 & " " & Usuarios!C44 & " " & Usuarios!D44 -> Ramon Maldonado | C51: =INDEX(INDIRECT("'" & TEXT(EDATE(J51,-2),"mm-yyyy") & "'!D:D"), MATCH(A51,INDIRECT("'" & TEXT(EDATE(J51,-2),"mm-yyyy") & "'!A:A"),0)) -> 0 | D51: 0 | E51: =D51-C51 -> 0 | F51: 1182.6 | G51: =E51*F51 -> 0 | H51: 5000 | I51: =E51*F51+H51 -> 5000 | J51: 45877 | L51: PAGADO | M51: =IF(L51="Pagado", I51, 0) -> 5000 | O51: TRANSFERENCIA | P51: =IF(L51="NO APLICA",0, (I51-M51)) -> 0
A52: 14 | B52: =Usuarios!B15 & " " & Usuarios!C15 & " " & Usuarios!D15 -> Ramona Mansilla | C52: =INDEX(INDIRECT("'" & TEXT(EDATE(J52,-2),"mm-yyyy") & "'!D:D"), MATCH(A52,INDIRECT("'" & TEXT(EDATE(J52,-2),"mm-yyyy") & "'!A:A"),0)) -> 56 | D52: 59 | E52: 0 | F52: 1182.6 | G52: =E52*F52 -> 0 | H52: 5000 | I52: =E52*F52+H52 -> 5000 | J52: 45877 | L52: PAGADO | M52: =IF(L52="Pagado", I52, 0) -> 5000 | P52: =IF(L52="NO APLICA",0, (I52-M52)) -> 0
A53: 54 | B53: =Usuarios!B55 & " " & Usuarios!C55 & " " & Usuarios!D55 -> Rosa Mancilla | C53: =INDEX(INDIRECT("'" & TEXT(EDATE(J53,-2),"mm-yyyy") & "'!D:D"), MATCH(A53,INDIRECT("'" & TEXT(EDATE(J53,-2),"mm-yyyy") & "'!A:A"),0)) -> 106 | D53: 106 | E53: =D53-C53 -> 0 | F53: 1182.6 | G53: =E53*F53 -> 0 | H53: 5000 | I53: =E53*F53+H53 -> 5000 | J53: 45877 | L53: PAGADO | M53: =IF(L53="Pagado", I53, 0) -> 5000 | P53: =IF(L53="NO APLICA",0, (I53-M53)) -> 0
A54: 49 | B54: =Usuarios!B50 & " " & Usuarios!C50 & " " & Usuarios!D50 -> Rosa Nuñez | C54: =INDEX(INDIRECT("'" & TEXT(EDATE(J54,-2),"mm-yyyy") & "'!D:D"), MATCH(A54,INDIRECT("'" & TEXT(EDATE(J54,-2),"mm-yyyy") & "'!A:A"),0)) -> 89 | D54: 95 | E54: =D54-C54 -> 6 | F54: 1182.6 | G54: =E54*F54 -> 7095.6 | H54: 5000 | I54: =E54*F54+H54 -> 12095.6 | J54: 45877 | L54: PENDIENTE | M54: =IF(L54="Pagado", I54, 0) -> 0 | P54: =IF(L54="NO APLICA",0, (I54-M54)) -> 12095.6
A55: 15 | B55: =Usuarios!B16 & " " & Usuarios!C16 & " " & Usuarios!D16 -> Sandra Mancilla Merino | C55: =INDEX(INDIRECT("'" & TEXT(EDATE(J55,-2),"mm-yyyy") & "'!D:D"), MATCH(A55,INDIRECT("'" & TEXT(EDATE(J55,-2),"mm-yyyy") & "'!A:A"),0)) -> 165 | D55: 172 | E55: =D55-C55 -> 7 | F55: 1182.6 | G55: =E55*F55 -> 8278.2 | H55: 5000 | I55: =E55*F55+H55 -> 13278.2 | J55: 45877 | L55: PAGADO | M55: =IF(L55="Pagado", I55, 0) -> 13278.2 | P55: =IF(L55="NO APLICA",0, (I55-M55)) -> 0
A56: 34 | B56: =Usuarios!B35 & " " & Usuarios!C35 & " " & Usuarios!D35 -> Vanesa Aguilar | C56: =INDEX(INDIRECT("'" & TEXT(EDATE(J56,-2),"mm-yyyy") & "'!D:D"), MATCH(A56,INDIRECT("'" & TEXT(EDATE(J56,-2),"mm-yyyy") & "'!A:A"),0)) -> 572 | D56: 591 | E56: =D56-C56 -> 19 | F56: 1182.6 | G56: =E56*F56 -> 22469.4 | H56: 5000 | I56: =E56*F56+H56 -> 27469.4 | J56: 45877 | L56: PAGADO | M56: =IF(L56="Pagado", I56, 0) -> 27469.4 | P56: =IF(L56="NO APLICA",0, (I56-M56)) -> 0
A57: 22 | B57: =Usuarios!B23 & " " & Usuarios!C23 & " " & Usuarios!D23 -> Yuri Millaquen | C57: =INDEX(INDIRECT("'" & TEXT(EDATE(J57,-2),"mm-yyyy") & "'!D:D"), MATCH(A57,INDIRECT("'" & TEXT(EDATE(J57,-2),"mm-yyyy") & "'!A:A"),0)) -> 185 | D57: 197 | E57: =D57-C57 -> 12 | F57: 1182.6 | G57: =E57*F57 -> 14191.2 | H57: 5000 | I57: =E57*F57+H57 -> 19191.2 | J57: 45877 | L57: PAGADO | M57: =IF(L57="Pagado", I57, 0) -> 19191.2 | P57: =IF(L57="NO APLICA",0, (I57-M57)) -> 0

Sheet 08-2025
A1: ID | B1: Nombre | C1: Lectura_Anterior | D1: Lectura_Actual | E1: Consumo_m3 | F1: Tarifa_m3 | G1: Subtotal_Consumo | H1: Cargo_Fijo | I1: Total_Factura | J1: Fecha_Lectura | K1: Lectura Tomada | L1: Estado_Pago | M1: Monto_Pagado | N1: Fecha_Pago | O1: Forma_Pago | P1: Saldo_Pendiente | Q1: comprobante_link
A2: 41 | B2: =Usuarios!B42 & " " & Usuarios!C42 & " " & Usuarios!D42 -> Astrid Gomez | C2: =INDEX(INDIRECT("'" & TEXT(EDATE(J2,-2),"mm-yyyy") & "'!D:D"), MATCH(A2,INDIRECT("'" & TEXT(EDATE(J2,-2),"mm-yyyy") & "'!A:A"),0)) -> 115 | D2: 120 | E2: =D2-C2 -> 5 | F2: 1182.6 | G2: =E2*F2 -> 5913 | H2: 5000 | I2: =E2*F2+H2 -> 10913 | J2: 45908 | K2: SI | L2: PENDIENTE | M2: =IF(L2="Pagado", I2, 0) -> 0 | P2: =IF(L2="NO APLICA",0, (I2-M2)) -> 10913
A3: 16 | B3: =Usuarios!B17 & " " & Usuarios!C17 & " " & Usuarios!D17 -> Carlos Agüero | C3: =INDEX(INDIRECT("'" & TEXT(EDATE(J3,-2),"mm-yyyy") & "'!D:D"), MATCH(A3,INDIRECT("'" & TEXT(EDATE(J3,-2),"mm-yyyy") & "'!A:A"),0)) -> 224 | D3: 238 | E3: =D3-C3 -> 14 | F3: 1182.6 | G3: =E3*F3 -> 16556.4 | H3: 5000 | I3: =E3*F3+H3 -> 21556.4 | J3: 45908 | K3: SI | L3: PENDIENTE | M3: =IF(L3="Pagado", I3, 0) -> 0 | P3: =IF(L3="NO APLICA",0, (I3-M3)) -> 21556.4
A4: 13 | B4: =Usuarios!B14 & " " & Usuarios!C14 & " " & Usuarios!D14 -> Carlos Gamin | C4: =INDEX(INDIRECT("'" & TEXT(EDATE(J4,-2),"mm-yyyy") & "'!D:D"), MATCH(A4,INDIRECT("'" & TEXT(EDATE(J4,-2),"mm-yyyy") & "'!A:A"),0)) -> 221 | D4: 232 | E4: =D4-C4 -> 11 | F4: 1182.6 | G4: =E4*F4 -> 13008.6 | H4: 5000 | I4: =E4*F4+H4 -> 18008.6 | J4: 45908 | K4: SI | L4: PENDIENTE | M4: =IF(L4="Pagado", I4, 0) -> 0 | P4: =IF(L4="NO APLICA",0, (I4-M4)) -> 18008.6
A5: 23 | B5: =Usuarios!B24 & " " & Usuarios!C24 & " " & Usuarios!D24 -> Carlos Nahuelpan | C5: =INDEX(INDIRECT("'" & TEXT(EDATE(J5,-2),"mm-yyyy") & "'!D:D"), MATCH(A5,INDIRECT("'" & TEXT(EDATE(J5,-2),"mm-yyyy") & "'!A:A"),0)) -> 127 | D5: 135 | E5: =D5-C5 -> 8 | F5: 1182.6 | G5: =E5*F5 -> 9460.8 | H5: 5000 | I5: =E5*F5+H5 -> 14460.8 | J5: 45908 | K5: SI | L5: PENDIENTE | M5: =IF(L5="Pagado", I5, 0) -> 0 | P5: =IF(L5="NO APLICA",0, (I5-M5)) -> 14460.8
A6: 4 | B6: =Usuarios!B5 & " " & Usuarios!C5 & " " & Usuarios!D5 -> Cristian Oyarzo | C6: =INDEX(INDIRECT("'" & TEXT(EDATE(J6,-2),"mm-yyyy") & "'!D:D"), MATCH(A6,INDIRECT("'" & TEXT(EDATE(J6,-2),"mm-yyyy") & "'!A:A"),0)) -> 615 | D6: 654 | E6: =D6-C6 -> 39 | F6: 1182.6 | G6: =E6*F6 -> 46121.4 | H6: 5000 | I6: =E6*F6+H6 -> 51121.4 | J6: 45908 | K6: SI | L6: PENDIENTE | M6: =IF(L6="Pagado", I6, 0) -> 0 | P6: =IF(L6="NO APLICA",0, (I6-M6)) -> 51121.4
A7: 36 | B7: =Usuarios!B37 & " " & Usuarios!C37 & " " & Usuarios!D37 -> Danilo Soto Soto | C7: =INDEX(INDIRECT("'" & TEXT(EDATE(J7,-2),"mm-yyyy") & "'!D:D"), MATCH(A7,INDIRECT("'" & TEXT(EDATE(J7,-2),"mm-yyyy") & "'!A:A"),0)) -> 0 | D7: 0 | E7: =D7-C7 -> 0 | F7: 1182.6 | G7: =E7*F7 -> 0 | H7: 5000 | I7: =E7*F7+H7 -> 5000 | J7: 45908 | K7: SI | L7: PENDIENTE | M7: =IF(L7="Pagado", I7, 0) -> 0 | P7: =IF(L7="NO APLICA",0, (I7-M7)) -> 5000
A8: 10 | B8: =Usuarios!B11 & " " & Usuarios!C11 & " " & Usuarios!D11 -> David Cartes | C8: =INDEX(INDIRECT("'" & TEXT(EDATE(J8,-2),"mm-yyyy") & "'!D:D"), MATCH(A8,INDIRECT("'" & TEXT(EDATE(J8,-2),"mm-yyyy") & "'!A:A"),0)) -> 150 | D8: 161 | E8: =D8-C8 -> 11 | F8: 1182.6 | G8: =E8*F8 -> 13008.6 | H8: 5000 | I8: =E8*F8+H8 -> 18008.6 | J8: 45908 | K8: SI | L8: PENDIENTE | M8: =IF(L8="Pagado", I8, 0) -> 0 | P8: =IF(L8="NO APLICA",0, (I8-M8)) -> 18008.6
A9: 19 | B9: =Usuarios!B20 & " " & Usuarios!C20 & " " & Usuarios!D20 -> Eduardo Chavez | C9: =INDEX(INDIRECT("'" & TEXT(EDATE(J9,-2),"mm-yyyy") & "'!D:D"), MATCH(A9,INDIRECT("'" & TEXT(EDATE(J9,-2),"mm-yyyy") & "'!A:A"),0)) -> 110 | D9: 117 | E9: =D9-C9 -> 7 | F9: 1182.6 | G9: =E9*F9 -> 8278.2 | H9: 5000 | I9: =E9*F9+H9 -> 13278.2 | J9: 45908 | K9: SI | L9: PAGADO | M9: =IF(L9="Pagado", I9, 0) -> 13278.2 | P9: =IF(L9="NO APLICA",0, (I9-M9)) -> 0
A10: 52 | B10: =Usuarios!B53 & " " & Usuarios!C53 & " " & Usuarios!D53 -> Esteban Oyarzo Levil | C10: =INDEX(INDIRECT("'" & TEXT(EDATE(J10,-2),"mm-yyyy") & "'!D:D"), MATCH(A10,INDIRECT("'" & TEXT(EDATE(J10,-2),"mm-yyyy") & "'!A:A"),0)) -> 0 | D10: 0 | E10: =D10-C10 -> 0 | F10: 1182.6 | G10: =E10*F10 -> 0 | H10: 5000 | I10: =E10*F10+H10 -> 5000 | J10: 45908 | K10: SI | L10: PENDIENTE | M10: =IF(L10="Pagado", I10, 0) -> 0 | P10: =IF(L10="NO APLICA",0, (I10-M10)) -> 5000
A11: 8 | B11: =Usuarios!B9 & " " & Usuarios!C9 & " " & Usuarios!D9 -> Gabriel Farias | C11: =INDEX(INDIRECT("'" & TEXT(EDATE(J11,-2),"mm-yyyy") & "'!D:D"), MATCH(A11,INDIRECT("'" & TEXT(EDATE(J11,-2),"mm-yyyy") & "'!A:A"),0)) -> 531 | D11: 573 | E11: =D11-C11 -> 42 | F11: 1182.6 | G11: =E11*F11 -> 49669.2 | H11: 5000 | I11: =E11*F11+H11 -> 54669.2 | J11: 45908 | K11: SI | L11: PENDIENTE | M11: =IF(L11="Pagado", I11, 0) -> 0 | P11: =IF(L11="NO APLICA",0, (I11-M11)) -> 54669.2
A12: 2 | B12: =Usuarios!B3 & " " & Usuarios!C3 & " " & Usuarios!D3 -> Gabriel Barria Zuñiga | C12: =INDEX(INDIRECT("'" & TEXT(EDATE(J12,-2),"mm-yyyy") & "'!D:D"), MATCH(A12,INDIRECT("'" & TEXT(EDATE(J12,-2),"mm-yyyy") & "'!A:A"),0)) -> 372 | D12: 391 | E12: =D12-C12 -> 19 | F12: 1182.6 | G12: =E12*F12 -> 22469.4 | H12: 5000 | I12: =E12*F12+H12 -> 27469.4 | J12: 45908 | K12: SI | L12: PAGADO | M12: =IF(L12="Pagado", I12, 0) -> 27469.4 | N12: 45932 | O12: EFECTIVO | P12: =IF(L12="NO APLICA",0, (I12-M12)) -> 0
A13: 3 | B13: =Usuarios!B4 & " " & Usuarios!C4 & " " & Usuarios!D4 -> Gino Reyes | C13: =INDEX(INDIRECT("'" & TEXT(EDATE(J13,-2),"mm-yyyy") & "'!D:D"), MATCH(A13,INDIRECT("'" & TEXT(EDATE(J13,-2),"mm-yyyy") & "'!A:A"),0)) -> 3 | D13: 3 | E13: =D13-C13 -> 0 | F13: 1182.6 | G13: =E13*F13 -> 0 | H13: 5000 | I13: =E13*F13+H13 -> 5000 | J13: 45908 | K13: SI | L13: PENDIENTE | M13: =IF(L13="Pagado", I13, 0) -> 0 | P13: =IF(L13="NO APLICA",0, (I13-M13)) -> 5000
A14: 39 | B14: =Usuarios!B40 & " " & Usuarios!C40 & " " & Usuarios!D40 -> Gloria Alvarez | C14: =INDEX(INDIRECT("'" & TEXT(EDATE(J14,-2),"mm-yyyy") & "'!D:D"), MATCH(A14,INDIRECT("'" & TEXT(EDATE(J14,-2),"mm-yyyy") & "'!A:A"),0)) -> 14 | D14: 14 | E14: =D14-C14 -> 0 | F14: 1182.6 | G14: =E14*F14 -> 0 | H14: 5000 | I14: =E14*F14+H14 -> 5000 | J14: 45908 | K14: SI | L14: PENDIENTE | M14: =IF(L14="Pagado", I14, 0) -> 0 | P14: =IF(L14="NO APLICA",0, (I14-M14)) -> 5000
A15: 40 | B15: =Usuarios!B41 & " " & Usuarios!C41 & " " & Usuarios!D41 -> Gloria Levil | C15: =INDEX(INDIRECT("'" & TEXT(EDATE(J15,-2),"mm-yyyy") & "'!D:D"), MATCH(A15,INDIRECT("'" & TEXT(EDATE(J15,-2),"mm-yyyy") & "'!A:A"),0)) -> 99 | D15: 99 | E15: =D15-C15 -> 0 | F15: 1182.6 | G15: =E15*F15 -> 0 | H15: 5000 | I15: =E15*F15+H15 -> 5000 | J15: 45908 | K15: SI | L15: PENDIENTE | M15: =IF(L15="Pagado", I15, 0) -> 0 | P15: =IF(L15="NO APLICA",0, (I15-M15)) -> 5000
A16: 50 | B16: =Usuarios!B51 & " " & Usuarios!C51 & " " & Usuarios!D51 -> Gloria Isamar Velasquez Almonacid | C16: =INDEX(INDIRECT("'" & TEXT(EDATE(J16,-2),"mm-yyyy") & "'!D:D"), MATCH(A16,INDIRECT("'" & TEXT(EDATE(J16,-2),"mm-yyyy") & "'!A:A"),0)) -> 66 | D16: 76 | E16: =D16-C16 -> 10 | F16: 1182.6 | G16: =E16*F16 -> 11826 | H16: 5000 | I16: =E16*F16+H16 -> 16826 | J16: 45908 | K16: SI | L16: PENDIENTE | M16: =IF(L16="Pagado", I16, 0) -> 0 | P16: =IF(L16="NO APLICA",0, (I16-M16)) -> 16826
A17: 26 | B17: =Usuarios!B27 & " " & Usuarios!C27 & " " & Usuarios!D27 -> Guido Quintuy | C17: =INDEX(INDIRECT("'" & TEXT(EDATE(J17,-2),"mm-yyyy") & "'!D:D"), MATCH(A17,INDIRECT("'" & TEXT(EDATE(J17,-2),"mm-yyyy") & "'!A:A"),0)) | J17: 45908 | K17: SI | L17: NO APLICA
A18: 55 | B18: =Usuarios!B56 & " " & Usuarios!C56 & " " & Usuarios!D56 -> Guido Quintuy - Sitio vacío | C18: =INDEX(INDIRECT("'" & TEXT(EDATE(J18,-2),"mm-yyyy") & "'!D:D"), MATCH(A18,INDIRECT("'" & TEXT(EDATE(J18,-2),"mm-yyyy") & "'!A:A"),0)) -> 0 | D18: 0 | E18: =D18-C18 -> 0 | F18: 1182.6 | G18: =E18*F18 -> 0 | H18: 5000 | I18: =E18*F18+H18 -> 5000 | J18: 45908 | K18: SI | L18: PENDIENTE | M18: =IF(L18="Pagado", I18, 0) -> 0 | P18: =IF(L18="NO APLICA",0, (I18-M18)) -> 5000
A19: 25 | B19: =Usuarios!B26 & " " & Usuarios!C26 & " " & Usuarios!D26 -> Inés Velasquez | C19: =INDEX(INDIRECT("'" & TEXT(EDATE(J19,-2),"mm-yyyy") & "'!D:D"), MATCH(A19,INDIRECT("'" & TEXT(EDATE(J19,-2),"mm-yyyy") & "'!A:A"),0)) -> 134 | D19: 139 | E19: =D19-C19 -> 5 | F19: 1182.6 | G19: =E19*F19 -> 5913 | H19: 5000 | I19: =E19*F19+H19 -> 10913 | J19: 45908 | K19: SI | L19: PENDIENTE | M19: =IF(L19="Pagado", I19, 0) -> 0 | P19: =IF(L19="NO APLICA",0, (I19-M19)) -> 10913
A20: 17 | B20: =Usuarios!B18 & " " & Usuarios!C18 & " " & Usuarios!D18 -> Joaquin Claramunt | C20: =INDEX(INDIRECT("'" & TEXT(EDATE(J20,-2),"mm-yyyy") & "'!D:D"), MATCH(A20,INDIRECT("'" & TEXT(EDATE(J20,-2),"mm-yyyy") & "'!A:A"),0)) -> 210 | D20: 222 | E20: =D20-C20 -> 12 | F20: 1182.6 | G20: =E20*F20 -> 14191.2 | H20: 5000 | I20: =E20*F20+H20 -> 19191.2 | J20: 45908 | K20: SI | L20: PENDIENTE | M20: =IF(L20="Pagado", I20, 0) -> 0 | P20: =IF(L20="NO APLICA",0, (I20-M20)) -> 19191.2
A21: 35 | B21: =Usuarios!B36 & " " & Usuarios!C36 & " " & Usuarios!D36 -> José Paredes | C21: =INDEX(INDIRECT("'" & TEXT(EDATE(J21,-2),"mm-yyyy") & "'!D:D"), MATCH(A21,INDIRECT("'" & TEXT(EDATE(J21,-2),"mm-yyyy") & "'!A:A"),0)) -> 0 | D21: 0 | E21: =D21-C21 -> 0 | F21: 1182.6 | G21: =E21*F21 -> 0 | H21: 5000 | I21: =E21*F21+H21 -> 5000 | J21: 45908 | K21: SI | L21: PENDIENTE | M21: =IF(L21="Pagado", I21, 0) -> 0 | P21: =IF(L21="NO APLICA",0, (I21-M21)) -> 5000
A22: 20 | B22: =Usuarios!B21 & " " & Usuarios!C21 & " " & Usuarios!D21 -> Juan Chavez | C22: =INDEX(INDIRECT("'" & TEXT(EDATE(J22,-2),"mm-yyyy") & "'!D:D"), MATCH(A22,INDIRECT("'" & TEXT(EDATE(J22,-2),"mm-yyyy") & "'!A:A"),0)) -> 29 | D22: 29 | E22: =D22-C22 -> 0 | F22: 1182.6 | G22: =E22*F22 -> 0 | H22: 5000 | I22: =E22*F22+H22 -> 5000 | J22: 45908 | K22: SI | L22: PENDIENTE | M22: =IF(L22="Pagado", I22, 0) -> 0 | P22: =IF(L22="NO APLICA",0, (I22-M22)) -> 5000
A23: 42 | B23: =Usuarios!B43 & " " & Usuarios!C43 & " " & Usuarios!D43 -> Leo Soto | C23: =INDEX(INDIRECT("'" & TEXT(EDATE(J23,-2),"mm-yyyy") & "'!D:D"), MATCH(A23,INDIRECT("'" & TEXT(EDATE(J23,-2),"mm-yyyy") & "'!A:A"),0)) -> 0 | D23: 0 | E23: =D23-C23 -> 0 | F23: 1182.6 | G23: =E23*F23 -> 0 | H23: 5000 | I23: =E23*F23+H23 -> 5000 | J23: 45908 | K23: SI | L23: PENDIENTE | M23: =IF(L23="Pagado", I23, 0) -> 0 | P23: =IF(L23="NO APLICA",0, (I23-M23)) -> 5000
A24: 57 | B24: =Usuarios!B58 & " " & Usuarios!C58 & " " & Usuarios!D58 -> Lishby Fuentes Diaz | C24: =INDEX(INDIRECT("'" & TEXT(EDATE(J24,-2),"mm-yyyy") & "'!D:D"), MATCH(A24,INDIRECT("'" & TEXT(EDATE(J24,-2),"mm-yyyy") & "'!A:A"),0)) -> 15 | D24: 34 | E24: =D24-C24 -> 19 | F24: 1182.6 | G24: =E24*F24 -> 22469.4 | H24: 5000 | I24: =E24*F24+H24 -> 27469.4 | J24: 45908 | K24: SI | L24: PENDIENTE | M24: =IF(L24="Pagado", I24, 0) -> 0 | P24: =IF(L24="NO APLICA",0, (I24-M24)) -> 27469.4
A25: 48 | B25: =Usuarios!B49 & " " & Usuarios!C49 & " " & Usuarios!D49 -> Luis Vicente Mondaca Muñoz | C25: =INDEX(INDIRECT("'" & TEXT(EDATE(J25,-2),"mm-yyyy") & "'!D:D"), MATCH(A25,INDIRECT("'" & TEXT(EDATE(J25,-2),"mm-yyyy") & "'!A:A"),0)) -> 359 | D25: 377 | E25: =D25-C25 -> 18 | F25: 1182.6 | G25: =E25*F25 -> 21286.8 | H25: 5000 | I25: =E25*F25+H25 -> 26286.8 | J25: 45908 | K25: SI | L25: PAGADO | M25: =IF(L25="Pagado", I25, 0) -> 26286.8 | N25: 45939 | O25: EFECTIVO | P25: =IF(L25="NO APLICA",0, (I25-M25)) -> 0
A26: 30 | B26: =Usuarios!B31 & " " & Usuarios!C31 & " " & Usuarios!D31 -> Luz Maldonado | C26: =INDEX(INDIRECT("'" & TEXT(EDATE(J26,-2),"mm-yyyy") & "'!D:D"), MATCH(A26,INDIRECT("'" & TEXT(EDATE(J26,-2),"mm-yyyy") & "'!A:A"),0)) -> 5 | D26: 5 | E26: =D26-C26 -> 0 | F26: 1182.6 | G26: =E26*F26 -> 0 | H26: 5000 | I26: =E26*F26+H26 -> 5000 | J26: 45908 | K26: SI | L26: PENDIENTE | M26: =IF(L26="Pagado", I26, 0) -> 0 | P26: =IF(L26="NO APLICA",0, (I26-M26)) -> 5000
A27: 7 | B27: =Usuarios!B8 & " " & Usuarios!C8 & " " & Usuarios!D8 -> Marcelo Millanao | C27: =INDEX(INDIRECT("'" & TEXT(EDATE(J27,-2),"mm-yyyy") & "'!D:D"), MATCH(A27,INDIRECT("'" & TEXT(EDATE(J27,-2),"mm-yyyy") & "'!A:A"),0)) -> 285 | D27: 299 | E27: =D27-C27 -> 14 | F27: 1182.6 | G27: =E27*F27 -> 16556.4 | H27: 5000 | I27: =E27*F27+H27 -> 21556.4 | J27: 45908 | K27: SI | L27: PARCIAL | M27: 15643 | P27: =IF(L27="NO APLICA",0, (I27-M27)) -> 5913.4
A28: 51 | B28: =Usuarios!B52 & " " & Usuarios!C52 & " " & Usuarios!D52 -> Maria Manquian | C28: =INDEX(INDIRECT("'" & TEXT(EDATE(J28,-2),"mm-yyyy") & "'!D:D"), MATCH(A28,INDIRECT("'" & TEXT(EDATE(J28,-2),"mm-yyyy") & "'!A:A"),0)) -> 0 | D28: 0 | E28: =D28-C28 -> 0 | F28: 1182.6 | G28: =E28*F28 -> 0 | H28: 5000 | I28: =E28*F28+H28 -> 5000 | J28: 45908 | K28: SI | L28: PENDIENTE | M28: =IF(L28="Pagado", I28, 0) -> 0 | P28: =IF(L28="NO APLICA",0, (I28-M28)) -> 5000
A29: 9 | B29: =Usuarios!B10 & " " & Usuarios!C10 & " " & Usuarios!D10 -> Maria Marin | C29: =INDEX(INDIRECT("'" & TEXT(EDATE(J29,-2),"mm-yyyy") & "'!D:D"), MATCH(A29,INDIRECT("'" & TEXT(EDATE(J29,-2),"mm-yyyy") & "'!A:A"),0)) -> 212 | D29: 223 | E29: =D29-C29 -> 11 | F29: 1182.6 | G29: =E29*F29 -> 13008.6 | H29: 5000 | I29: =E29*F29+H29 -> 18008.6 | J29: 45908 | K29: SI | L29: PAGADO | M29: =IF(L29="Pagado", I29, 0) -> 18008.6 | P29: =IF(L29="NO APLICA",0, (I29-M29)) -> 0
A30: 33 | B30: =Usuarios!B34 & " " & Usuarios!C34 & " " & Usuarios!D34 -> Maria Oliva Soto Almonacid | C30: =INDEX(INDIRECT("'" & TEXT(EDATE(J30,-2),"mm-yyyy") & "'!D:D"), MATCH(A30,INDIRECT("'" & TEXT(EDATE(J30,-2),"mm-yyyy") & "'!A:A"),0)) -> 55 | D30: 57 | E30: =D30-C30 -> 2 | F30: 1182.6 | G30: =E30*F30 -> 2365.2 | H30: 5000 | I30: =E30*F30+H30 -> 7365.2 | J30: 45908 | K30: SI | L30: PAGADO | M30: =IF(L30="Pagado", I30, 0) -> 7365.2 | P30: =IF(L30="NO APLICA",0, (I30-M30)) -> 0
A31: 44 | B31: =Usuarios!B45 & " " & Usuarios!C45 & " " & Usuarios!D45 -> María Sonia Quintui | C31: =INDEX(INDIRECT("'" & TEXT(EDATE(J31,-2),"mm-yyyy") & "'!D:D"), MATCH(A31,INDIRECT("'" & TEXT(EDATE(J31,-2),"mm-yyyy") & "'!A:A"),0)) -> 18 | D31: 19 | E31: =D31-C31 -> 1 | F31: 1182.6 | G31: =E31*F31 -> 1182.6 | H31: 5000 | I31: =E31*F31+H31 -> 6182.6 | J31: 45908 | K31: SI | L31: PENDIENTE | M31: =IF(L31="Pagado", I31, 0) -> 0 | P31: =IF(L31="NO APLICA",0, (I31-M31)) -> 6182.6
A32: 24 | B32: =Usuarios!B25 & " " & Usuarios!C25 & " " & Usuarios!D25 -> Maria Velasquez Miranda | C32: =INDEX(INDIRECT("'" & TEXT(EDATE(J32,-2),"mm-yyyy") & "'!D:D"), MATCH(A32,INDIRECT("'" & TEXT(EDATE(J32,-2),"mm-yyyy") & "'!A:A"),0)) -> 302 | D32: 311 | E32: =D32-C32 -> 9 | F32: 1182.6 | G32: =E32*F32 -> 10643.4 | H32: 5000 | I32: =E32*F32+H32 -> 15643.4 | J32: 45908 | K32: SI | L32: PENDIENTE | M32: =IF(L32="Pagado", I32, 0) -> 0 | P32: =IF(L32="NO APLICA",0, (I32-M32)) -> 15643.4
A33: 56 | B33: =Usuarios!B57 & " " & Usuarios!C57 & " " & Usuarios!D57 -> Mario Velasquez | C33: =INDEX(INDIRECT("'" & TEXT(EDATE(J33,-2),"mm-yyyy") & "'!D:D"), MATCH(A33,INDIRECT("'" & TEXT(EDATE(J33,-2),"mm-yyyy") & "'!A:A"),0)) -> 56 | D33: 66 | E33: =D33-C33 -> 10 | F33: 1182.6 | G33: =E33*F33 -> 11826 | H33: 5000 | I33: =E33*F33+H33 -> 16826 | J33: 45908 | K33: SI | L33: PENDIENTE | M33: =IF(L33="Pagado", I33, 0) -> 0 | P33: =IF(L33="NO APLICA",0, (I33-M33)) -> 16826
A34: 5 | B34: =Usuarios!B6 & " " & Usuarios!C6 & " " & Usuarios!D6 -> Marisol Castro | C34: =INDEX(INDIRECT("'" & TEXT(EDATE(J34,-2),"mm-yyyy") & "'!D:D"), MATCH(A34,INDIRECT("'" & TEXT(EDATE(J34,-2),"mm-yyyy") & "'!A:A"),0)) -> 130 | D34: 138 | E34: =D34-C34 -> 8 | F34: 1182.6 | G34: =E34*F34 -> 9460.8 | H34: 5000 | I34: =E34*F34+H34 -> 14460.8 | J34: 45908 | K34: SI | L34: PAGADO | M34: =IF(L34="Pagado", I34, 0) -> 14460.8 | P34: =IF(L34="NO APLICA",0, (I34-M34)) -> 0
A35: 6 | B35: =Usuarios!B7 & " " & Usuarios!C7 & " " & Usuarios!D7 -> Mauricio Muñoz | C35: =INDEX(INDIRECT("'" & TEXT(EDATE(J35,-2),"mm-yyyy") & "'!D:D"), MATCH(A35,INDIRECT("'" & TEXT(EDATE(J35,-2),"mm-yyyy") & "'!A:A"),0)) -> 225 | D35: 238 | E35: =D35-C35 -> 13 | F35: 1182.6 | G35: =E35*F35 -> 15373.8 | H35: 5000 | I35: =E35*F35+H35 -> 20373.8 | J35: 45908 | K35: SI | L35: PAGADO | M35: =IF(L35="Pagado", I35, 0) -> 20373.8 | N35: 45932 | O35: TRANSFERENCIA | P35: =IF(L35="NO APLICA",0, (I35-M35)) -> 0
A36: 46 | B36: =Usuarios!B47 & " " & Usuarios!C47 & " " & Usuarios!D47 -> Mauricio Muñoz taller | C36: =INDEX(INDIRECT("'" & TEXT(EDATE(J36,-2),"mm-yyyy") & "'!D:D"), MATCH(A36,INDIRECT("'" & TEXT(EDATE(J36,-2),"mm-yyyy") & "'!A:A"),0)) -> 0 | D36: 0 | E36: =D36-C36 -> 0 | F36: 1182.6 | G36: =E36*F36 -> 0 | H36: 5000 | I36: =E36*F36+H36 -> 5000 | J36: 45908 | K36: SI | L36: PENDIENTE | M36: =IF(L36="Pagado", I36, 0) -> 0 | P36: =IF(L36="NO APLICA",0, (I36-M36)) -> 5000
A37: 11 | B37: =Usuarios!B12 & " " & Usuarios!C12 & " " & Usuarios!D12 -> Miguel Ñanco | C37: =INDEX(INDIRECT("'" & TEXT(EDATE(J37,-2),"mm-yyyy") & "'!D:D"), MATCH(A37,INDIRECT("'" & TEXT(EDATE(J37,-2),"mm-yyyy") & "'!A:A"),0)) -> 1 | D37: 3 | E37: =D37-C37 -> 2 | F37: 1182.6 | G37: =E37*F37 -> 2365.2 | H37: 5000 | I37: =E37*F37+H37 -> 7365.2 | J37: 45908 | K37: SI | L37: PENDIENTE | M37: =IF(L37="Pagado", I37, 0) -> 0 | P37: =IF(L37="NO APLICA",0, (I37-M37)) -> 7365.2
A38: 29 | B38: =Usuarios!B30 & " " & Usuarios!C30 & " " & Usuarios!D30 -> Miriam Alvarado | C38: =INDEX(INDIRECT("'" & TEXT(EDATE(J38,-2),"mm-yyyy") & "'!D:D"), MATCH(A38,INDIRECT("'" & TEXT(EDATE(J38,-2),"mm-yyyy") & "'!A:A"),0)) -> 636 | D38: 659 | E38: =D38-C38 -> 23 | F38: 1182.6 | G38: =E38*F38 -> 27199.8 | H38: 5000 | I38: =E38*F38+H38 -> 32199.8 | J38: 45908 | K38: SI | L38: PENDIENTE | M38: =IF(L38="Pagado", I38, 0) -> 0 | P38: =IF(L38="NO APLICA",0, (I38-M38)) -> 32199.8
A39: 45 | B39: =Usuarios!B46 & " " & Usuarios!C46 & " " & Usuarios!D46 -> Monica Cuello | C39: =INDEX(INDIRECT("'" & TEXT(EDATE(J39,-2),"mm-yyyy") & "'!D:D"), MATCH(A39,INDIRECT("'" & TEXT(EDATE(J39,-2),"mm-yyyy") & "'!A:A"),0)) -> 0 | D39: 0 | E39: =D39-C39 -> 0 | F39: 1182.6 | G39: =E39*F39 -> 0 | H39: 5000 | I39: =E39*F39+H39 -> 5000 | J39: 45908 | K39: SI | L39: PAGADO | M39: =IF(L39="Pagado", I39, 0) -> 5000 | P39: =IF(L39="NO APLICA",0, (I39-M39)) -> 0
A40: 1 | B40: =Usuarios!B2 & " " & Usuarios!C2 & " " & Usuarios!D2 -> Nancy Zuñiga Villarroel | C40: =INDEX(INDIRECT("'" & TEXT(EDATE(J40,-2),"mm-yyyy") & "'!D:D"), MATCH(A40,INDIRECT("'" & TEXT(EDATE(J40,-2),"mm-yyyy") & "'!A:A"),0)) -> 233 | D40: 247 | E40: =D40-C40 -> 14 | F40: 1182.6 | G40: =E40*F40 -> 16556.4 | H40: 5000 | I40: =E40*F40+H40 -> 21556.4 | J40: 45908 | K40: SI | L40: PENDIENTE | M40: =IF(L40="Pagado", I40, 0) -> 0 | P40: =IF(L40="NO APLICA",0, (I40-M40)) -> 21556.4
A41: 32 | B41: =Usuarios!B33 & " " & Usuarios!C33 & " " & Usuarios!D33 -> Natividad Soto | C41: =INDEX(INDIRECT("'" & TEXT(EDATE(J41,-2),"mm-yyyy") & "'!D:D"), MATCH(A41,INDIRECT("'" & TEXT(EDATE(J41,-2),"mm-yyyy") & "'!A:A"),0)) -> 153 | D41: 176 | E41: =D41-C41 -> 23 | F41: 1182.6 | G41: =E41*F41 -> 27199.8 | H41: 5000 | I41: =E41*F41+H41 -> 32199.8 | J41: 45908 | K41: SI | L41: PAGADO | M41: 0 | P41: =IF(L41="NO APLICA",0, (I41-M41)) -> 32199.8
A42: 18 | B42: =Usuarios!B19 & " " & Usuarios!C19 & " " & Usuarios!D19 -> Nelson Mansilla | C42: =INDEX(INDIRECT("'" & TEXT(EDATE(J42,-2),"mm-yyyy") & "'!D:D"), MATCH(A42,INDIRECT("'" & TEXT(EDATE(J42,-2),"mm-yyyy") & "'!A:A"),0)) -> 151 | D42: 161 | E42: =D42-C42 -> 10 | F42: 1182.6 | G42: =E42*F42 -> 11826 | H42: 5000 | I42: =E42*F42+H42 -> 16826 | J42: 45908 | K42: SI | L42: PENDIENTE | M42: =IF(L42="Pagado", I42, 0) -> 0 | P42: =IF(L42="NO APLICA",0, (I42-M42)) -> 16826
A43: 53 | B43: =Usuarios!B54 & " " & Usuarios!C54 & " " & Usuarios!D54 -> Nicolas Andres Cardenas Bustamante | C43: =INDEX(INDIRECT("'" & TEXT(EDATE(J43,-2),"mm-yyyy") & "'!D:D"), MATCH(A43,INDIRECT("'" & TEXT(EDATE(J43,-2),"mm-yyyy") & "'!A:A"),0)) -> 0 | D43: 0 | E43: =D43-C43 -> 0 | F43: 1182.6 | G43: =E43*F43 -> 0 | H43: 5000 | I43: =E43*F43+H43 -> 5000 | J43: 45908 | K43: SI | L43: PENDIENTE | M43: =IF(L43="Pagado", I43, 0) -> 0 | P43: =IF(L43="NO APLICA",0, (I43-M43)) -> 5000
A44: 28 | B44: =Usuarios!B29 & " " & Usuarios!C29 & " " & Usuarios!D29 -> Nora Ñanco | C44: =INDEX(INDIRECT("'" & TEXT(EDATE(J44,-2),"mm-yyyy") & "'!D:D"), MATCH(A44,INDIRECT("'" & TEXT(EDATE(J44,-2),"mm-yyyy") & "'!A:A"),0)) -> 513 | D44: 543 | E44: =D44-C44 -> 30 | F44: 1182.6 | G44: =E44*F44 -> 35478 | H44: 5000 | I44: =E44*F44+H44 -> 40478 | J44: 45908 | K44: SI | L44: PAGADO | M44: =IF(L44="Pagado", I44, 0) -> 40478 | P44: =IF(L44="NO APLICA",0, (I44-M44)) -> 0
A45: 38 | B45: =Usuarios!B39 & " " & Usuarios!C39 & " " & Usuarios!D39 -> Norma Sanchez | C45: =INDEX(INDIRECT("'" & TEXT(EDATE(J45,-2),"mm-yyyy") & "'!D:D"), MATCH(A45,INDIRECT("'" & TEXT(EDATE(J45,-2),"mm-yyyy") & "'!A:A"),0)) -> 9 | D45: 9 | E45: =D45-C45 -> 0 | F45: 1182.6 | G45: =E45*F45 -> 0 | H45: 5000 | I45: =E45*F45+H45 -> 5000 | J45: 45908 | K45: SI | L45: PENDIENTE | M45: =IF(L45="Pagado", I45, 0) -> 0 | P45: =IF(L45="NO APLICA",0, (I45-M45)) -> 5000
A46: 47 | B46: =Usuarios!B48 & " " & Usuarios!C48 & " " & Usuarios!D48 -> Pablo Contreras | C46: =INDEX(INDIRECT("'" & TEXT(EDATE(J46,-2),"mm-yyyy") & "'!D:D"), MATCH(A46,INDIRECT("'" & TEXT(EDATE(J46,-2),"mm-yyyy") & "'!A:A"),0)) | J46: 45908 | K46: SI | L46: PENDIENTE | M46: =IF(L46="Pagado", I46, 0) -> 0 | P46: =IF(L46="NO APLICA",0, (I46-M46)) -> 0
A47: 31 | B47: =Usuarios!B32 & " " & Usuarios!C32 & " " & Usuarios!D32 -> Patricia Carcamo Gonzales | C47: =INDEX(INDIRECT("'" & TEXT(EDATE(J47,-2),"mm-yyyy") & "'!D:D"), MATCH(A47,INDIRECT("'" & TEXT(EDATE(J47,-2),"mm-yyyy") & "'!A:A"),0)) -> 219 | D47: 232 | E47: =D47-C47 -> 13 | F47: 1182.6 | G47: =E47*F47 -> 15373.8 | H47: 5000 | I47: =E47*F47+H47 -> 20373.8 | J47: 45908 | K47: SI | L47: PENDIENTE | M47: =IF(L47="Pagado", I47, 0) -> 0 | P47: =IF(L47="NO APLICA",0, (I47-M47)) -> 20373.8
A48: 37 | B48: =Usuarios!B38 & " " & Usuarios!C38 & " " & Usuarios!D38 -> Patricio Alvarez Mancilla | C48: =INDEX(INDIRECT("'" & TEXT(EDATE(J48,-2),"mm-yyyy") & "'!D:D"), MATCH(A48,INDIRECT("'" & TEXT(EDATE(J48,-2),"mm-yyyy") & "'!A:A"),0)) -> 0 | D48: 10 | E48: =D48-C48 -> 10 | F48: 1182.6 | G48: =E48*F48 -> 11826 | H48: 5000 | I48: =E48*F48+H48 -> 16826 | J48: 45908 | K48: SI | L48: PENDIENTE | M48: =IF(L48="Pagado", I48, 0) -> 0 | P48: =IF(L48="NO APLICA",0, (I48-M48)) -> 16826
A49: 27 | B49: =Usuarios!B28 & " " & Usuarios!C28 & " " & Usuarios!D28 -> Pedro Almonacid | C49: =INDEX(INDIRECT("'" & TEXT(EDATE(J49,-2),"mm-yyyy") & "'!D:D"), MATCH(A49,INDIRECT("'" & TEXT(EDATE(J49,-2),"mm-yyyy") & "'!A:A"),0)) -> 250 | D49: 262 | E49: =D49-C49 -> 12 | F49: 1182.6 | G49: =E49*F49 -> 14191.2 | H49: 5000 | I49: =E49*F49+H49 -> 19191.2 | J49: 45908 | K49: SI | L49: PENDIENTE | M49: =IF(L49="Pagado", I49, 0) -> 0 | P49: =IF(L49="NO APLICA",0, (I49-M49)) -> 19191.2
A50: 12 | B50: =Usuarios!B13 & " " & Usuarios!C13 & " " & Usuarios!D13 -> Pedro Contreras | C50: =INDEX(INDIRECT("'" & TEXT(EDATE(J50,-2),"mm-yyyy") & "'!D:D"), MATCH(A50,INDIRECT("'" & TEXT(EDATE(J50,-2),"mm-yyyy") & "'!A:A"),0)) -> 137 | D50: 146 | E50: =D50-C50 -> 9 | F50: 1182.6 | G50: =E50*F50 -> 10643.4 | H50: 5000 | I50: =E50*F50+H50 -> 15643.4 | J50: 45908 | K50: SI | L50: PENDIENTE | M50: =IF(L50="Pagado", I50, 0) -> 0 | P50: =IF(L50="NO APLICA",0, (I50-M50)) -> 15643.4
A51: 43 | B51: =Usuarios!B44 & " " & Usuarios!C44 & " " & Usuarios!D44 -> Ramon Maldonado | C51: =INDEX(INDIRECT("'" & TEXT(EDATE(J51,-2),"mm-yyyy") & "'!D:D"), MATCH(A51,INDIRECT("'" & TEXT(EDATE(J51,-2),"mm-yyyy") & "'!A:A"),0)) -> 0 | D51: 0 | E51: =D51-C51 -> 0 | F51: 1182.6 | G51: =E51*F51 -> 0 | H51: 5000 | I51: =E51*F51+H51 -> 5000 | J51: 45908 | K51: SI | L51: PENDIENTE | M51: =IF(L51="Pagado", I51, 0) -> 0 | O51: TRANSFERENCIA | P51: =IF(L51="NO APLICA",0, (I51-M51)) -> 5000
A52: 14 | B52: =Usuarios!B15 & " " & Usuarios!C15 & " " & Usuarios!D15 -> Ramona Mansilla | C52: =INDEX(INDIRECT("'" & TEXT(EDATE(J52,-2),"mm-yyyy") & "'!D:D"), MATCH(A52,INDIRECT("'" & TEXT(EDATE(J52,-2),"mm-yyyy") & "'!A:A"),0)) -> 59 | D52: 62 | E52: =D52-C52 -> 3 | F52: 1182.6 | G52: =E52*F52 -> 3547.8 | H52: 5000 | I52: =E52*F52+H52 -> 8547.8 | J52: 45908 | K52: SI | L52: PAGADO | M52: =IF(L52="Pagado", I52, 0) -> 8547.8 | P52: =IF(L52="NO APLICA",0, (I52-M52)) -> 0
A53: 54 | B53: =Usuarios!B55 & " " & Usuarios!C55 & " " & Usuarios!D55 -> Rosa Mancilla | C53: =INDEX(INDIRECT("'" & TEXT(EDATE(J53,-2),"mm-yyyy") & "'!D:D"), MATCH(A53,INDIRECT("'" & TEXT(EDATE(J53,-2),"mm-yyyy") & "'!A:A"),0)) -> 106 | D53: 106 | E53: =D53-C53 -> 0 | F53: 1182.6 | G53: =E53*F53 -> 0 | H53: 5000 | I53: =E53*F53+H53 -> 5000 | J53: 45908 | K53: SI | L53: PAGADO | M53: =IF(L53="Pagado", I53, 0) -> 5000 | P53: =IF(L53="NO APLICA",0, (I53-M53)) -> 0
A54: 49 | B54: =Usuarios!B50 & " " & Usuarios!C50 & " " & Usuarios!D50 -> Rosa Nuñez | C54: =INDEX(INDIRECT("'" & TEXT(EDATE(J54,-2),"mm-yyyy") & "'!D:D"), MATCH(A54,INDIRECT("'" & TEXT(EDATE(J54,-2),"mm-yyyy") & "'!A:A"),0)) -> 95 | D54: 95 | E54: =D54-C54 -> 0 | F54: 1182.6 | G54: =E54*F54 -> 0 | H54: 5000 | I54: =E54*F54+H54 -> 5000 | J54: 45908 | K54: SI | L54: PAGADO | M54: =IF(L54="Pagado", I54, 0) -> 5000 | P54: =IF(L54="NO APLICA",0, (I54-M54)) -> 0
A55: 15 | B55: =Usuarios!B16 & " " & Usuarios!C16 & " " & Usuarios!D16 -> Sandra Mancilla Merino | C55: =INDEX(INDIRECT("'" & TEXT(EDATE(J55,-2),"mm-yyyy") & "'!D:D"), MATCH(A55,INDIRECT("'" & TEXT(EDATE(J55,-2),"mm-yyyy") & "'!A:A"),0)) -> 172 | D55: 183 | E55: =D55-C55 -> 11 | F55: 1182.6 | G55: =E55*F55 -> 13008.6 | H55: 5000 | I55: =E55*F55+H55 -> 18008.6 | J55: 45908 | K55: SI | L55: PENDIENTE | M55: =IF(L55="Pagado", I55, 0) -> 0 | P55: =IF(L55="NO APLICA",0, (I55-M55)) -> 18008.6
A56: 34 | B56: =Usuarios!B35 & " " & Usuarios!C35 & " " & Usuarios!D35 -> Vanesa Aguilar | C56: =INDEX(INDIRECT("'" & TEXT(EDATE(J56,-2),"mm-yyyy") & "'!D:D"), MATCH(A56,INDIRECT("'" & TEXT(EDATE(J56,-2),"mm-yyyy") & "'!A:A"),0)) -> 591 | D56: 611 | E56: =D56-C56 -> 20 | F56: 1182.6 | G56: =E56*F56 -> 23652 | H56: 5000 | I56: =E56*F56+H56 -> 28652 | J56: 45908 | K56: SI | L56: PENDIENTE | M56: =IF(L56="Pagado", I56, 0) -> 0 | P56: =IF(L56="NO APLICA",0, (I56-M56)) -> 28652
A57: 22 | B57: =Usuarios!B23 & " " & Usuarios!C23 & " " & Usuarios!D23 -> Yuri Millaquen | C57: =INDEX(INDIRECT("'" & TEXT(EDATE(J57,-2),"mm-yyyy") & "'!D:D"), MATCH(A57,INDIRECT("'" & TEXT(EDATE(J57,-2),"mm-yyyy") & "'!A:A"),0)) -> 197 | D57: 209 | E57: =D57-C57 -> 12 | F57: 1182.6 | G57: =E57*F57 -> 14191.2 | H57: 5000 | I57: =E57*F57+H57 -> 19191.2 | J57: 45908 | K57: SI | L57: PENDIENTE | M57: =IF(L57="Pagado", I57, 0) -> 0 | P57: =IF(L57="NO APLICA",0, (I57-M57)) -> 19191.2
C58: ='07-2025'!D98

Sheet 09-2025
A1: ID | B1: Nombre | C1: Lectura_Anterior | D1: Lectura_Actual | E1: Consumo_m3 | F1: Tarifa_m3 | G1: Subtotal_Consumo | H1: Cargo_Fijo | I1: Total_Factura | J1: Fecha_Lectura | K1: Lectura Tomada | L1: Estado_Pago | M1: Monto_Pagado | N1: Fecha_Pago | O1: Forma_Pago | P1: Saldo_Pendiente | Q1: comprobante_link
A2: 41 | B2: =Usuarios!B42 & " " & Usuarios!C42 & " " & Usuarios!D42 -> Astrid Gomez | C2: =INDEX(INDIRECT("'" & TEXT(EDATE(J2,-2),"mm-yyyy") & "'!D:D"), MATCH(A2,INDIRECT("'" & TEXT(EDATE(J2,-2),"mm-yyyy") & "'!A:A"),0)) -> 120 | D2: 125 | E2: =D2-C2 -> 5 | F2: 1182.6 | G2: =E2*F2 -> 5913 | H2: 5000 | I2: =E2*F2+H2 -> 10913 | J2: 45935 | K2: SI | L2: PENDIENTE | M2: =IF(L2="Pagado", I2, 0) -> 0 | P2: =IF(L2="NO APLICA",0, (I2-M2)) -> 10913
A3: 16 | B3: =Usuarios!B17 & " " & Usuarios!C17 & " " & Usuarios!D17 -> Carlos Agüero | C3: =INDEX(INDIRECT("'" & TEXT(EDATE(J3,-2),"mm-yyyy") & "'!D:D"), MATCH(A3,INDIRECT("'" & TEXT(EDATE(J3,-2),"mm-yyyy") & "'!A:A"),0)) -> 238 | D3: 249 | E3: =D3-C3 -> 11 | F3: 1182.6 | G3: =E3*F3 -> 13008.6 | H3: 5000 | I3: =E3*F3+H3 -> 18008.6 | J3: 45935 | K3: SI | L3: PENDIENTE | M3: =IF(L3="Pagado", I3, 0) -> 0 | P3: =IF(L3="NO APLICA",0, (I3-M3)) -> 18008.6
A4: 13 | B4: =Usuarios!B14 & " " & Usuarios!C14 & " " & Usuarios!D14 -> Carlos Gamin | C4: =INDEX(INDIRECT("'" & TEXT(EDATE(J4,-2),"mm-yyyy") & "'!D:D"), MATCH(A4,INDIRECT("'" & TEXT(EDATE(J4,-2),"mm-yyyy") & "'!A:A"),0)) -> 232 | D4: 237 | E4: =D4-C4 -> 5 | F4: 1182.6 | G4: =E4*F4 -> 5913 | H4: 5000 | I4: =E4*F4+H4 -> 10913 | J4: 45935 | K4: SI | L4: PENDIENTE | M4: =IF(L4="Pagado", I4, 0) -> 0 | P4: =IF(L4="NO APLICA",0, (I4-M4)) -> 10913
A5: 23 | B5: =Usuarios!B24 & " " & Usuarios!C24 & " " & Usuarios!D24 -> Carlos Nahuelpan | C5: =INDEX(INDIRECT("'" & TEXT(EDATE(J5,-2),"mm-yyyy") & "'!D:D"), MATCH(A5,INDIRECT("'" & TEXT(EDATE(J5,-2),"mm-yyyy") & "'!A:A"),0)) -> 135 | D5: 141 | E5: =D5-C5 -> 6 | F5: 1182.6 | G5: =E5*F5 -> 7095.6 | H5: 5000 | I5: =E5*F5+H5 -> 12095.6 | J5: 45935 | K5: SI | L5: PENDIENTE | M5: =IF(L5="Pagado", I5, 0) -> 0 | P5: =IF(L5="NO APLICA",0, (I5-M5)) -> 12095.6
A6: 4 | B6: =Usuarios!B5 & " " & Usuarios!C5 & " " & Usuarios!D5 -> Cristian Oyarzo | C6: =INDEX(INDIRECT("'" & TEXT(EDATE(J6,-2),"mm-yyyy") & "'!D:D"), MATCH(A6,INDIRECT("'" & TEXT(EDATE(J6,-2),"mm-yyyy") & "'!A:A"),0)) -> 654 | D6: 683 | E6: =D6-C6 -> 29 | F6: 1182.6 | G6: =E6*F6 -> 34295.4 | H6: 5000 | I6: =E6*F6+H6 -> 39295.4 | J6: 45935 | K6: SI | L6: PENDIENTE | M6: =IF(L6="Pagado", I6, 0) -> 0 | P6: =IF(L6="NO APLICA",0, (I6-M6)) -> 39295.4
A7: 36 | B7: =Usuarios!B37 & " " & Usuarios!C37 & " " & Usuarios!D37 -> Danilo Soto Soto | C7: =INDEX(INDIRECT("'" & TEXT(EDATE(J7,-2),"mm-yyyy") & "'!D:D"), MATCH(A7,INDIRECT("'" & TEXT(EDATE(J7,-2),"mm-yyyy") & "'!A:A"),0)) -> 0 | E7: =D7-C7 -> 0 | F7: 1182.6 | G7: =E7*F7 -> 0 | H7: 5000 | I7: =E7*F7+H7 -> 5000 | J7: 45935 | K7: SI | L7: PENDIENTE | M7: =IF(L7="Pagado", I7, 0) -> 0 | P7: =IF(L7="NO APLICA",0, (I7-M7)) -> 5000
A8: 10 | B8: =Usuarios!B11 & " " & Usuarios!C11 & " " & Usuarios!D11 -> David Cartes | C8: =INDEX(INDIRECT("'" & TEXT(EDATE(J8,-2),"mm-yyyy") & "'!D:D"), MATCH(A8,INDIRECT("'" & TEXT(EDATE(J8,-2),"mm-yyyy") & "'!A:A"),0)) -> 161 | D8: 172 | E8: =D8-C8 -> 11 | F8: 1182.6 | G8: =E8*F8 -> 13008.6 | H8: 5000 | I8: =E8*F8+H8 -> 18008.6 | J8: 45936 | K8: SI | L8: PENDIENTE | M8: =IF(L8="Pagado", I8, 0) -> 0 | P8: =IF(L8="NO APLICA",0, (I8-M8)) -> 18008.6
A9: 19 | B9: =Usuarios!B20 & " " & Usuarios!C20 & " " & Usuarios!D20 -> Eduardo Chavez | C9: =INDEX(INDIRECT("'" & TEXT(EDATE(J9,-2),"mm-yyyy") & "'!D:D"), MATCH(A9,INDIRECT("'" & TEXT(EDATE(J9,-2),"mm-yyyy") & "'!A:A"),0)) -> 117 | D9: 123 | E9: =D9-C9 -> 6 | F9: 1182.6 | G9: =E9*F9 -> 7095.6 | H9: 5000 | I9: =E9*F9+H9 -> 12095.6 | J9: 45935 | K9: SI | L9: PAGADO | M9: =IF(L9="Pagado", I9, 0) -> 12095.6 | P9: =IF(L9="NO APLICA",0, (I9-M9)) -> 0
B10: =Usuarios!B21 & " " & Usuarios!C21 & " " & Usuarios!D21 -> Juan Chavez | C10: =INDEX(INDIRECT("'" & TEXT(EDATE(J10,-2),"mm-yyyy") & "'!D:D"), MATCH(A10,INDIRECT("'" & TEXT(EDATE(J10,-2),"mm-yyyy") & "'!A:A"),0)) -> #NUM! | E10: =D10-C10 -> #NUM! | G10: =E10*F10 -> #NUM! | I10: =E10*F10+H10 -> #NUM! | M10: =IF(L10="Pagado", I10, 0) -> 0 | P10: =IF(L10="NO APLICA",0, (I10-M10)) -> #NUM!
A11: 52 | B11: =Usuarios!B53 & " " & Usuarios!C53 & " " & Usuarios!D53 -> Esteban Oyarzo Levil | C11: =INDEX(INDIRECT("'" & TEXT(EDATE(J11,-2),"mm-yyyy") & "'!D:D"), MATCH(A11,INDIRECT("'" & TEXT(EDATE(J11,-2),"mm-yyyy") & "'!A:A"),0)) -> #NUM! | E11: =D11-C11 -> #NUM! | F11: 1182.6 | G11: =E11*F11 -> #NUM! | H11: 5000 | I11: =E11*F11+H11 -> #NUM! | K11: SI | L11: PENDIENTE | M11: =IF(L11="Pagado", I11, 0) -> 0 | P11: =IF(L11="NO APLICA",0, (I11-M11)) -> #NUM!
A12: 8 | B12: =Usuarios!B9 & " " & Usuarios!C9 & " " & Usuarios!D9 -> Gabriel Farias | C12: =INDEX(INDIRECT("'" & TEXT(EDATE(J12,-2),"mm-yyyy") & "'!D:D"), MATCH(A12,INDIRECT("'" & TEXT(EDATE(J12,-2),"mm-yyyy") & "'!A:A"),0)) -> 573 | D12: 601 | E12: =D12-C12 -> 28 | F12: 1182.6 | G12: =E12*F12 -> 33112.8 | H12: 5000 | I12: =E12*F12+H12 -> 38112.8 | J12: 45935 | K12: SI | L12: PENDIENTE | M12: =IF(L12="Pagado", I12, 0) -> 0 | P12: =IF(L12="NO APLICA",0, (I12-M12)) -> 38112.8
A13: 2 | B13: =Usuarios!B3 & " " & Usuarios!C3 & " " & Usuarios!D3 -> Gabriel Barria Zuñiga | C13: =INDEX(INDIRECT("'" & TEXT(EDATE(J13,-2),"mm-yyyy") & "'!D:D"), MATCH(A13,INDIRECT("'" & TEXT(EDATE(J13,-2),"mm-yyyy") & "'!A:A"),0)) -> 391 | D13: 406 | E13: =D13-C13 -> 15 | F13: 1182.6 | G13: =E13*F13 -> 17739 | H13: 5000 | I13: =E13*F13+H13 -> 22739 | J13: 45935 | K13: SI | L13: PENDIENTE | M13: =IF(L13="Pagado", I13, 0) -> 0 | P13: =IF(L13="NO APLICA",0, (I13-M13)) -> 22739
A14: 3 | B14: =Usuarios!B4 & " " & Usuarios!C4 & " " & Usuarios!D4 -> Gino Reyes | C14: =INDEX(INDIRECT("'" & TEXT(EDATE(J14,-2),"mm-yyyy") & "'!D:D"), MATCH(A14,INDIRECT("'" & TEXT(EDATE(J14,-2),"mm-yyyy") & "'!A:A"),0)) -> 3 | D14: 3 | E14: =D14-C14 -> 0 | F14: 1182.6 | G14: =E14*F14 -> 0 | H14: 5000 | I14: =E14*F14+H14 -> 5000 | J14: 45935 | K14: SI | L14: PENDIENTE | M14: =IF(L14="Pagado", I14, 0) -> 0 | P14: =IF(L14="NO APLICA",0, (I14-M14)) -> 5000
A15: 39 | B15: =Usuarios!B40 & " " & Usuarios!C40 & " " & Usuarios!D40 -> Gloria Alvarez | C15: =INDEX(INDIRECT("'" & TEXT(EDATE(J15,-2),"mm-yyyy") & "'!D:D"), MATCH(A15,INDIRECT("'" & TEXT(EDATE(J15,-2),"mm-yyyy") & "'!A:A"),0)) -> 14 | D15: 20 | E15: =D15-C15 -> 6 | F15: 1182.6 | G15: =E15*F15 -> 7095.6 | H15: 5000 | I15: =E15*F15+H15 -> 12095.6 | J15: 45935 | K15: SI | L15: PENDIENTE | M15: =IF(L15="Pagado", I15, 0) -> 0 | P15: =IF(L15="NO APLICA",0, (I15-M15)) -> 12095.6
A16: 40 | B16: =Usuarios!B41 & " " & Usuarios!C41 & " " & Usuarios!D41 -> Gloria Levil | C16: =INDEX(INDIRECT("'" & TEXT(EDATE(J16,-2),"mm-yyyy") & "'!D:D"), MATCH(A16,INDIRECT("'" & TEXT(EDATE(J16,-2),"mm-yyyy") & "'!A:A"),0)) -> 99 | D16: 100 | E16: =D16-C16 -> 1 | F16: 1182.6 | G16: =E16*F16 -> 1182.6 | H16: 5000 | I16: =E16*F16+H16 -> 6182.6 | J16: 45935 | K16: SI | L16: PENDIENTE | M16: =IF(L16="Pagado", I16, 0) -> 0 | P16: =IF(L16="NO APLICA",0, (I16-M16)) -> 6182.6
A17: 50 | B17: =Usuarios!B51 & " " & Usuarios!C51 & " " & Usuarios!D51 -> Gloria Isamar Velasquez Almonacid | C17: =INDEX(INDIRECT("'" & TEXT(EDATE(J17,-2),"mm-yyyy") & "'!D:D"), MATCH(A17,INDIRECT("'" & TEXT(EDATE(J17,-2),"mm-yyyy") & "'!A:A"),0)) -> 76 | D17: 83 | E17: =D17-C17 -> 7 | F17: 1182.6 | G17: =E17*F17 -> 8278.2 | H17: 5000 | I17: =E17*F17+H17 -> 13278.2 | J17: 45935 | K17: SI | L17: PENDIENTE | M17: =IF(L17="Pagado", I17, 0) -> 0 | P17: =IF(L17="NO APLICA",0, (I17-M17)) -> 13278.2
A18: 26 | B18: =Usuarios!B27 & " " & Usuarios!C27 & " " & Usuarios!D27 -> Guido Quintuy | C18: =INDEX(INDIRECT("'" & TEXT(EDATE(J18,-2),"mm-yyyy") & "'!D:D"), MATCH(A18,INDIRECT("'" & TEXT(EDATE(J18,-2),"mm-yyyy") & "'!A:A"),0)) -> #NUM! | K18: SI | L18: NO APLICA
A19: 55 | B19: =Usuarios!B56 & " " & Usuarios!C56 & " " & Usuarios!D56 -> Guido Quintuy - Sitio vacío | C19: =INDEX(INDIRECT("'" & TEXT(EDATE(J19,-2),"mm-yyyy") & "'!D:D"), MATCH(A19,INDIRECT("'" & TEXT(EDATE(J19,-2),"mm-yyyy") & "'!A:A"),0)) -> 0 | D19: 0 | E19: =D19-C19 -> 0 | F19: 1182.6 | G19: =E19*F19 -> 0 | H19: 5000 | I19: =E19*F19+H19 -> 5000 | J19: 45935 | K19: SI | L19: PENDIENTE | M19: =IF(L19="Pagado", I19, 0) -> 0 | P19: =IF(L19="NO APLICA",0, (I19-M19)) -> 5000
A20: 25 | B20: =Usuarios!B26 & " " & Usuarios!C26 & " " & Usuarios!D26 -> Inés Velasquez | C20: =INDEX(INDIRECT("'" & TEXT(EDATE(J20,-2),"mm-yyyy") & "'!D:D"), MATCH(A20,INDIRECT("'" & TEXT(EDATE(J20,-2),"mm-yyyy") & "'!A:A"),0)) -> 139 | D20: 147 | E20: =D20-C20 -> 8 | F20: 1182.6 | G20: =E20*F20 -> 9460.8 | H20: 5000 | I20: =E20*F20+H20 -> 14460.8 | J20: 45935 | K20: SI | L20: PENDIENTE | M20: =IF(L20="Pagado", I20, 0) -> 0 | P20: =IF(L20="NO APLICA",0, (I20-M20)) -> 14460.8
A21: 17 | B21: =Usuarios!B18 & " " & Usuarios!C18 & " " & Usuarios!D18 -> Joaquin Claramunt | C21: =INDEX(INDIRECT("'" & TEXT(EDATE(J21,-2),"mm-yyyy") & "'!D:D"), MATCH(A21,INDIRECT("'" & TEXT(EDATE(J21,-2),"mm-yyyy") & "'!A:A"),0)) -> 222 | D21: 233 | E21: =D21-C21 -> 11 | F21: 1182.6 | G21: =E21*F21 -> 13008.6 | H21: 5000 | I21: =E21*F21+H21 -> 18008.6 | J21: 45935 | K21: SI | L21: PENDIENTE | M21: =IF(L21="Pagado", I21, 0) -> 0 | P21: =IF(L21="NO APLICA",0, (I21-M21)) -> 18008.6
A22: 35 | B22: =Usuarios!B36 & " " & Usuarios!C36 & " " & Usuarios!D36 -> José Paredes | C22: =INDEX(INDIRECT("'" & TEXT(EDATE(J22,-2),"mm-yyyy") & "'!D:D"), MATCH(A22,INDIRECT("'" & TEXT(EDATE(J22,-2),"mm-yyyy") & "'!A:A"),0)) -> #NUM! | D22: 0 | E22: =D22-C22 -> #NUM! | F22: 1182.6 | G22: =E22*F22 -> #NUM! | H22: 5000 | I22: =E22*F22+H22 -> #NUM! | K22: SI | L22: PENDIENTE | M22: =IF(L22="Pagado", I22, 0) -> 0 | P22: =IF(L22="NO APLICA",0, (I22-M22)) -> #NUM!
A23: 20 | B23: =Usuarios!B21 & " " & Usuarios!C21 & " " & Usuarios!D21 -> Juan Chavez | C23: =INDEX(INDIRECT("'" & TEXT(EDATE(J23,-2),"mm-yyyy") & "'!D:D"), MATCH(A23,INDIRECT("'" & TEXT(EDATE(J23,-2),"mm-yyyy") & "'!A:A"),0)) -> 29 | D23: 30 | E23: =D23-C23 -> 1 | F23: 1182.6 | G23: =E23*F23 -> 1182.6 | H23: 5000 | I23: =E23*F23+H23 -> 6182.6 | J23: 45935 | K23: SI | L23: PENDIENTE | M23: =IF(L23="Pagado", I23, 0) -> 0 | P23: =IF(L23="NO APLICA",0, (I23-M23)) -> 6182.6
A24: 42 | B24: =Usuarios!B43 & " " & Usuarios!C43 & " " & Usuarios!D43 -> Leo Soto | C24: =INDEX(INDIRECT("'" & TEXT(EDATE(J24,-2),"mm-yyyy") & "'!D:D"), MATCH(A24,INDIRECT("'" & TEXT(EDATE(J24,-2),"mm-yyyy") & "'!A:A"),0)) -> 0 | D24: 0 | E24: =D24-C24 -> 0 | F24: 1182.6 | G24: =E24*F24 -> 0 | H24: 5000 | I24: =E24*F24+H24 -> 5000 | J24: 45935 | K24: SI | L24: PENDIENTE | M24: =IF(L24="Pagado", I24, 0) -> 0 | P24: =IF(L24="NO APLICA",0, (I24-M24)) -> 5000
A25: 57 | B25: =Usuarios!B58 & " " & Usuarios!C58 & " " & Usuarios!D58 -> Lishby Fuentes Diaz | C25: =INDEX(INDIRECT("'" & TEXT(EDATE(J25,-2),"mm-yyyy") & "'!D:D"), MATCH(A25,INDIRECT("'" & TEXT(EDATE(J25,-2),"mm-yyyy") & "'!A:A"),0)) -> 34 | D25: 46 | E25: =D25-C25 -> 12 | F25: 1182.6 | G25: =E25*F25 -> 14191.2 | H25: 5000 | I25: =E25*F25+H25 -> 19191.2 | J25: 45935 | K25: SI | L25: PENDIENTE | M25: =IF(L25="Pagado", I25, 0) -> 0 | P25: =IF(L25="NO APLICA",0, (I25-M25)) -> 19191.2
A26: 48 | B26: =Usuarios!B49 & " " & Usuarios!C49 & " " & Usuarios!D49 -> Luis Vicente Mondaca Muñoz | C26: =INDEX(INDIRECT("'" & TEXT(EDATE(J26,-2),"mm-yyyy") & "'!D:D"), MATCH(A26,INDIRECT("'" & TEXT(EDATE(J26,-2),"mm-yyyy") & "'!A:A"),0)) -> 377 | D26: 389 | E26: =D26-C26 -> 12 | F26: 1182.6 | G26: =E26*F26 -> 14191.2 | H26: 5000 | I26: =E26*F26+H26 -> 19191.2 | J26: 45935 | K26: SI | L26: PENDIENTE | M26: =IF(L26="Pagado", I26, 0) -> 0 | P26: =IF(L26="NO APLICA",0, (I26-M26)) -> 19191.2
A27: 30 | B27: =Usuarios!B31 & " " & Usuarios!C31 & " " & Usuarios!D31 -> Luz Maldonado | C27: =INDEX(INDIRECT("'" & TEXT(EDATE(J27,-2),"mm-yyyy") & "'!D:D"), MATCH(A27,INDIRECT("'" & TEXT(EDATE(J27,-2),"mm-yyyy") & "'!A:A"),0)) -> #NUM! | E27: =D27-C27 -> #NUM! | F27: 1182.6 | G27: =E27*F27 -> #NUM! | H27: 5000 | I27: =E27*F27+H27 -> #NUM! | K27: SI | L27: PENDIENTE | M27: =IF(L27="Pagado", I27, 0) -> 0 | P27: =IF(L27="NO APLICA",0, (I27-M27)) -> #NUM!
A28: 7 | B28: =Usuarios!B8 & " " & Usuarios!C8 & " " & Usuarios!D8 -> Marcelo Millanao | C28: =INDEX(INDIRECT("'" & TEXT(EDATE(J28,-2),"mm-yyyy") & "'!D:D"), MATCH(A28,INDIRECT("'" & TEXT(EDATE(J28,-2),"mm-yyyy") & "'!A:A"),0)) -> 299 | D28: 309 | E28: =D28-C28 -> 10 | F28: 1182.6 | G28: =E28*F28 -> 11826 | H28: 5000 | I28: =E28*F28+H28 -> 16826 | J28: 45935 | K28: SI | L28: PENDIENTE | M28: =IF(L28="Pagado", I28, 0) -> 0 | P28: =IF(L28="NO APLICA",0, (I28-M28)) -> 16826
A29: 51 | B29: =Usuarios!B52 & " " & Usuarios!C52 & " " & Usuarios!D52 -> Maria Manquian | C29: =INDEX(INDIRECT("'" & TEXT(EDATE(J29,-2),"mm-yyyy") & "'!D:D"), MATCH(A29,INDIRECT("'" & TEXT(EDATE(J29,-2),"mm-yyyy") & "'!A:A"),0)) -> #NUM! | E29: =D29-C29 -> #NUM! | F29: 1182.6 | G29: =E29*F29 -> #NUM! | H29: 5000 | I29: =E29*F29+H29 -> #NUM! | K29: SI | L29: PENDIENTE | M29: =IF(L29="Pagado", I29, 0) -> 0 | P29: =IF(L29="NO APLICA",0, (I29-M29)) -> #NUM!
A30: 9 | B30: =Usuarios!B10 & " " & Usuarios!C10 & " " & Usuarios!D10 -> Maria Marin | C30: =INDEX(INDIRECT("'" & TEXT(EDATE(J30,-2),"mm-yyyy") & "'!D:D"), MATCH(A30,INDIRECT("'" & TEXT(EDATE(J30,-2),"mm-yyyy") & "'!A:A"),0)) -> 223 | D30: 232 | E30: =D30-C30 -> 9 | F30: 1182.6 | G30: =E30*F30 -> 10643.4 | H30: 5000 | I30: =E30*F30+H30 -> 15643.4 | J30: 45935 | K30: SI | L30: PENDIENTE | M30: =IF(L30="Pagado", I30, 0) -> 0 | P30: =IF(L30="NO APLICA",0, (I30-M30)) -> 15643.4
A31: 33 | B31: =Usuarios!B34 & " " & Usuarios!C34 & " " & Usuarios!D34 -> Maria Oliva Soto Almonacid | C31: =INDEX(INDIRECT("'" & TEXT(EDATE(J31,-2),"mm-yyyy") & "'!D:D"), MATCH(A31,INDIRECT("'" & TEXT(EDATE(J31,-2),"mm-yyyy") & "'!A:A"),0)) -> 57 | D31: 59 | E31: =D31-C31 -> 2 | F31: 1182.6 | G31: =E31*F31 -> 2365.2 | H31: 5000 | I31: =E31*F31+H31 -> 7365.2 | J31: 45935 | K31: SI | L31: PAGADO | M31: =IF(L31="Pagado", I31, 0) -> 7365.2 | P31: =IF(L31="NO APLICA",0, (I31-M31)) -> 0
A32: 44 | B32: =Usuarios!B45 & " " & Usuarios!C45 & " " & Usuarios!D45 -> María Sonia Quintui | C32: =INDEX(INDIRECT("'" & TEXT(EDATE(J32,-2),"mm-yyyy") & "'!D:D"), MATCH(A32,INDIRECT("'" & TEXT(EDATE(J32,-2),"mm-yyyy") & "'!A:A"),0)) -> 19 | D32: 19 | E32: =D32-C32 -> 0 | F32: 1182.6 | G32: =E32*F32 -> 0 | H32: 5000 | I32: =E32*F32+H32 -> 5000 | J32: 45935 | K32: SI | L32: PENDIENTE | M32: =IF(L32="Pagado", I32, 0) -> 0 | P32: =IF(L32="NO APLICA",0, (I32-M32)) -> 5000
A33: 24 | B33: =Usuarios!B25 & " " & Usuarios!C25 & " " & Usuarios!D25 -> Maria Velasquez Miranda | C33: =INDEX(INDIRECT("'" & TEXT(EDATE(J33,-2),"mm-yyyy") & "'!D:D"), MATCH(A33,INDIRECT("'" & TEXT(EDATE(J33,-2),"mm-yyyy") & "'!A:A"),0)) -> 311 | D33: 314 | E33: =D33-C33 -> 3 | F33: 1182.6 | G33: =E33*F33 -> 3547.8 | H33: 5000 | I33: =E33*F33+H33 -> 8547.8 | J33: 45935 | K33: SI | L33: PENDIENTE | M33: =IF(L33="Pagado", I33, 0) -> 0 | P33: =IF(L33="NO APLICA",0, (I33-M33)) -> 8547.8
A34: 56 | B34: =Usuarios!B57 & " " & Usuarios!C57 & " " & Usuarios!D57 -> Mario Velasquez | C34: =INDEX(INDIRECT("'" & TEXT(EDATE(J34,-2),"mm-yyyy") & "'!D:D"), MATCH(A34,INDIRECT("'" & TEXT(EDATE(J34,-2),"mm-yyyy") & "'!A:A"),0)) -> 66 | D34: 77 | E34: =D34-C34 -> 11 | F34: 1182.6 | G34: =E34*F34 -> 13008.6 | H34: 5000 | I34: =E34*F34+H34 -> 18008.6 | J34: 45935 | K34: SI | L34: PENDIENTE | M34: =IF(L34="Pagado", I34, 0) -> 0 | P34: =IF(L34="NO APLICA",0, (I34-M34)) -> 18008.6
A35: 5 | B35: =Usuarios!B6 & " " & Usuarios!C6 & " " & Usuarios!D6 -> Marisol Castro | C35: =INDEX(INDIRECT("'" & TEXT(EDATE(J35,-2),"mm-yyyy") & "'!D:D"), MATCH(A35,INDIRECT("'" & TEXT(EDATE(J35,-2),"mm-yyyy") & "'!A:A"),0)) -> 138 | D35: 145 | E35: =D35-C35 -> 7 | F35: 1182.6 | G35: =E35*F35 -> 8278.2 | H35: 5000 | I35: =E35*F35+H35 -> 13278.2 | J35: 45935 | K35: SI | L35: PAGADO | M35: =IF(L35="Pagado", I35, 0) -> 13278.2 | P35: =IF(L35="NO APLICA",0, (I35-M35)) -> 0
A36: 6 | B36: =Usuarios!B7 & " " & Usuarios!C7 & " " & Usuarios!D7 -> Mauricio Muñoz | C36: =INDEX(INDIRECT("'" & TEXT(EDATE(J36,-2),"mm-yyyy") & "'!D:D"), MATCH(A36,INDIRECT("'" & TEXT(EDATE(J36,-2),"mm-yyyy") & "'!A:A"),0)) -> 238 | D36: 245 | E36: =D36-C36 -> 7 | F36: 1182.6 | G36: =E36*F36 -> 8278.2 | H36: 5000 | I36: =E36*F36+H36 -> 13278.2 | J36: 45935 | K36: SI | L36: PENDIENTE | M36: =IF(L36="Pagado", I36, 0) -> 0 | P36: =IF(L36="NO APLICA",0, (I36-M36)) -> 13278.2
A37: 46 | B37: =Usuarios!B47 & " " & Usuarios!C47 & " " & Usuarios!D47 -> Mauricio Muñoz taller | C37: =INDEX(INDIRECT("'" & TEXT(EDATE(J37,-2),"mm-yyyy") & "'!D:D"), MATCH(A37,INDIRECT("'" & TEXT(EDATE(J37,-2),"mm-yyyy") & "'!A:A"),0)) -> 0 | D37: 0 | E37: =D37-C37 -> 0 | F37: 1182.6 | G37: =E37*F37 -> 0 | H37: 5000 | I37: =E37*F37+H37 -> 5000 | J37: 45935 | K37: SI | L37: PENDIENTE | M37: =IF(L37="Pagado", I37, 0) -> 0 | P37: =IF(L37="NO APLICA",0, (I37-M37)) -> 5000
A38: 11 | B38: =Usuarios!B12 & " " & Usuarios!C12 & " " & Usuarios!D12 -> Miguel Ñanco | C38: =INDEX(INDIRECT("'" & TEXT(EDATE(J38,-2),"mm-yyyy") & "'!D:D"), MATCH(A38,INDIRECT("'" & TEXT(EDATE(J38,-2),"mm-yyyy") & "'!A:A"),0)) -> 3 | D38: 5 | E38: =D38-C38 -> 2 | F38: 1182.6 | G38: =E38*F38 -> 2365.2 | H38: 5000 | I38: =E38*F38+H38 -> 7365.2 | J38: 45935 | K38: SI | L38: PENDIENTE | M38: =IF(L38="Pagado", I38, 0) -> 0 | P38: =IF(L38="NO APLICA",0, (I38-M38)) -> 7365.2
A39: 29 | B39: =Usuarios!B30 & " " & Usuarios!C30 & " " & Usuarios!D30 -> Miriam Alvarado | C39: =INDEX(INDIRECT("'" & TEXT(EDATE(J39,-2),"mm-yyyy") & "'!D:D"), MATCH(A39,INDIRECT("'" & TEXT(EDATE(J39,-2),"mm-yyyy") & "'!A:A"),0)) -> 659 | D39: 677 | E39: =D39-C39 -> 18 | F39: 1182.6 | G39: =E39*F39 -> 21286.8 | H39: 5000 | I39: =E39*F39+H39 -> 26286.8 | J39: 45935 | K39: SI | L39: PENDIENTE | M39: =IF(L39="Pagado", I39, 0) -> 0 | P39: =IF(L39="NO APLICA",0, (I39-M39)) -> 26286.8
A40: 45 | B40: =Usuarios!B46 & " " & Usuarios!C46 & " " & Usuarios!D46 -> Monica Cuello | C40: =INDEX(INDIRECT("'" & TEXT(EDATE(J40,-2),"mm-yyyy") & "'!D:D"), MATCH(A40,INDIRECT("'" & TEXT(EDATE(J40,-2),"mm-yyyy") & "'!A:A"),0)) -> 0 | D40: 0 | E40: =D40-C40 -> 0 | F40: 1182.6 | G40: =E40*F40 -> 0 | H40: 5000 | I40: =E40*F40+H40 -> 5000 | J40: 45935 | K40: SI | L40: PENDIENTE | M40: =IF(L40="Pagado", I40, 0) -> 0 | P40: =IF(L40="NO APLICA",0, (I40-M40)) -> 5000
A41: 1 | B41: =Usuarios!B2 & " " & Usuarios!C2 & " " & Usuarios!D2 -> Nancy Zuñiga Villarroel | C41: =INDEX(INDIRECT("'" & TEXT(EDATE(J41,-2),"mm-yyyy") & "'!D:D"), MATCH(A41,INDIRECT("'" & TEXT(EDATE(J41,-2),"mm-yyyy") & "'!A:A"),0)) -> 247 | D41: 255 | E41: =D41-C41 -> 8 | F41: 1182.6 | G41: =E41*F41 -> 9460.8 | H41: 5000 | I41: =E41*F41+H41 -> 14460.8 | J41: 45935 | K41: SI | L41: PENDIENTE | M41: =IF(L41="Pagado", I41, 0) -> 0 | P41: =IF(L41="NO APLICA",0, (I41-M41)) -> 14460.8
A42: 32 | B42: =Usuarios!B33 & " " & Usuarios!C33 & " " & Usuarios!D33 -> Natividad Soto | C42: =INDEX(INDIRECT("'" & TEXT(EDATE(J42,-2),"mm-yyyy") & "'!D:D"), MATCH(A42,INDIRECT("'" & TEXT(EDATE(J42,-2),"mm-yyyy") & "'!A:A"),0)) -> 176 | D42: 177 | E42: =D42-C42 -> 1 | F42: 1182.6 | G42: =E42*F42 -> 1182.6 | H42: 5000 | I42: =E42*F42+H42 -> 6182.6 | J42: 45935 | K42: SI | L42: PENDIENTE | M42: 0 | P42: =IF(L42="NO APLICA",0, (I42-M42)) -> 6182.6
A43: 18 | B43: =Usuarios!B19 & " " & Usuarios!C19 & " " & Usuarios!D19 -> Nelson Mansilla | C43: =INDEX(INDIRECT("'" & TEXT(EDATE(J43,-2),"mm-yyyy") & "'!D:D"), MATCH(A43,INDIRECT("'" & TEXT(EDATE(J43,-2),"mm-yyyy") & "'!A:A"),0)) -> 161 | D43: 167 | E43: =D43-C43 -> 6 | F43: 1182.6 | G43: =E43*F43 -> 7095.6 | H43: 5000 | I43: =E43*F43+H43 -> 12095.6 | J43: 45935 | K43: SI | L43: PENDIENTE | M43: =IF(L43="Pagado", I43, 0) -> 0 | P43: =IF(L43="NO APLICA",0, (I43-M43)) -> 12095.6
A44: 53 | B44: =Usuarios!B54 & " " & Usuarios!C54 & " " & Usuarios!D54 -> Nicolas Andres Cardenas Bustamante | C44: =INDEX(INDIRECT("'" & TEXT(EDATE(J44,-2),"mm-yyyy") & "'!D:D"), MATCH(A44,INDIRECT("'" & TEXT(EDATE(J44,-2),"mm-yyyy") & "'!A:A"),0)) -> 0 | E44: =D44-C44 -> 0 | F44: 1182.6 | G44: =E44*F44 -> 0 | H44: 5000 | I44: =E44*F44+H44 -> 5000 | J44: 45935 | K44: SI | L44: PENDIENTE | M44: =IF(L44="Pagado", I44, 0) -> 0 | P44: =IF(L44="NO APLICA",0, (I44-M44)) -> 5000
A45: 28 | B45: =Usuarios!B29 & " " & Usuarios!C29 & " " & Usuarios!D29 -> Nora Ñanco | C45: =INDEX(INDIRECT("'" & TEXT(EDATE(J45,-2),"mm-yyyy") & "'!D:D"), MATCH(A45,INDIRECT("'" & TEXT(EDATE(J45,-2),"mm-yyyy") & "'!A:A"),0)) -> 543 | D45: 562 | E45: =D45-C45 -> 19 | F45: 1182.6 | G45: =E45*F45 -> 22469.4 | H45: 5000 | I45: =E45*F45+H45 -> 27469.4 | J45: 45935 | K45: SI | L45: PENDIENTE | M45: =IF(L45="Pagado", I45, 0) -> 0 | P45: =IF(L45="NO APLICA",0, (I45-M45)) -> 27469.4
A46: 38 | B46: =Usuarios!B39 & " " & Usuarios!C39 & " " & Usuarios!D39 -> Norma Sanchez | C46: =INDEX(INDIRECT("'" & TEXT(EDATE(J46,-2),"mm-yyyy") & "'!D:D"), MATCH(A46,INDIRECT("'" & TEXT(EDATE(J46,-2),"mm-yyyy") & "'!A:A"),0)) -> #NUM! | E46: =D46-C46 -> #NUM! | F46: 1182.6 | G46: =E46*F46 -> #NUM! | H46: 5000 | I46: =E46*F46+H46 -> #NUM! | K46: SI | L46: PENDIENTE | M46: =IF(L46="Pagado", I46, 0) -> 0 | P46: =IF(L46="NO APLICA",0, (I46-M46)) -> #NUM!
A47: 47 | B47: =Usuarios!B48 & " " & Usuarios!C48 & " " & Usuarios!D48 -> Pablo Contreras | C47: =INDEX(INDIRECT("'" & TEXT(EDATE(J47,-2),"mm-yyyy") & "'!D:D"), MATCH(A47,INDIRECT("'" & TEXT(EDATE(J47,-2),"mm-yyyy") & "'!A:A"),0)) -> #NUM! | K47: SI | L47: NO APLICA | M47: =IF(L47="Pagado", I47, 0) -> 0 | P47: =IF(L47="NO APLICA",0, (I47-M47)) -> 0
A48: 31 | B48: =Usuarios!B32 & " " & Usuarios!C32 & " " & Usuarios!D32 -> Patricia Carcamo Gonzales | C48: =INDEX(INDIRECT("'" & TEXT(EDATE(J48,-2),"mm-yyyy") & "'!D:D"), MATCH(A48,INDIRECT("'" & TEXT(EDATE(J48,-2),"mm-yyyy") & "'!A:A"),0)) -> 232 | D48: 244 | E48: =D48-C48 -> 12 | F48: 1182.6 | G48: =E48*F48 -> 14191.2 | H48: 5000 | I48: =E48*F48+H48 -> 19191.2 | J48: 45935 | K48: SI | L48: PENDIENTE | M48: =IF(L48="Pagado", I48, 0) -> 0 | P48: =IF(L48="NO APLICA",0, (I48-M48)) -> 19191.2
A49: 37 | B49: =Usuarios!B38 & " " & Usuarios!C38 & " " & Usuarios!D38 -> Patricio Alvarez Mancilla | C49: =INDEX(INDIRECT("'" & TEXT(EDATE(J49,-2),"mm-yyyy") & "'!D:D"), MATCH(A49,INDIRECT("'" & TEXT(EDATE(J49,-2),"mm-yyyy") & "'!A:A"),0)) -> 10 | D49: 11 | E49: =D49-C49 -> 1 | F49: 1182.6 | G49: =E49*F49 -> 1182.6 | H49: 5000 | I49: =E49*F49+H49 -> 6182.6 | J49: 45935 | K49: SI | L49: PENDIENTE | M49: =IF(L49="Pagado", I49, 0) -> 0 | P49: =IF(L49="NO APLICA",0, (I49-M49)) -> 6182.6
A50: 27 | B50: =Usuarios!B28 & " " & Usuarios!C28 & " " & Usuarios!D28 -> Pedro Almonacid | C50: =INDEX(INDIRECT("'" & TEXT(EDATE(J50,-2),"mm-yyyy") & "'!D:D"), MATCH(A50,INDIRECT("'" & TEXT(EDATE(J50,-2),"mm-yyyy") & "'!A:A"),0)) -> 262 | D50: 273 | E50: =D50-C50 -> 11 | F50: 1182.6 | G50: =E50*F50 -> 13008.6 | H50: 5000 | I50: =E50*F50+H50 -> 18008.6 | J50: 45935 | K50: SI | L50: PENDIENTE | M50: =IF(L50="Pagado", I50, 0) -> 0 | P50: =IF(L50="NO APLICA",0, (I50-M50)) -> 18008.6
A51: 12 | B51: =Usuarios!B13 & " " & Usuarios!C13 & " " & Usuarios!D13 -> Pedro Contreras | C51: =INDEX(INDIRECT("'" & TEXT(EDATE(J51,-2),"mm-yyyy") & "'!D:D"), MATCH(A51,INDIRECT("'" & TEXT(EDATE(J51,-2),"mm-yyyy") & "'!A:A"),0)) -> 146 | D51: 154 | E51: =D51-C51 -> 8 | F51: 1182.6 | G51: =E51*F51 -> 9460.8 | H51: 5000 | I51: =E51*F51+H51 -> 14460.8 | J51: 45935 | K51: SI | L51: PENDIENTE | M51: =IF(L51="Pagado", I51, 0) -> 0 | P51: =IF(L51="NO APLICA",0, (I51-M51)) -> 14460.8
A52: 43 | B52: =Usuarios!B44 & " " & Usuarios!C44 & " " & Usuarios!D44 -> Ramon Maldonado | C52: =INDEX(INDIRECT("'" & TEXT(EDATE(J52,-2),"mm-yyyy") & "'!D:D"), MATCH(A52,INDIRECT("'" & TEXT(EDATE(J52,-2),"mm-yyyy") & "'!A:A"),0)) -> 0 | D52: 0 | E52: =D52-C52 -> 0 | F52: 1182.6 | G52: =E52*F52 -> 0 | H52: 5000 | I52: =E52*F52+H52 -> 5000 | J52: 45935 | K52: SI | L52: PENDIENTE | M52: =IF(L52="Pagado", I52, 0) -> 0 | P52: =IF(L52="NO APLICA",0, (I52-M52)) -> 5000
A53: 14 | B53: =Usuarios!B15 & " " & Usuarios!C15 & " " & Usuarios!D15 -> Ramona Mansilla | C53: =INDEX(INDIRECT("'" & TEXT(EDATE(J53,-2),"mm-yyyy") & "'!D:D"), MATCH(A53,INDIRECT("'" & TEXT(EDATE(J53,-2),"mm-yyyy") & "'!A:A"),0)) -> 62 | D53: 66 | E53: =D53-C53 -> 4 | F53: 1182.6 | G53: =E53*F53 -> 4730.4 | H53: 5000 | I53: =E53*F53+H53 -> 9730.4 | J53: 45935 | K53: SI | L53: PENDIENTE | M53: =IF(L53="Pagado", I53, 0) -> 0 | P53: =IF(L53="NO APLICA",0, (I53-M53)) -> 9730.4
A54: 54 | B54: =Usuarios!B55 & " " & Usuarios!C55 & " " & Usuarios!D55 -> Rosa Mancilla | C54: =INDEX(INDIRECT("'" & TEXT(EDATE(J54,-2),"mm-yyyy") & "'!D:D"), MATCH(A54,INDIRECT("'" & TEXT(EDATE(J54,-2),"mm-yyyy") & "'!A:A"),0)) -> 106 | D54: 106 | E54: =D54-C54 -> 0 | F54: 1182.6 | G54: =E54*F54 -> 0 | H54: 5000 | I54: =E54*F54+H54 -> 5000 | J54: 45935 | K54: SI | L54: PENDIENTE | M54: =IF(L54="Pagado", I54, 0) -> 0 | P54: =IF(L54="NO APLICA",0, (I54-M54)) -> 5000
A55: 49 | B55: =Usuarios!B50 & " " & Usuarios!C50 & " " & Usuarios!D50 -> Rosa Nuñez | C55: =INDEX(INDIRECT("'" & TEXT(EDATE(J55,-2),"mm-yyyy") & "'!D:D"), MATCH(A55,INDIRECT("'" & TEXT(EDATE(J55,-2),"mm-yyyy") & "'!A:A"),0)) -> 95 | D55: 105 | E55: =D55-C55 -> 10 | F55: 1182.6 | G55: =E55*F55 -> 11826 | H55: 5000 | I55: =E55*F55+H55 -> 16826 | J55: 45935 | K55: SI | L55: PENDIENTE | M55: =IF(L55="Pagado", I55, 0) -> 0 | P55: =IF(L55="NO APLICA",0, (I55-M55)) -> 16826
A56: 15 | B56: =Usuarios!B16 & " " & Usuarios!C16 & " " & Usuarios!D16 -> Sandra Mancilla Merino | C56: =INDEX(INDIRECT("'" & TEXT(EDATE(J56,-2),"mm-yyyy") & "'!D:D"), MATCH(A56,INDIRECT("'" & TEXT(EDATE(J56,-2),"mm-yyyy") & "'!A:A"),0)) -> 183 | D56: 191 | E56: =D56-C56 -> 8 | F56: 1182.6 | G56: =E56*F56 -> 9460.8 | H56: 5000 | I56: =E56*F56+H56 -> 14460.8 | J56: 45935 | K56: SI | L56: PENDIENTE | M56: =IF(L56="Pagado", I56, 0) -> 0 | P56: =IF(L56="NO APLICA",0, (I56-M56)) -> 14460.8
A57: 34 | B57: =Usuarios!B35 & " " & Usuarios!C35 & " " & Usuarios!D35 -> Vanesa Aguilar | C57: =INDEX(INDIRECT("'" & TEXT(EDATE(J57,-2),"mm-yyyy") & "'!D:D"), MATCH(A57,INDIRECT("'" & TEXT(EDATE(J57,-2),"mm-yyyy") & "'!A:A"),0)) -> 611 | D57: 626 | E57: =D57-C57 -> 15 | F57: 1182.6 | G57: =E57*F57 -> 17739 | H57: 5000 | I57: =E57*F57+H57 -> 22739 | J57: 45935 | K57: SI | L57: PENDIENTE | M57: =IF(L57="Pagado", I57, 0) -> 0 | P57: =IF(L57="NO APLICA",0, (I57-M57)) -> 22739
A58: 22 | B58: =Usuarios!B23 & " " & Usuarios!C23 & " " & Usuarios!D23 -> Yuri Millaquen | C58: =INDEX(INDIRECT("'" & TEXT(EDATE(J58,-2),"mm-yyyy") & "'!D:D"), MATCH(A58,INDIRECT("'" & TEXT(EDATE(J58,-2),"mm-yyyy") & "'!A:A"),0)) -> 209 | D58: 220 | E58: =D58-C58 -> 11 | F58: 1182.6 | G58: =E58*F58 -> 13008.6 | H58: 5000 | I58: =E58*F58+H58 -> 18008.6 | J58: 45935 | K58: SI | L58: PENDIENTE | M58: =IF(L58="Pagado", I58, 0) -> 0 | P58: =IF(L58="NO APLICA",0, (I58-M58)) -> 18008.6

Sheet 10-2025
A1: ID | B1: Nombre | C1: Lectura_Anterior | D1: Lectura_Actual | E1: Consumo_m3 | F1: Tarifa_m3 | G1: Subtotal_Consumo | H1: Cargo_Fijo | I1: Total_Factura | J1: Fecha_Lectura | K1: Lectura Tomada | L1: Estado_Pago | M1: Monto_Pagado | N1: Fecha_Pago | O1: Forma_Pago | P1: Saldo_Pendiente | Q1: comprobante_link
A2: 41 | B2: =Usuarios!B42 & " " & Usuarios!C42 & " " & Usuarios!D42 -> Astrid Gomez | C2: =INDEX(INDIRECT("'" & TEXT(EDATE(J2,-2),"mm-yyyy") & "'!D:D"), MATCH(A2,INDIRECT("'" & TEXT(EDATE(J2,-2),"mm-yyyy") & "'!A:A"),0)) -> 125 | D2: 131 | E2: =D2-C2 -> 6 | F2: 1182.6 | G2: =E2*F2 -> 7095.6 | H2: 5000 | I2: =E2*F2+H2 -> 12095.6 | J2: 45965 | K2: SI | L2: PENDIENTE | M2: =IF(L2="Pagado", I2, 0) -> 0 | P2: =IF(L2="NO APLICA",0, (I2-M2)) -> 12095.6
A3: 16 | B3: =Usuarios!B17 & " " & Usuarios!C17 & " " & Usuarios!D17 -> Carlos Agüero | C3: =INDEX(INDIRECT("'" & TEXT(EDATE(J3,-2),"mm-yyyy") & "'!D:D"), MATCH(A3,INDIRECT("'" & TEXT(EDATE(J3,-2),"mm-yyyy") & "'!A:A"),0)) -> 249 | E3: =D3-C3 -> -249 | F3: 1182.6 | G3: =E3*F3 -> -294467.4 | H3: 5000 | I3: =E3*F3+H3 -> -289467.4 | J3: 45966 | K3: SI | L3: PENDIENTE | M3: =IF(L3="Pagado", I3, 0) -> 0 | P3: =IF(L3="NO APLICA",0, (I3-M3)) -> -289467.4
A4: 13 | B4: =Usuarios!B14 & " " & Usuarios!C14 & " " & Usuarios!D14 -> Carlos Gamin | C4: =INDEX(INDIRECT("'" & TEXT(EDATE(J4,-2),"mm-yyyy") & "'!D:D"), MATCH(A4,INDIRECT("'" & TEXT(EDATE(J4,-2),"mm-yyyy") & "'!A:A"),0)) -> 237 | E4: =D4-C4 -> -237 | F4: 1182.6 | G4: =E4*F4 -> -280276.2 | H4: 5000 | I4: =E4*F4+H4 -> -275276.2 | J4: 45967 | K4: SI | L4: PENDIENTE | M4: =IF(L4="Pagado", I4, 0) -> 0 | P4: =IF(L4="NO APLICA",0, (I4-M4)) -> -275276.2
